{"trip_id":1840,"trip_token":null,"itineraries":[{"id":13667,"trip_part_id":3459,"mode_id":1,"service_id":3,"server_status":200,"server_message":null,"duration":2764,"walk_time":772,"transit_time":1990,"wait_time":2,"walk_distance":999.1786066998746,"transfers":1,"count":null,"legs":"---\n- startTime: 1435185709000\n  endTime: 1435185779000\n  departureDelay: 0\n  arrivalDelay: 0\n  realTime: false\n  isNonExactFrequency: \n  headway: \n  distance: 86.65877198238739\n  from:\n    name: West Market Street\n    stopId: \n    stopCode: \n    platformCode: \n    lon: -76.76788573568848\n    lat: 39.95297156023158\n    arrival: \n    departure: 1435185709000\n    orig: ''\n    zoneId: \n    stopIndex: \n  to:\n    name: W Market St At Diamond St Ib\n    stopId:\n      agencyId: '210'\n      id: '766447'\n    stopCode: \n    platformCode: \n    lon: -76.76878412778319\n    lat: 39.95293343815699\n    arrival: 1435185779000\n    departure: 1435185780000\n    orig: \n    zoneId: \n    stopIndex: \n  legGeometry:\n    points: aizrFhvpsMZlDQDA?\n    levels: \n    length: 4\n  transitLeg: false\n  mode: WALK\n  route: ''\n  agencyName: \n  agencyUrl: \n  agencyTimeZoneOffset: -14400000\n  routeColor: \n  routeType: \n  routeId: \n  routeTextColor: \n  interlineWithPreviousLeg: false\n  tripShortName: \n  tripBlockId: \n  headsign: \n  agencyId: \n  tripId: \n  serviceDate: \n  intermediateStops: \n  steps:\n  - distance: 75.84173737731417\n    relativeDirection: DEPART\n    streetName: West Market Street\n    absoluteDirection: WEST\n    exit: \n    stayOn: false\n    area: false\n    bogusName: false\n    lon: -76.76788573568848\n    lat: 39.95297156023158\n    alerts: \n    elevation: []\n  - distance: 10.817034605073214\n    relativeDirection: RIGHT\n    streetName: North Diamond Street\n    absoluteDirection: NORTH\n    exit: \n    stayOn: false\n    area: false\n    bogusName: false\n    lon: -76.7687589\n    lat: 39.9528381\n    alerts: \n    elevation: []\n  notes: \n  alerts: \n  routeShortName: \n  routeLongName: \n  boardRule: \n  alightRule: \n  rentedBike: false\n  duration: 70.0\n- startTime: 1435185780000\n  endTime: 1435186800000\n  departureDelay: 0\n  arrivalDelay: 0\n  realTime: false\n  isNonExactFrequency: \n  headway: \n  distance: 3402.844344321629\n  from:\n    name: W Market St At Diamond St Ib\n    stopId:\n      agencyId: '210'\n      id: '766447'\n    stopCode: \n    platformCode: \n    lon: -76.76870836193655\n    lat: 39.95295348683858\n    arrival: 1435185779000\n    departure: 1435185780000\n    orig: \n    zoneId: \n    stopIndex: 0\n  to:\n    name: Transfer Center\n    stopId:\n      agencyId: '210'\n      id: '765237'\n    stopCode: \n    platformCode: \n    lon: -76.731524\n    lat: 39.959945\n    arrival: 1435186800000\n    departure: 1435186800000\n    orig: \n    zoneId: '0'\n    stopIndex: 14\n  legGeometry:\n    points: \"{hzrFz{psMgGjA_AqLYkKdG[\\\\Co@cW[kLm@}R?CgAuFgA{FOaAMu@fCgAbCeAOs@y@wDQ{@iAuFUcAIc@iAkFiAwFOo@CKsAyG_CcLyAuGI_@qAiGG_@aAyEoBcJG[Kg@Q_AwB{JMg@@?eCuKu@A\"\n    levels: \n    length: 42\n  transitLeg: true\n  mode: BUS\n  route: 5W\n  agencyName: \n  agencyUrl: \n  agencyTimeZoneOffset: -14400000\n  routeColor: '800080'\n  routeType: 3\n  routeId: '1270'\n  routeTextColor: FFFFFF\n  interlineWithPreviousLeg: false\n  tripShortName: \n  tripBlockId: \n  headsign: 5w Downtown\n  agencyId: '210'\n  tripId: 54015A1024B1797\n  serviceDate: '20150624'\n  intermediateStops: \n  steps: []\n  notes: \n  alerts: \n  routeShortName: 5W\n  routeLongName: West York  West York Ind Park\n  boardRule: \n  alightRule: \n  rentedBike: false\n  duration: 1020.0\n- startTime: 1435186800000\n  endTime: 1435187770000\n  departureDelay: 0\n  arrivalDelay: 0\n  realTime: false\n  isNonExactFrequency: \n  headway: \n  distance: 4786.37466854201\n  from:\n    name: Transfer Center\n    stopId:\n      agencyId: '210'\n      id: '765237'\n    stopCode: \n    platformCode: \n    lon: -76.731524\n    lat: 39.959945\n    arrival: 1435186800000\n    departure: 1435186800000\n    orig: \n    zoneId: '0'\n    stopIndex: 0\n  to:\n    name: Camp Betty At Mt Rose Ave Ob\n    stopId:\n      agencyId: '210'\n      id: '765016'\n    stopCode: \n    platformCode: \n    lon: -76.682706\n    lat: 39.957379\n    arrival: 1435187770000\n    departure: 1435187771000\n    orig: \n    zoneId: '0'\n    stopIndex: 17\n  legGeometry:\n    points: ot{rFzsisMv@?mCyM??QcA}@_E_AmEy@aEOw@k@cCy@_E[cB[eB_AqEq@cDIa@dAg@`Ae@dBm@b@OzB{@f@UCuCMaFCgCAo@EsBM}EOgHAo@EuAKmEIaHCq@Ck@McFGgBIiBMeDGeBUsISiJ?SAa@O}IMoHC{@uAHwAJiBDCaDCeBA_AfHa@TA~FYpCGb@CxAIX_I\\oGFmBb@wLBsALeFDkENqBT}BHkG@kB?gDBeACwB?m@AwBOkELa@JELCXB~At@RN\n    levels: \n    length: 82\n  transitLeg: true\n  mode: BUS\n  route: 5E\n  agencyName: \n  agencyUrl: \n  agencyTimeZoneOffset: -14400000\n  routeColor: DB7093\n  routeType: 3\n  routeId: '1271'\n  routeTextColor: '000000'\n  interlineWithPreviousLeg: false\n  tripShortName: \n  tripBlockId: \n  headsign: Kmart Greensprings\n  agencyId: '210'\n  tripId: 54043A1024B1797\n  serviceDate: '20150624'\n  intermediateStops: \n  steps: []\n  notes: \n  alerts: \n  routeShortName: 5E\n  routeLongName: Haines Rd  Kmart  Greensprings\n  boardRule: \n  alightRule: \n  rentedBike: false\n  duration: 970.0\n- startTime: 1435187771000\n  endTime: 1435188473000\n  departureDelay: 0\n  arrivalDelay: 0\n  realTime: false\n  isNonExactFrequency: \n  headway: \n  distance: 912.4087335487009\n  from:\n    name: Camp Betty At Mt Rose Ave Ob\n    stopId:\n      agencyId: '210'\n      id: '765016'\n    stopCode: \n    platformCode: \n    lon: -76.68266362675077\n    lat: 39.95734572174098\n    arrival: 1435187770000\n    departure: 1435187771000\n    orig: \n    zoneId: \n    stopIndex: \n  to:\n    name: Erlen Drive\n    stopId: \n    stopCode: \n    platformCode: \n    lon: -76.67966600881111\n    lat: 39.96437079412677\n    arrival: 1435188473000\n    departure: \n    orig: ''\n    zoneId: \n    stopIndex: \n  legGeometry:\n    points: kd{rFta`sMSO_Bw@cAYSEaB_@qDu@OEmAUeCi@mCe@VcFaDUaDG_Gk@\n    levels: \n    length: 15\n  transitLeg: false\n  mode: WALK\n  route: ''\n  agencyName: \n  agencyUrl: \n  agencyTimeZoneOffset: -14400000\n  routeColor: \n  routeType: \n  routeId: \n  routeTextColor: \n  interlineWithPreviousLeg: false\n  tripShortName: \n  tripBlockId: \n  headsign: \n  agencyId: \n  tripId: \n  serviceDate: \n  intermediateStops: \n  steps:\n  - distance: 489.6573354632666\n    relativeDirection: DEPART\n    streetName: Haines Road\n    absoluteDirection: NORTHEAST\n    exit: \n    stayOn: false\n    area: false\n    bogusName: false\n    lon: -76.68266362675077\n    lat: 39.95734572174098\n    alerts: \n    elevation: []\n  - distance: 98.53025812689052\n    relativeDirection: RIGHT\n    streetName: Raleigh Drive\n    absoluteDirection: EAST\n    exit: \n    stayOn: false\n    area: false\n    bogusName: false\n    lon: -76.68118\n    lat: 39.9615941\n    alerts: \n    elevation: []\n  - distance: 324.22113995854363\n    relativeDirection: LEFT\n    streetName: Erlen Drive\n    absoluteDirection: NORTH\n    exit: \n    stayOn: false\n    area: false\n    bogusName: false\n    lon: -76.6800351\n    lat: 39.9614712\n    alerts: \n    elevation: []\n  notes: \n  alerts: \n  routeShortName: \n  routeLongName: \n  boardRule: \n  alightRule: \n  rentedBike: false\n  duration: 702.0\n","cost":"1.6","hidden":false,"created_at":"2015-06-15T16:14:10.471-04:00","updated_at":"2015-06-15T16:14:10.622-04:00","ride_count":null,"external_info":null,"match_score":-0.3,"missing_information":false,"accommodation_mismatch":false,"missing_information_text":null,"date_mismatch":false,"time_mismatch":false,"too_late":false,"missing_accommodations":"","cost_comments":null,"selected":null,"start_time":"2015-06-24T18:41:49.000-04:00","end_time":"2015-06-24T19:27:53.000-04:00","is_bookable":false,"booking_confirmation":null,"duration_estimated":false,"map_image":{"url":null},"too_early":false,"returned_mode_code":"mode_transit","order_xml":null,"discounts":null,"segment_index":0,"start_location":{"address_components":[{"long_name":"1829 W Market St","short_name":"1829 W Market St","types":["street_address"]},{"long_name":"York","short_name":"York","types":["locality","political"]},{"long_name":"Pennsylvania","short_name":"Pennsylvania","types":["administrative_area_level_1","political"]},{"long_name":"17404","short_name":"17404","types":["postal_code"]}],"formatted_address":"1829 W Market St, York, Pennsylvania 17404","geometry":{"location":{"lat":39.953249,"lng":-76.7679579}},"id":4319,"name":"1829 W Market St","scope":"user"},"end_location":{"address_components":[{"long_name":"701 Erlen Drive","short_name":"701 Erlen Drive","types":["street_address"]},{"long_name":"York","short_name":"York","types":["locality","political"]},{"long_name":"Pennsylvania","short_name":"Pennsylvania","types":["administrative_area_level_1","political"]},{"long_name":"17402","short_name":"17402","types":["postal_code"]}],"formatted_address":"701 Erlen Drive, York, Pennsylvania 17402","geometry":{"location":{"lat":39.964296,"lng":-76.678936}},"id":4320,"name":"East York Elementary School","scope":"user"},"prebooking_questions":[{"question":"Will you be traveling with an approved escort","choices":[true,false],"code":"assistant"},{"question":"How many children or family members will be traveling with you?","choices":[0,1,2],"code":"children"}],"bookable":false,"json_legs":[{"startTime":1435185709000,"endTime":1435185779000,"departureDelay":0,"arrivalDelay":0,"realTime":false,"isNonExactFrequency":null,"headway":null,"distance":86.65877198238739,"from":{"name":"West Market Street","stopId":null,"stopCode":null,"platformCode":null,"lon":-76.76788573568848,"lat":39.95297156023158,"arrival":null,"departure":1435185709000,"orig":"","zoneId":null,"stopIndex":null},"to":{"name":"W Market St At Diamond St Ib","stopId":{"agencyId":"210","id":"766447"},"stopCode":null,"platformCode":null,"lon":-76.76878412778319,"lat":39.95293343815699,"arrival":1435185779000,"departure":1435185780000,"orig":null,"zoneId":null,"stopIndex":null},"legGeometry":{"points":"aizrFhvpsMZlDQDA?","levels":null,"length":4},"transitLeg":false,"mode":"WALK","route":"","agencyName":null,"agencyUrl":null,"agencyTimeZoneOffset":-14400000,"routeColor":null,"routeType":null,"routeId":null,"routeTextColor":null,"interlineWithPreviousLeg":false,"tripShortName":null,"tripBlockId":null,"headsign":null,"agencyId":null,"tripId":null,"serviceDate":null,"intermediateStops":null,"steps":[{"distance":75.84173737731417,"relativeDirection":"DEPART","streetName":"West Market Street","absoluteDirection":"WEST","exit":null,"stayOn":false,"area":false,"bogusName":false,"lon":-76.76788573568848,"lat":39.95297156023158,"alerts":null,"elevation":[]},{"distance":10.817034605073214,"relativeDirection":"RIGHT","streetName":"North Diamond Street","absoluteDirection":"NORTH","exit":null,"stayOn":false,"area":false,"bogusName":false,"lon":-76.7687589,"lat":39.9528381,"alerts":null,"elevation":[]}],"notes":null,"alerts":null,"routeShortName":null,"routeLongName":null,"boardRule":null,"alightRule":null,"rentedBike":false,"duration":70.0},{"startTime":1435185780000,"endTime":1435186800000,"departureDelay":0,"arrivalDelay":0,"realTime":false,"isNonExactFrequency":null,"headway":null,"distance":3402.844344321629,"from":{"name":"W Market St At Diamond St Ib","stopId":{"agencyId":"210","id":"766447"},"stopCode":null,"platformCode":null,"lon":-76.76870836193655,"lat":39.95295348683858,"arrival":1435185779000,"departure":1435185780000,"orig":null,"zoneId":null,"stopIndex":0},"to":{"name":"Transfer Center","stopId":{"agencyId":"210","id":"765237"},"stopCode":null,"platformCode":null,"lon":-76.731524,"lat":39.959945,"arrival":1435186800000,"departure":1435186800000,"orig":null,"zoneId":"0","stopIndex":14},"legGeometry":{"points":"{hzrFz{psMgGjA_AqLYkKdG[\\Co@cW[kLm@}R?CgAuFgA{FOaAMu@fCgAbCeAOs@y@wDQ{@iAuFUcAIc@iAkFiAwFOo@CKsAyG_CcLyAuGI_@qAiGG_@aAyEoBcJG[Kg@Q_AwB{JMg@@?eCuKu@A","levels":null,"length":42},"transitLeg":true,"mode":"BUS","route":"5W","agencyName":null,"agencyUrl":null,"agencyTimeZoneOffset":-14400000,"routeColor":"800080","routeType":3,"routeId":"1270","routeTextColor":"FFFFFF","interlineWithPreviousLeg":false,"tripShortName":null,"tripBlockId":null,"headsign":"5w Downtown","agencyId":"210","tripId":"54015A1024B1797","serviceDate":"20150624","intermediateStops":null,"steps":[],"notes":null,"alerts":null,"routeShortName":"5W","routeLongName":"West York  West York Ind Park","boardRule":null,"alightRule":null,"rentedBike":false,"duration":1020.0},{"startTime":1435186800000,"endTime":1435187770000,"departureDelay":0,"arrivalDelay":0,"realTime":false,"isNonExactFrequency":null,"headway":null,"distance":4786.37466854201,"from":{"name":"Transfer Center","stopId":{"agencyId":"210","id":"765237"},"stopCode":null,"platformCode":null,"lon":-76.731524,"lat":39.959945,"arrival":1435186800000,"departure":1435186800000,"orig":null,"zoneId":"0","stopIndex":0},"to":{"name":"Camp Betty At Mt Rose Ave Ob","stopId":{"agencyId":"210","id":"765016"},"stopCode":null,"platformCode":null,"lon":-76.682706,"lat":39.957379,"arrival":1435187770000,"departure":1435187771000,"orig":null,"zoneId":"0","stopIndex":17},"legGeometry":{"points":"ot{rFzsisMv@?mCyM??QcA}@_E_AmEy@aEOw@k@cCy@_E[cB[eB_AqEq@cDIa@dAg@`Ae@dBm@b@OzB{@f@UCuCMaFCgCAo@EsBM}EOgHAo@EuAKmEIaHCq@Ck@McFGgBIiBMeDGeBUsISiJ?SAa@O}IMoHC{@uAHwAJiBDCaDCeBA_AfHa@TA~FYpCGb@CxAIX_I\\oGFmBb@wLBsALeFDkENqBT}BHkG@kB?gDBeACwB?m@AwBOkELa@JELCXB~At@RN","levels":null,"length":82},"transitLeg":true,"mode":"BUS","route":"5E","agencyName":null,"agencyUrl":null,"agencyTimeZoneOffset":-14400000,"routeColor":"DB7093","routeType":3,"routeId":"1271","routeTextColor":"000000","interlineWithPreviousLeg":false,"tripShortName":null,"tripBlockId":null,"headsign":"Kmart Greensprings","agencyId":"210","tripId":"54043A1024B1797","serviceDate":"20150624","intermediateStops":null,"steps":[],"notes":null,"alerts":null,"routeShortName":"5E","routeLongName":"Haines Rd  Kmart  Greensprings","boardRule":null,"alightRule":null,"rentedBike":false,"duration":970.0},{"startTime":1435187771000,"endTime":1435188473000,"departureDelay":0,"arrivalDelay":0,"realTime":false,"isNonExactFrequency":null,"headway":null,"distance":912.4087335487009,"from":{"name":"Camp Betty At Mt Rose Ave Ob","stopId":{"agencyId":"210","id":"765016"},"stopCode":null,"platformCode":null,"lon":-76.68266362675077,"lat":39.95734572174098,"arrival":1435187770000,"departure":1435187771000,"orig":null,"zoneId":null,"stopIndex":null},"to":{"name":"Erlen Drive","stopId":null,"stopCode":null,"platformCode":null,"lon":-76.67966600881111,"lat":39.96437079412677,"arrival":1435188473000,"departure":null,"orig":"","zoneId":null,"stopIndex":null},"legGeometry":{"points":"kd{rFta`sMSO_Bw@cAYSEaB_@qDu@OEmAUeCi@mCe@VcFaDUaDG_Gk@","levels":null,"length":15},"transitLeg":false,"mode":"WALK","route":"","agencyName":null,"agencyUrl":null,"agencyTimeZoneOffset":-14400000,"routeColor":null,"routeType":null,"routeId":null,"routeTextColor":null,"interlineWithPreviousLeg":false,"tripShortName":null,"tripBlockId":null,"headsign":null,"agencyId":null,"tripId":null,"serviceDate":null,"intermediateStops":null,"steps":[{"distance":489.6573354632666,"relativeDirection":"DEPART","streetName":"Haines Road","absoluteDirection":"NORTHEAST","exit":null,"stayOn":false,"area":false,"bogusName":false,"lon":-76.68266362675077,"lat":39.95734572174098,"alerts":null,"elevation":[]},{"distance":98.53025812689052,"relativeDirection":"RIGHT","streetName":"Raleigh Drive","absoluteDirection":"EAST","exit":null,"stayOn":false,"area":false,"bogusName":false,"lon":-76.68118,"lat":39.9615941,"alerts":null,"elevation":[]},{"distance":324.22113995854363,"relativeDirection":"LEFT","streetName":"Erlen Drive","absoluteDirection":"NORTH","exit":null,"stayOn":false,"area":false,"bogusName":false,"lon":-76.6800351,"lat":39.9614712,"alerts":null,"elevation":[]}],"notes":null,"alerts":null,"routeShortName":null,"routeLongName":null,"boardRule":null,"alightRule":null,"rentedBike":false,"duration":702.0}]},{"id":13668,"trip_part_id":3459,"mode_id":1,"service_id":3,"server_status":200,"server_message":null,"duration":3995,"walk_time":1851,"transit_time":2142,"wait_time":2,"walk_distance":2407.767724203174,"transfers":1,"count":null,"legs":"---\n- startTime: 1435184970000\n  endTime: 1435185839000\n  departureDelay: 0\n  arrivalDelay: 0\n  realTime: false\n  isNonExactFrequency: \n  headway: \n  distance: 1119.8433833244983\n  from:\n    name: West Market Street\n    stopId: \n    stopCode: \n    platformCode: \n    lon: -76.76788573568848\n    lat: 39.95297156023158\n    arrival: \n    departure: 1435184970000\n    orig: ''\n    zoneId: \n    stopIndex: \n  to:\n    name: Bannister At Clinton Ib\n    stopId:\n      agencyId: '210'\n      id: '765391'\n    stopCode: \n    platformCode: \n    lon: -76.7672033902395\n    lat: 39.96045950372425\n    arrival: 1435185839000\n    departure: 1435185840000\n    orig: \n    zoneId: \n    stopIndex: \n  legGeometry:\n    points: aizrFhvpsMZlDQDA?_C`@kCb@yAT{AVgBZ}AXS_BsAFsAFaDXyCLcCLuAcKaCF?MCaA\n    levels: \n    length: 20\n  transitLeg: false\n  mode: WALK\n  route: ''\n  agencyName: \n  agencyUrl: \n  agencyTimeZoneOffset: -14400000\n  routeColor: \n  routeType: \n  routeId: \n  routeTextColor: \n  interlineWithPreviousLeg: false\n  tripShortName: \n  tripBlockId: \n  headsign: \n  agencyId: \n  tripId: \n  serviceDate: \n  intermediateStops: \n  steps:\n  - distance: 75.84173737731417\n    relativeDirection: DEPART\n    streetName: West Market Street\n    absoluteDirection: WEST\n    exit: \n    stayOn: false\n    area: false\n    bogusName: false\n    lon: -76.76788573568848\n    lat: 39.95297156023158\n    alerts: \n    elevation: []\n  - distance: 378.8498457368015\n    relativeDirection: RIGHT\n    streetName: North Diamond Street\n    absoluteDirection: NORTH\n    exit: \n    stayOn: false\n    area: false\n    bogusName: false\n    lon: -76.7687589\n    lat: 39.9528381\n    alerts: \n    elevation: []\n  - distance: 42.46359232050136\n    relativeDirection: RIGHT\n    streetName: Filbert Street\n    absoluteDirection: EAST\n    exit: \n    stayOn: false\n    area: false\n    bogusName: false\n    lon: -76.7696335\n    lat: 39.9561785\n    alerts: \n    elevation: []\n  - distance: 344.37320490378784\n    relativeDirection: LEFT\n    streetName: North Diamond Street\n    absoluteDirection: NORTH\n    exit: \n    stayOn: false\n    area: false\n    bogusName: false\n    lon: -76.7691508\n    lat: 39.956273\n    alerts: \n    elevation: []\n  - distance: 243.9865048267162\n    relativeDirection: RIGHT\n    streetName: service road\n    absoluteDirection: EAST\n    exit: \n    stayOn: false\n    area: false\n    bogusName: true\n    lon: -76.7695052\n    lat: 39.9593576\n    alerts: \n    elevation: []\n  - distance: 34.328498159377375\n    relativeDirection: RIGHT\n    streetName: Bannister Street\n    absoluteDirection: EAST\n    exit: \n    stayOn: false\n    area: false\n    bogusName: false\n    lon: -76.7676046\n    lat: 39.9604323\n    alerts: \n    elevation: []\n  notes: \n  alerts: \n  routeShortName: \n  routeLongName: \n  boardRule: \n  alightRule: \n  rentedBike: false\n  duration: 869.0\n- startTime: 1435185840000\n  endTime: 1435186800000\n  departureDelay: 0\n  arrivalDelay: 0\n  realTime: false\n  isNonExactFrequency: \n  headway: \n  distance: 3185.898405989211\n  from:\n    name: Bannister At Clinton Ib\n    stopId:\n      agencyId: '210'\n      id: '765391'\n    stopCode: \n    platformCode: \n    lon: -76.767202\n    lat: 39.960439\n    arrival: 1435185839000\n    departure: 1435185840000\n    orig: \n    zoneId: '0'\n    stopIndex: 6\n  to:\n    name: Transfer Center\n    stopId:\n      agencyId: '210'\n      id: '765237'\n    stopCode: \n    platformCode: \n    lon: -76.731524\n    lat: 39.959945\n    arrival: 1435186800000\n    departure: 1435186800000\n    orig: \n    zoneId: '0'\n    stopIndex: 16\n  legGeometry:\n    points: yw{rF`rpsMU_IUeJEuBOmGSgKSiHbCaLj@eCh@eCJa@`@{An@mCr@oCh@qBj@_CBKXoAZcAj@iCn@oCv@uCPi@DSh@_Cd@eBf@uBd@gCo@_DScAoBcJUcAcD{NOw@qDmQSaAyBwKa@cBCB}C_OvCgAZxAvAC\n    levels: \n    length: 43\n  transitLeg: true\n  mode: BUS\n  route: 1W\n  agencyName: \n  agencyUrl: \n  agencyTimeZoneOffset: -14400000\n  routeColor: FF0000\n  routeType: 3\n  routeId: '1264'\n  routeTextColor: '000000'\n  interlineWithPreviousLeg: false\n  tripShortName: \n  tripBlockId: \n  headsign: 1w Downtown\n  agencyId: '210'\n  tripId: 53779A1024B1797\n  serviceDate: '20150624'\n  intermediateStops: \n  steps: []\n  notes: \n  alerts: \n  routeShortName: 1W\n  routeLongName: West Manchester Mall\n  boardRule: \n  alightRule: \n  rentedBike: false\n  duration: 960.0\n- startTime: 1435186800000\n  endTime: 1435187982000\n  departureDelay: 0\n  arrivalDelay: 0\n  realTime: false\n  isNonExactFrequency: \n  headway: \n  distance: 4597.981331821435\n  from:\n    name: Transfer Center\n    stopId:\n      agencyId: '210'\n      id: '765237'\n    stopCode: \n    platformCode: \n    lon: -76.731524\n    lat: 39.959945\n    arrival: 1435186800000\n    departure: 1435186800000\n    orig: \n    zoneId: '0'\n    stopIndex: 0\n  to:\n    name: E Market At Royal Ob\n    stopId:\n      agencyId: '210'\n      id: '765013'\n    stopCode: \n    platformCode: \n    lon: -76.681946\n    lat: 39.973889\n    arrival: 1435187982000\n    departure: 1435187983000\n    orig: \n    zoneId: '0'\n    stopIndex: 17\n  legGeometry:\n    points: ot{rFzsisMv@?mCyM??QcA}@_E_AmEy@aE{@{D_C`A}Ap@w@ZyBaKSy@kB{I_BaJAEa@qBUkAUkAw@sDsCkIs@uBUs@Oe@{@eCq@qBa@cA_CsHWs@oD_KUo@wC_IMa@AEoCeIMa@Qk@qBmGcAmCk@uBEy@KcBEgAEm@[mFa@mH??k@sJBa@@OK@CqBSsDOyCEy@IaCOsBIiA?MG_BG{A?KMgEKoEQqEAYMmDQgECm@K}CKuECg@GeD]mFIaA\n    levels: \n    length: 76\n  transitLeg: true\n  mode: BUS\n  route: 1E\n  agencyName: \n  agencyUrl: \n  agencyTimeZoneOffset: -14400000\n  routeColor: FF0000\n  routeType: 3\n  routeId: '1265'\n  routeTextColor: '000000'\n  interlineWithPreviousLeg: false\n  tripShortName: \n  tripBlockId: \n  headsign: East York\n  agencyId: '210'\n  tripId: 53813A1024B1797\n  serviceDate: '20150624'\n  intermediateStops: \n  steps: []\n  notes: \n  alerts: \n  routeShortName: 1E\n  routeLongName: East York\n  boardRule: \n  alightRule: \n  rentedBike: false\n  duration: 1182.0\n- startTime: 1435187983000\n  endTime: 1435188965000\n  departureDelay: 0\n  arrivalDelay: 0\n  realTime: false\n  isNonExactFrequency: \n  headway: \n  distance: 1287.6298109345778\n  from:\n    name: E Market At Royal Ob\n    stopId:\n      agencyId: '210'\n      id: '765013'\n    stopCode: \n    platformCode: \n    lon: -76.6819547471471\n    lat: 39.9739597747891\n    arrival: 1435187982000\n    departure: 1435187983000\n    orig: \n    zoneId: \n    stopIndex: \n  to:\n    name: Erlen Drive\n    stopId: \n    stopCode: \n    platformCode: \n    lon: -76.67966600881111\n    lat: 39.96437079412677\n    arrival: 1435188965000\n    departure: \n    orig: ''\n    zoneId: \n    stopIndex: \n  legGeometry:\n    points: el~rFf}_sMF`AbJqAbKy@vHArHh@jHf@VeHRkEfE`@\n    levels: \n    length: 10\n  transitLeg: false\n  mode: WALK\n  route: ''\n  agencyName: \n  agencyUrl: \n  agencyTimeZoneOffset: -14400000\n  routeColor: \n  routeType: \n  routeId: \n  routeTextColor: \n  interlineWithPreviousLeg: false\n  tripShortName: \n  tripBlockId: \n  headsign: \n  agencyId: \n  tripId: \n  serviceDate: \n  intermediateStops: \n  steps:\n  - distance: 28.755737153530887\n    relativeDirection: DEPART\n    streetName: East Market Street\n    absoluteDirection: WEST\n    exit: \n    stayOn: false\n    area: false\n    bogusName: false\n    lon: -76.6819547471471\n    lat: 39.9739597747891\n    alerts: \n    elevation: []\n  - distance: 931.5273083562267\n    relativeDirection: LEFT\n    streetName: South Royal Street\n    absoluteDirection: SOUTH\n    exit: \n    stayOn: false\n    area: false\n    bogusName: false\n    lon: -76.6822879\n    lat: 39.9739186\n    alerts: \n    elevation: []\n  - distance: 214.26441832231393\n    relativeDirection: LEFT\n    streetName: 7th Avenue\n    absoluteDirection: EAST\n    exit: \n    stayOn: false\n    area: false\n    bogusName: false\n    lon: -76.681988\n    lat: 39.965598\n    alerts: \n    elevation: []\n  - distance: 113.08234710250632\n    relativeDirection: RIGHT\n    streetName: Erlen Drive\n    absoluteDirection: SOUTH\n    exit: \n    stayOn: false\n    area: false\n    bogusName: false\n    lon: -76.6794902\n    lat: 39.9653788\n    alerts: \n    elevation: []\n  notes: \n  alerts: \n  routeShortName: \n  routeLongName: \n  boardRule: \n  alightRule: \n  rentedBike: false\n  duration: 982.0\n","cost":"1.6","hidden":false,"created_at":"2015-06-15T16:14:10.513-04:00","updated_at":"2015-06-15T16:14:10.626-04:00","ride_count":null,"external_info":null,"match_score":-0.19999999999999998,"missing_information":false,"accommodation_mismatch":false,"missing_information_text":null,"date_mismatch":false,"time_mismatch":false,"too_late":false,"missing_accommodations":"","cost_comments":null,"selected":null,"start_time":"2015-06-24T18:29:30.000-04:00","end_time":"2015-06-24T19:36:05.000-04:00","is_bookable":false,"booking_confirmation":null,"duration_estimated":false,"map_image":{"url":null},"too_early":false,"returned_mode_code":"mode_transit","order_xml":null,"discounts":null,"segment_index":0,"start_location":{"address_components":[{"long_name":"1829 W Market St","short_name":"1829 W Market St","types":["street_address"]},{"long_name":"York","short_name":"York","types":["locality","political"]},{"long_name":"Pennsylvania","short_name":"Pennsylvania","types":["administrative_area_level_1","political"]},{"long_name":"17404","short_name":"17404","types":["postal_code"]}],"formatted_address":"1829 W Market St, York, Pennsylvania 17404","geometry":{"location":{"lat":39.953249,"lng":-76.7679579}},"id":4319,"name":"1829 W Market St","scope":"user"},"end_location":{"address_components":[{"long_name":"701 Erlen Drive","short_name":"701 Erlen Drive","types":["street_address"]},{"long_name":"York","short_name":"York","types":["locality","political"]},{"long_name":"Pennsylvania","short_name":"Pennsylvania","types":["administrative_area_level_1","political"]},{"long_name":"17402","short_name":"17402","types":["postal_code"]}],"formatted_address":"701 Erlen Drive, York, Pennsylvania 17402","geometry":{"location":{"lat":39.964296,"lng":-76.678936}},"id":4320,"name":"East York Elementary School","scope":"user"},"prebooking_questions":[{"question":"Will you be traveling with an approved escort","choices":[true,false],"code":"assistant"},{"question":"How many children or family members will be traveling with you?","choices":[0,1,2],"code":"children"}],"bookable":false,"json_legs":[{"startTime":1435184970000,"endTime":1435185839000,"departureDelay":0,"arrivalDelay":0,"realTime":false,"isNonExactFrequency":null,"headway":null,"distance":1119.8433833244983,"from":{"name":"West Market Street","stopId":null,"stopCode":null,"platformCode":null,"lon":-76.76788573568848,"lat":39.95297156023158,"arrival":null,"departure":1435184970000,"orig":"","zoneId":null,"stopIndex":null},"to":{"name":"Bannister At Clinton Ib","stopId":{"agencyId":"210","id":"765391"},"stopCode":null,"platformCode":null,"lon":-76.7672033902395,"lat":39.96045950372425,"arrival":1435185839000,"departure":1435185840000,"orig":null,"zoneId":null,"stopIndex":null},"legGeometry":{"points":"aizrFhvpsMZlDQDA?_C`@kCb@yAT{AVgBZ}AXS_BsAFsAFaDXyCLcCLuAcKaCF?MCaA","levels":null,"length":20},"transitLeg":false,"mode":"WALK","route":"","agencyName":null,"agencyUrl":null,"agencyTimeZoneOffset":-14400000,"routeColor":null,"routeType":null,"routeId":null,"routeTextColor":null,"interlineWithPreviousLeg":false,"tripShortName":null,"tripBlockId":null,"headsign":null,"agencyId":null,"tripId":null,"serviceDate":null,"intermediateStops":null,"steps":[{"distance":75.84173737731417,"relativeDirection":"DEPART","streetName":"West Market Street","absoluteDirection":"WEST","exit":null,"stayOn":false,"area":false,"bogusName":false,"lon":-76.76788573568848,"lat":39.95297156023158,"alerts":null,"elevation":[]},{"distance":378.8498457368015,"relativeDirection":"RIGHT","streetName":"North Diamond Street","absoluteDirection":"NORTH","exit":null,"stayOn":false,"area":false,"bogusName":false,"lon":-76.7687589,"lat":39.9528381,"alerts":null,"elevation":[]},{"distance":42.46359232050136,"relativeDirection":"RIGHT","streetName":"Filbert Street","absoluteDirection":"EAST","exit":null,"stayOn":false,"area":false,"bogusName":false,"lon":-76.7696335,"lat":39.9561785,"alerts":null,"elevation":[]},{"distance":344.37320490378784,"relativeDirection":"LEFT","streetName":"North Diamond Street","absoluteDirection":"NORTH","exit":null,"stayOn":false,"area":false,"bogusName":false,"lon":-76.7691508,"lat":39.956273,"alerts":null,"elevation":[]},{"distance":243.9865048267162,"relativeDirection":"RIGHT","streetName":"service road","absoluteDirection":"EAST","exit":null,"stayOn":false,"area":false,"bogusName":true,"lon":-76.7695052,"lat":39.9593576,"alerts":null,"elevation":[]},{"distance":34.328498159377375,"relativeDirection":"RIGHT","streetName":"Bannister Street","absoluteDirection":"EAST","exit":null,"stayOn":false,"area":false,"bogusName":false,"lon":-76.7676046,"lat":39.9604323,"alerts":null,"elevation":[]}],"notes":null,"alerts":null,"routeShortName":null,"routeLongName":null,"boardRule":null,"alightRule":null,"rentedBike":false,"duration":869.0},{"startTime":1435185840000,"endTime":1435186800000,"departureDelay":0,"arrivalDelay":0,"realTime":false,"isNonExactFrequency":null,"headway":null,"distance":3185.898405989211,"from":{"name":"Bannister At Clinton Ib","stopId":{"agencyId":"210","id":"765391"},"stopCode":null,"platformCode":null,"lon":-76.767202,"lat":39.960439,"arrival":1435185839000,"departure":1435185840000,"orig":null,"zoneId":"0","stopIndex":6},"to":{"name":"Transfer Center","stopId":{"agencyId":"210","id":"765237"},"stopCode":null,"platformCode":null,"lon":-76.731524,"lat":39.959945,"arrival":1435186800000,"departure":1435186800000,"orig":null,"zoneId":"0","stopIndex":16},"legGeometry":{"points":"yw{rF`rpsMU_IUeJEuBOmGSgKSiHbCaLj@eCh@eCJa@`@{An@mCr@oCh@qBj@_CBKXoAZcAj@iCn@oCv@uCPi@DSh@_Cd@eBf@uBd@gCo@_DScAoBcJUcAcD{NOw@qDmQSaAyBwKa@cBCB}C_OvCgAZxAvAC","levels":null,"length":43},"transitLeg":true,"mode":"BUS","route":"1W","agencyName":null,"agencyUrl":null,"agencyTimeZoneOffset":-14400000,"routeColor":"FF0000","routeType":3,"routeId":"1264","routeTextColor":"000000","interlineWithPreviousLeg":false,"tripShortName":null,"tripBlockId":null,"headsign":"1w Downtown","agencyId":"210","tripId":"53779A1024B1797","serviceDate":"20150624","intermediateStops":null,"steps":[],"notes":null,"alerts":null,"routeShortName":"1W","routeLongName":"West Manchester Mall","boardRule":null,"alightRule":null,"rentedBike":false,"duration":960.0},{"startTime":1435186800000,"endTime":1435187982000,"departureDelay":0,"arrivalDelay":0,"realTime":false,"isNonExactFrequency":null,"headway":null,"distance":4597.981331821435,"from":{"name":"Transfer Center","stopId":{"agencyId":"210","id":"765237"},"stopCode":null,"platformCode":null,"lon":-76.731524,"lat":39.959945,"arrival":1435186800000,"departure":1435186800000,"orig":null,"zoneId":"0","stopIndex":0},"to":{"name":"E Market At Royal Ob","stopId":{"agencyId":"210","id":"765013"},"stopCode":null,"platformCode":null,"lon":-76.681946,"lat":39.973889,"arrival":1435187982000,"departure":1435187983000,"orig":null,"zoneId":"0","stopIndex":17},"legGeometry":{"points":"ot{rFzsisMv@?mCyM??QcA}@_E_AmEy@aE{@{D_C`A}Ap@w@ZyBaKSy@kB{I_BaJAEa@qBUkAUkAw@sDsCkIs@uBUs@Oe@{@eCq@qBa@cA_CsHWs@oD_KUo@wC_IMa@AEoCeIMa@Qk@qBmGcAmCk@uBEy@KcBEgAEm@[mFa@mH??k@sJBa@@OK@CqBSsDOyCEy@IaCOsBIiA?MG_BG{A?KMgEKoEQqEAYMmDQgECm@K}CKuECg@GeD]mFIaA","levels":null,"length":76},"transitLeg":true,"mode":"BUS","route":"1E","agencyName":null,"agencyUrl":null,"agencyTimeZoneOffset":-14400000,"routeColor":"FF0000","routeType":3,"routeId":"1265","routeTextColor":"000000","interlineWithPreviousLeg":false,"tripShortName":null,"tripBlockId":null,"headsign":"East York","agencyId":"210","tripId":"53813A1024B1797","serviceDate":"20150624","intermediateStops":null,"steps":[],"notes":null,"alerts":null,"routeShortName":"1E","routeLongName":"East York","boardRule":null,"alightRule":null,"rentedBike":false,"duration":1182.0},{"startTime":1435187983000,"endTime":1435188965000,"departureDelay":0,"arrivalDelay":0,"realTime":false,"isNonExactFrequency":null,"headway":null,"distance":1287.6298109345778,"from":{"name":"E Market At Royal Ob","stopId":{"agencyId":"210","id":"765013"},"stopCode":null,"platformCode":null,"lon":-76.6819547471471,"lat":39.9739597747891,"arrival":1435187982000,"departure":1435187983000,"orig":null,"zoneId":null,"stopIndex":null},"to":{"name":"Erlen Drive","stopId":null,"stopCode":null,"platformCode":null,"lon":-76.67966600881111,"lat":39.96437079412677,"arrival":1435188965000,"departure":null,"orig":"","zoneId":null,"stopIndex":null},"legGeometry":{"points":"el~rFf}_sMF`AbJqAbKy@vHArHh@jHf@VeHRkEfE`@","levels":null,"length":10},"transitLeg":false,"mode":"WALK","route":"","agencyName":null,"agencyUrl":null,"agencyTimeZoneOffset":-14400000,"routeColor":null,"routeType":null,"routeId":null,"routeTextColor":null,"interlineWithPreviousLeg":false,"tripShortName":null,"tripBlockId":null,"headsign":null,"agencyId":null,"tripId":null,"serviceDate":null,"intermediateStops":null,"steps":[{"distance":28.755737153530887,"relativeDirection":"DEPART","streetName":"East Market Street","absoluteDirection":"WEST","exit":null,"stayOn":false,"area":false,"bogusName":false,"lon":-76.6819547471471,"lat":39.9739597747891,"alerts":null,"elevation":[]},{"distance":931.5273083562267,"relativeDirection":"LEFT","streetName":"South Royal Street","absoluteDirection":"SOUTH","exit":null,"stayOn":false,"area":false,"bogusName":false,"lon":-76.6822879,"lat":39.9739186,"alerts":null,"elevation":[]},{"distance":214.26441832231393,"relativeDirection":"LEFT","streetName":"7th Avenue","absoluteDirection":"EAST","exit":null,"stayOn":false,"area":false,"bogusName":false,"lon":-76.681988,"lat":39.965598,"alerts":null,"elevation":[]},{"distance":113.08234710250632,"relativeDirection":"RIGHT","streetName":"Erlen Drive","absoluteDirection":"SOUTH","exit":null,"stayOn":false,"area":false,"bogusName":false,"lon":-76.6794902,"lat":39.9653788,"alerts":null,"elevation":[]}],"notes":null,"alerts":null,"routeShortName":null,"routeLongName":null,"boardRule":null,"alightRule":null,"rentedBike":false,"duration":982.0}]},{"id":13669,"trip_part_id":3459,"mode_id":1,"service_id":3,"server_status":200,"server_message":null,"duration":3256,"walk_time":1052,"transit_time":2202,"wait_time":2,"walk_distance":1374.4298827255896,"transfers":1,"count":null,"legs":"---\n- startTime: 1435187509000\n  endTime: 1435187579000\n  departureDelay: 0\n  arrivalDelay: 0\n  realTime: false\n  isNonExactFrequency: \n  headway: \n  distance: 86.65877198238739\n  from:\n    name: West Market Street\n    stopId: \n    stopCode: \n    platformCode: \n    lon: -76.76788573568848\n    lat: 39.95297156023158\n    arrival: \n    departure: 1435187509000\n    orig: ''\n    zoneId: \n    stopIndex: \n  to:\n    name: W Market St At Diamond St Ib\n    stopId:\n      agencyId: '210'\n      id: '766447'\n    stopCode: \n    platformCode: \n    lon: -76.76878412778319\n    lat: 39.95293343815699\n    arrival: 1435187579000\n    departure: 1435187580000\n    orig: \n    zoneId: \n    stopIndex: \n  legGeometry:\n    points: aizrFhvpsMZlDQDA?\n    levels: \n    length: 4\n  transitLeg: false\n  mode: WALK\n  route: ''\n  agencyName: \n  agencyUrl: \n  agencyTimeZoneOffset: -14400000\n  routeColor: \n  routeType: \n  routeId: \n  routeTextColor: \n  interlineWithPreviousLeg: false\n  tripShortName: \n  tripBlockId: \n  headsign: \n  agencyId: \n  tripId: \n  serviceDate: \n  intermediateStops: \n  steps:\n  - distance: 75.84173737731417\n    relativeDirection: DEPART\n    streetName: West Market Street\n    absoluteDirection: WEST\n    exit: \n    stayOn: false\n    area: false\n    bogusName: false\n    lon: -76.76788573568848\n    lat: 39.95297156023158\n    alerts: \n    elevation: []\n  - distance: 10.817034605073214\n    relativeDirection: RIGHT\n    streetName: North Diamond Street\n    absoluteDirection: NORTH\n    exit: \n    stayOn: false\n    area: false\n    bogusName: false\n    lon: -76.7687589\n    lat: 39.9528381\n    alerts: \n    elevation: []\n  notes: \n  alerts: \n  routeShortName: \n  routeLongName: \n  boardRule: \n  alightRule: \n  rentedBike: false\n  duration: 70.0\n- startTime: 1435187580000\n  endTime: 1435188600000\n  departureDelay: 0\n  arrivalDelay: 0\n  realTime: false\n  isNonExactFrequency: \n  headway: \n  distance: 3402.844344321629\n  from:\n    name: W Market St At Diamond St Ib\n    stopId:\n      agencyId: '210'\n      id: '766447'\n    stopCode: \n    platformCode: \n    lon: -76.76870836193655\n    lat: 39.95295348683858\n    arrival: 1435187579000\n    departure: 1435187580000\n    orig: \n    zoneId: \n    stopIndex: 0\n  to:\n    name: Transfer Center\n    stopId:\n      agencyId: '210'\n      id: '765237'\n    stopCode: \n    platformCode: \n    lon: -76.731524\n    lat: 39.959945\n    arrival: 1435188600000\n    departure: 1435188600000\n    orig: \n    zoneId: '0'\n    stopIndex: 14\n  legGeometry:\n    points: \"{hzrFz{psMgGjA_AqLYkKdG[\\\\Co@cW[kLm@}R?CgAuFgA{FOaAMu@fCgAbCeAOs@y@wDQ{@iAuFUcAIc@iAkFiAwFOo@CKsAyG_CcLyAuGI_@qAiGG_@aAyEoBcJG[Kg@Q_AwB{JMg@@?eCuKu@A\"\n    levels: \n    length: 42\n  transitLeg: true\n  mode: BUS\n  route: 5W\n  agencyName: \n  agencyUrl: \n  agencyTimeZoneOffset: -14400000\n  routeColor: '800080'\n  routeType: 3\n  routeId: '1270'\n  routeTextColor: FFFFFF\n  interlineWithPreviousLeg: false\n  tripShortName: \n  tripBlockId: \n  headsign: 5w Downtown\n  agencyId: '210'\n  tripId: 54016A1024B1797\n  serviceDate: '20150624'\n  intermediateStops: \n  steps: []\n  notes: \n  alerts: \n  routeShortName: 5W\n  routeLongName: West York  West York Ind Park\n  boardRule: \n  alightRule: \n  rentedBike: false\n  duration: 1020.0\n- startTime: 1435188600000\n  endTime: 1435189782000\n  departureDelay: 0\n  arrivalDelay: 0\n  realTime: false\n  isNonExactFrequency: \n  headway: \n  distance: 4597.981331821435\n  from:\n    name: Transfer Center\n    stopId:\n      agencyId: '210'\n      id: '765237'\n    stopCode: \n    platformCode: \n    lon: -76.731524\n    lat: 39.959945\n    arrival: 1435188600000\n    departure: 1435188600000\n    orig: \n    zoneId: '0'\n    stopIndex: 0\n  to:\n    name: E Market At Royal Ob\n    stopId:\n      agencyId: '210'\n      id: '765013'\n    stopCode: \n    platformCode: \n    lon: -76.681946\n    lat: 39.973889\n    arrival: 1435189782000\n    departure: 1435189783000\n    orig: \n    zoneId: '0'\n    stopIndex: 17\n  legGeometry:\n    points: ot{rFzsisMv@?mCyM??QcA}@_E_AmEy@aE{@{D_C`A}Ap@w@ZyBaKSy@kB{I_BaJAEa@qBUkAUkAw@sDsCkIs@uBUs@Oe@{@eCq@qBa@cA_CsHWs@oD_KUo@wC_IMa@AEoCeIMa@Qk@qBmGcAmCk@uBEy@KcBEgAEm@[mFa@mH??k@sJBa@@OK@CqBSsDOyCEy@IaCOsBIiA?MG_BG{A?KMgEKoEQqEAYMmDQgECm@K}CKuECg@GeD]mFIaA\n    levels: \n    length: 76\n  transitLeg: true\n  mode: BUS\n  route: 1E\n  agencyName: \n  agencyUrl: \n  agencyTimeZoneOffset: -14400000\n  routeColor: FF0000\n  routeType: 3\n  routeId: '1265'\n  routeTextColor: '000000'\n  interlineWithPreviousLeg: false\n  tripShortName: \n  tripBlockId: \n  headsign: East York Via Market\n  agencyId: '210'\n  tripId: 53814A1024B1797\n  serviceDate: '20150624'\n  intermediateStops: \n  steps: []\n  notes: \n  alerts: \n  routeShortName: 1E\n  routeLongName: East York\n  boardRule: \n  alightRule: \n  rentedBike: false\n  duration: 1182.0\n- startTime: 1435189783000\n  endTime: 1435190765000\n  departureDelay: 0\n  arrivalDelay: 0\n  realTime: false\n  isNonExactFrequency: \n  headway: \n  distance: 1287.6298109345778\n  from:\n    name: E Market At Royal Ob\n    stopId:\n      agencyId: '210'\n      id: '765013'\n    stopCode: \n    platformCode: \n    lon: -76.6819547471471\n    lat: 39.9739597747891\n    arrival: 1435189782000\n    departure: 1435189783000\n    orig: \n    zoneId: \n    stopIndex: \n  to:\n    name: Erlen Drive\n    stopId: \n    stopCode: \n    platformCode: \n    lon: -76.67966600881111\n    lat: 39.96437079412677\n    arrival: 1435190765000\n    departure: \n    orig: ''\n    zoneId: \n    stopIndex: \n  legGeometry:\n    points: el~rFf}_sMF`AbJqAbKy@vHArHh@jHf@VeHRkEfE`@\n    levels: \n    length: 10\n  transitLeg: false\n  mode: WALK\n  route: ''\n  agencyName: \n  agencyUrl: \n  agencyTimeZoneOffset: -14400000\n  routeColor: \n  routeType: \n  routeId: \n  routeTextColor: \n  interlineWithPreviousLeg: false\n  tripShortName: \n  tripBlockId: \n  headsign: \n  agencyId: \n  tripId: \n  serviceDate: \n  intermediateStops: \n  steps:\n  - distance: 28.755737153530887\n    relativeDirection: DEPART\n    streetName: East Market Street\n    absoluteDirection: WEST\n    exit: \n    stayOn: false\n    area: false\n    bogusName: false\n    lon: -76.6819547471471\n    lat: 39.9739597747891\n    alerts: \n    elevation: []\n  - distance: 931.5273083562267\n    relativeDirection: LEFT\n    streetName: South Royal Street\n    absoluteDirection: SOUTH\n    exit: \n    stayOn: false\n    area: false\n    bogusName: false\n    lon: -76.6822879\n    lat: 39.9739186\n    alerts: \n    elevation: []\n  - distance: 214.26441832231393\n    relativeDirection: LEFT\n    streetName: 7th Avenue\n    absoluteDirection: EAST\n    exit: \n    stayOn: false\n    area: false\n    bogusName: false\n    lon: -76.681988\n    lat: 39.965598\n    alerts: \n    elevation: []\n  - distance: 113.08234710250632\n    relativeDirection: RIGHT\n    streetName: Erlen Drive\n    absoluteDirection: SOUTH\n    exit: \n    stayOn: false\n    area: false\n    bogusName: false\n    lon: -76.6794902\n    lat: 39.9653788\n    alerts: \n    elevation: []\n  notes: \n  alerts: \n  routeShortName: \n  routeLongName: \n  boardRule: \n  alightRule: \n  rentedBike: false\n  duration: 982.0\n","cost":"1.6","hidden":false,"created_at":"2015-06-15T16:14:10.546-04:00","updated_at":"2015-06-15T16:14:10.630-04:00","ride_count":null,"external_info":null,"match_score":-0.09999999999999998,"missing_information":false,"accommodation_mismatch":false,"missing_information_text":null,"date_mismatch":false,"time_mismatch":false,"too_late":false,"missing_accommodations":"","cost_comments":null,"selected":null,"start_time":"2015-06-24T19:11:49.000-04:00","end_time":"2015-06-24T20:06:05.000-04:00","is_bookable":false,"booking_confirmation":null,"duration_estimated":false,"map_image":{"url":null},"too_early":false,"returned_mode_code":"mode_transit","order_xml":null,"discounts":null,"segment_index":0,"start_location":{"address_components":[{"long_name":"1829 W Market St","short_name":"1829 W Market St","types":["street_address"]},{"long_name":"York","short_name":"York","types":["locality","political"]},{"long_name":"Pennsylvania","short_name":"Pennsylvania","types":["administrative_area_level_1","political"]},{"long_name":"17404","short_name":"17404","types":["postal_code"]}],"formatted_address":"1829 W Market St, York, Pennsylvania 17404","geometry":{"location":{"lat":39.953249,"lng":-76.7679579}},"id":4319,"name":"1829 W Market St","scope":"user"},"end_location":{"address_components":[{"long_name":"701 Erlen Drive","short_name":"701 Erlen Drive","types":["street_address"]},{"long_name":"York","short_name":"York","types":["locality","political"]},{"long_name":"Pennsylvania","short_name":"Pennsylvania","types":["administrative_area_level_1","political"]},{"long_name":"17402","short_name":"17402","types":["postal_code"]}],"formatted_address":"701 Erlen Drive, York, Pennsylvania 17402","geometry":{"location":{"lat":39.964296,"lng":-76.678936}},"id":4320,"name":"East York Elementary School","scope":"user"},"prebooking_questions":[{"question":"Will you be traveling with an approved escort","choices":[true,false],"code":"assistant"},{"question":"How many children or family members will be traveling with you?","choices":[0,1,2],"code":"children"}],"bookable":false,"json_legs":[{"startTime":1435187509000,"endTime":1435187579000,"departureDelay":0,"arrivalDelay":0,"realTime":false,"isNonExactFrequency":null,"headway":null,"distance":86.65877198238739,"from":{"name":"West Market Street","stopId":null,"stopCode":null,"platformCode":null,"lon":-76.76788573568848,"lat":39.95297156023158,"arrival":null,"departure":1435187509000,"orig":"","zoneId":null,"stopIndex":null},"to":{"name":"W Market St At Diamond St Ib","stopId":{"agencyId":"210","id":"766447"},"stopCode":null,"platformCode":null,"lon":-76.76878412778319,"lat":39.95293343815699,"arrival":1435187579000,"departure":1435187580000,"orig":null,"zoneId":null,"stopIndex":null},"legGeometry":{"points":"aizrFhvpsMZlDQDA?","levels":null,"length":4},"transitLeg":false,"mode":"WALK","route":"","agencyName":null,"agencyUrl":null,"agencyTimeZoneOffset":-14400000,"routeColor":null,"routeType":null,"routeId":null,"routeTextColor":null,"interlineWithPreviousLeg":false,"tripShortName":null,"tripBlockId":null,"headsign":null,"agencyId":null,"tripId":null,"serviceDate":null,"intermediateStops":null,"steps":[{"distance":75.84173737731417,"relativeDirection":"DEPART","streetName":"West Market Street","absoluteDirection":"WEST","exit":null,"stayOn":false,"area":false,"bogusName":false,"lon":-76.76788573568848,"lat":39.95297156023158,"alerts":null,"elevation":[]},{"distance":10.817034605073214,"relativeDirection":"RIGHT","streetName":"North Diamond Street","absoluteDirection":"NORTH","exit":null,"stayOn":false,"area":false,"bogusName":false,"lon":-76.7687589,"lat":39.9528381,"alerts":null,"elevation":[]}],"notes":null,"alerts":null,"routeShortName":null,"routeLongName":null,"boardRule":null,"alightRule":null,"rentedBike":false,"duration":70.0},{"startTime":1435187580000,"endTime":1435188600000,"departureDelay":0,"arrivalDelay":0,"realTime":false,"isNonExactFrequency":null,"headway":null,"distance":3402.844344321629,"from":{"name":"W Market St At Diamond St Ib","stopId":{"agencyId":"210","id":"766447"},"stopCode":null,"platformCode":null,"lon":-76.76870836193655,"lat":39.95295348683858,"arrival":1435187579000,"departure":1435187580000,"orig":null,"zoneId":null,"stopIndex":0},"to":{"name":"Transfer Center","stopId":{"agencyId":"210","id":"765237"},"stopCode":null,"platformCode":null,"lon":-76.731524,"lat":39.959945,"arrival":1435188600000,"departure":1435188600000,"orig":null,"zoneId":"0","stopIndex":14},"legGeometry":{"points":"{hzrFz{psMgGjA_AqLYkKdG[\\Co@cW[kLm@}R?CgAuFgA{FOaAMu@fCgAbCeAOs@y@wDQ{@iAuFUcAIc@iAkFiAwFOo@CKsAyG_CcLyAuGI_@qAiGG_@aAyEoBcJG[Kg@Q_AwB{JMg@@?eCuKu@A","levels":null,"length":42},"transitLeg":true,"mode":"BUS","route":"5W","agencyName":null,"agencyUrl":null,"agencyTimeZoneOffset":-14400000,"routeColor":"800080","routeType":3,"routeId":"1270","routeTextColor":"FFFFFF","interlineWithPreviousLeg":false,"tripShortName":null,"tripBlockId":null,"headsign":"5w Downtown","agencyId":"210","tripId":"54016A1024B1797","serviceDate":"20150624","intermediateStops":null,"steps":[],"notes":null,"alerts":null,"routeShortName":"5W","routeLongName":"West York  West York Ind Park","boardRule":null,"alightRule":null,"rentedBike":false,"duration":1020.0},{"startTime":1435188600000,"endTime":1435189782000,"departureDelay":0,"arrivalDelay":0,"realTime":false,"isNonExactFrequency":null,"headway":null,"distance":4597.981331821435,"from":{"name":"Transfer Center","stopId":{"agencyId":"210","id":"765237"},"stopCode":null,"platformCode":null,"lon":-76.731524,"lat":39.959945,"arrival":1435188600000,"departure":1435188600000,"orig":null,"zoneId":"0","stopIndex":0},"to":{"name":"E Market At Royal Ob","stopId":{"agencyId":"210","id":"765013"},"stopCode":null,"platformCode":null,"lon":-76.681946,"lat":39.973889,"arrival":1435189782000,"departure":1435189783000,"orig":null,"zoneId":"0","stopIndex":17},"legGeometry":{"points":"ot{rFzsisMv@?mCyM??QcA}@_E_AmEy@aE{@{D_C`A}Ap@w@ZyBaKSy@kB{I_BaJAEa@qBUkAUkAw@sDsCkIs@uBUs@Oe@{@eCq@qBa@cA_CsHWs@oD_KUo@wC_IMa@AEoCeIMa@Qk@qBmGcAmCk@uBEy@KcBEgAEm@[mFa@mH??k@sJBa@@OK@CqBSsDOyCEy@IaCOsBIiA?MG_BG{A?KMgEKoEQqEAYMmDQgECm@K}CKuECg@GeD]mFIaA","levels":null,"length":76},"transitLeg":true,"mode":"BUS","route":"1E","agencyName":null,"agencyUrl":null,"agencyTimeZoneOffset":-14400000,"routeColor":"FF0000","routeType":3,"routeId":"1265","routeTextColor":"000000","interlineWithPreviousLeg":false,"tripShortName":null,"tripBlockId":null,"headsign":"East York Via Market","agencyId":"210","tripId":"53814A1024B1797","serviceDate":"20150624","intermediateStops":null,"steps":[],"notes":null,"alerts":null,"routeShortName":"1E","routeLongName":"East York","boardRule":null,"alightRule":null,"rentedBike":false,"duration":1182.0},{"startTime":1435189783000,"endTime":1435190765000,"departureDelay":0,"arrivalDelay":0,"realTime":false,"isNonExactFrequency":null,"headway":null,"distance":1287.6298109345778,"from":{"name":"E Market At Royal Ob","stopId":{"agencyId":"210","id":"765013"},"stopCode":null,"platformCode":null,"lon":-76.6819547471471,"lat":39.9739597747891,"arrival":1435189782000,"departure":1435189783000,"orig":null,"zoneId":null,"stopIndex":null},"to":{"name":"Erlen Drive","stopId":null,"stopCode":null,"platformCode":null,"lon":-76.67966600881111,"lat":39.96437079412677,"arrival":1435190765000,"departure":null,"orig":"","zoneId":null,"stopIndex":null},"legGeometry":{"points":"el~rFf}_sMF`AbJqAbKy@vHArHh@jHf@VeHRkEfE`@","levels":null,"length":10},"transitLeg":false,"mode":"WALK","route":"","agencyName":null,"agencyUrl":null,"agencyTimeZoneOffset":-14400000,"routeColor":null,"routeType":null,"routeId":null,"routeTextColor":null,"interlineWithPreviousLeg":false,"tripShortName":null,"tripBlockId":null,"headsign":null,"agencyId":null,"tripId":null,"serviceDate":null,"intermediateStops":null,"steps":[{"distance":28.755737153530887,"relativeDirection":"DEPART","streetName":"East Market Street","absoluteDirection":"WEST","exit":null,"stayOn":false,"area":false,"bogusName":false,"lon":-76.6819547471471,"lat":39.9739597747891,"alerts":null,"elevation":[]},{"distance":931.5273083562267,"relativeDirection":"LEFT","streetName":"South Royal Street","absoluteDirection":"SOUTH","exit":null,"stayOn":false,"area":false,"bogusName":false,"lon":-76.6822879,"lat":39.9739186,"alerts":null,"elevation":[]},{"distance":214.26441832231393,"relativeDirection":"LEFT","streetName":"7th Avenue","absoluteDirection":"EAST","exit":null,"stayOn":false,"area":false,"bogusName":false,"lon":-76.681988,"lat":39.965598,"alerts":null,"elevation":[]},{"distance":113.08234710250632,"relativeDirection":"RIGHT","streetName":"Erlen Drive","absoluteDirection":"SOUTH","exit":null,"stayOn":false,"area":false,"bogusName":false,"lon":-76.6794902,"lat":39.9653788,"alerts":null,"elevation":[]}],"notes":null,"alerts":null,"routeShortName":null,"routeLongName":null,"boardRule":null,"alightRule":null,"rentedBike":false,"duration":982.0}]},{"id":13670,"trip_part_id":3459,"mode_id":1,"service_id":3,"server_status":200,"server_message":null,"duration":2764,"walk_time":772,"transit_time":1990,"wait_time":2,"walk_distance":999.1786066998746,"transfers":1,"count":null,"legs":"---\n- startTime: 1435189309000\n  endTime: 1435189379000\n  departureDelay: 0\n  arrivalDelay: 0\n  realTime: false\n  isNonExactFrequency: \n  headway: \n  distance: 86.65877198238739\n  from:\n    name: West Market Street\n    stopId: \n    stopCode: \n    platformCode: \n    lon: -76.76788573568848\n    lat: 39.95297156023158\n    arrival: \n    departure: 1435189309000\n    orig: ''\n    zoneId: \n    stopIndex: \n  to:\n    name: W Market St At Diamond St Ib\n    stopId:\n      agencyId: '210'\n      id: '766447'\n    stopCode: \n    platformCode: \n    lon: -76.76878412778319\n    lat: 39.95293343815699\n    arrival: 1435189379000\n    departure: 1435189380000\n    orig: \n    zoneId: \n    stopIndex: \n  legGeometry:\n    points: aizrFhvpsMZlDQDA?\n    levels: \n    length: 4\n  transitLeg: false\n  mode: WALK\n  route: ''\n  agencyName: \n  agencyUrl: \n  agencyTimeZoneOffset: -14400000\n  routeColor: \n  routeType: \n  routeId: \n  routeTextColor: \n  interlineWithPreviousLeg: false\n  tripShortName: \n  tripBlockId: \n  headsign: \n  agencyId: \n  tripId: \n  serviceDate: \n  intermediateStops: \n  steps:\n  - distance: 75.84173737731417\n    relativeDirection: DEPART\n    streetName: West Market Street\n    absoluteDirection: WEST\n    exit: \n    stayOn: false\n    area: false\n    bogusName: false\n    lon: -76.76788573568848\n    lat: 39.95297156023158\n    alerts: \n    elevation: []\n  - distance: 10.817034605073214\n    relativeDirection: RIGHT\n    streetName: North Diamond Street\n    absoluteDirection: NORTH\n    exit: \n    stayOn: false\n    area: false\n    bogusName: false\n    lon: -76.7687589\n    lat: 39.9528381\n    alerts: \n    elevation: []\n  notes: \n  alerts: \n  routeShortName: \n  routeLongName: \n  boardRule: \n  alightRule: \n  rentedBike: false\n  duration: 70.0\n- startTime: 1435189380000\n  endTime: 1435190400000\n  departureDelay: 0\n  arrivalDelay: 0\n  realTime: false\n  isNonExactFrequency: \n  headway: \n  distance: 3402.844344321629\n  from:\n    name: W Market St At Diamond St Ib\n    stopId:\n      agencyId: '210'\n      id: '766447'\n    stopCode: \n    platformCode: \n    lon: -76.76870836193655\n    lat: 39.95295348683858\n    arrival: 1435189379000\n    departure: 1435189380000\n    orig: \n    zoneId: \n    stopIndex: 0\n  to:\n    name: Transfer Center\n    stopId:\n      agencyId: '210'\n      id: '765237'\n    stopCode: \n    platformCode: \n    lon: -76.731524\n    lat: 39.959945\n    arrival: 1435190400000\n    departure: 1435190400000\n    orig: \n    zoneId: '0'\n    stopIndex: 14\n  legGeometry:\n    points: \"{hzrFz{psMgGjA_AqLYkKdG[\\\\Co@cW[kLm@}R?CgAuFgA{FOaAMu@fCgAbCeAOs@y@wDQ{@iAuFUcAIc@iAkFiAwFOo@CKsAyG_CcLyAuGI_@qAiGG_@aAyEoBcJG[Kg@Q_AwB{JMg@@?eCuKu@A\"\n    levels: \n    length: 42\n  transitLeg: true\n  mode: BUS\n  route: 5W\n  agencyName: \n  agencyUrl: \n  agencyTimeZoneOffset: -14400000\n  routeColor: '800080'\n  routeType: 3\n  routeId: '1270'\n  routeTextColor: FFFFFF\n  interlineWithPreviousLeg: false\n  tripShortName: \n  tripBlockId: \n  headsign: 5w Downtown\n  agencyId: '210'\n  tripId: 54017A1024B1797\n  serviceDate: '20150624'\n  intermediateStops: \n  steps: []\n  notes: \n  alerts: \n  routeShortName: 5W\n  routeLongName: West York  West York Ind Park\n  boardRule: \n  alightRule: \n  rentedBike: false\n  duration: 1020.0\n- startTime: 1435190400000\n  endTime: 1435191370000\n  departureDelay: 0\n  arrivalDelay: 0\n  realTime: false\n  isNonExactFrequency: \n  headway: \n  distance: 4786.37466854201\n  from:\n    name: Transfer Center\n    stopId:\n      agencyId: '210'\n      id: '765237'\n    stopCode: \n    platformCode: \n    lon: -76.731524\n    lat: 39.959945\n    arrival: 1435190400000\n    departure: 1435190400000\n    orig: \n    zoneId: '0'\n    stopIndex: 0\n  to:\n    name: Camp Betty At Mt Rose Ave Ob\n    stopId:\n      agencyId: '210'\n      id: '765016'\n    stopCode: \n    platformCode: \n    lon: -76.682706\n    lat: 39.957379\n    arrival: 1435191370000\n    departure: 1435191371000\n    orig: \n    zoneId: '0'\n    stopIndex: 17\n  legGeometry:\n    points: ot{rFzsisMv@?mCyM??QcA}@_E_AmEy@aEOw@k@cCy@_E[cB[eB_AqEq@cDIa@dAg@`Ae@dBm@b@OzB{@f@UCuCMaFCgCAo@EsBM}EOgHAo@EuAKmEIaHCq@Ck@McFGgBIiBMeDGeBUsISiJ?SAa@O}IMoHC{@uAHwAJiBDCaDCeBA_AfHa@TA~FYpCGb@CxAIX_I\\oGFmBb@wLBsALeFDkENqBT}BHkG@kB?gDBeACwB?m@AwBOkELa@JELCXB~At@RN\n    levels: \n    length: 82\n  transitLeg: true\n  mode: BUS\n  route: 5E\n  agencyName: \n  agencyUrl: \n  agencyTimeZoneOffset: -14400000\n  routeColor: DB7093\n  routeType: 3\n  routeId: '1271'\n  routeTextColor: '000000'\n  interlineWithPreviousLeg: false\n  tripShortName: \n  tripBlockId: \n  headsign: Kmart Greensprings\n  agencyId: '210'\n  tripId: 54044A1024B1797\n  serviceDate: '20150624'\n  intermediateStops: \n  steps: []\n  notes: \n  alerts: \n  routeShortName: 5E\n  routeLongName: Haines Rd  Kmart  Greensprings\n  boardRule: \n  alightRule: \n  rentedBike: false\n  duration: 970.0\n- startTime: 1435191371000\n  endTime: 1435192073000\n  departureDelay: 0\n  arrivalDelay: 0\n  realTime: false\n  isNonExactFrequency: \n  headway: \n  distance: 912.4087335487009\n  from:\n    name: Camp Betty At Mt Rose Ave Ob\n    stopId:\n      agencyId: '210'\n      id: '765016'\n    stopCode: \n    platformCode: \n    lon: -76.68266362675077\n    lat: 39.95734572174098\n    arrival: 1435191370000\n    departure: 1435191371000\n    orig: \n    zoneId: \n    stopIndex: \n  to:\n    name: Erlen Drive\n    stopId: \n    stopCode: \n    platformCode: \n    lon: -76.67966600881111\n    lat: 39.96437079412677\n    arrival: 1435192073000\n    departure: \n    orig: ''\n    zoneId: \n    stopIndex: \n  legGeometry:\n    points: kd{rFta`sMSO_Bw@cAYSEaB_@qDu@OEmAUeCi@mCe@VcFaDUaDG_Gk@\n    levels: \n    length: 15\n  transitLeg: false\n  mode: WALK\n  route: ''\n  agencyName: \n  agencyUrl: \n  agencyTimeZoneOffset: -14400000\n  routeColor: \n  routeType: \n  routeId: \n  routeTextColor: \n  interlineWithPreviousLeg: false\n  tripShortName: \n  tripBlockId: \n  headsign: \n  agencyId: \n  tripId: \n  serviceDate: \n  intermediateStops: \n  steps:\n  - distance: 489.6573354632666\n    relativeDirection: DEPART\n    streetName: Haines Road\n    absoluteDirection: NORTHEAST\n    exit: \n    stayOn: false\n    area: false\n    bogusName: false\n    lon: -76.68266362675077\n    lat: 39.95734572174098\n    alerts: \n    elevation: []\n  - distance: 98.53025812689052\n    relativeDirection: RIGHT\n    streetName: Raleigh Drive\n    absoluteDirection: EAST\n    exit: \n    stayOn: false\n    area: false\n    bogusName: false\n    lon: -76.68118\n    lat: 39.9615941\n    alerts: \n    elevation: []\n  - distance: 324.22113995854363\n    relativeDirection: LEFT\n    streetName: Erlen Drive\n    absoluteDirection: NORTH\n    exit: \n    stayOn: false\n    area: false\n    bogusName: false\n    lon: -76.6800351\n    lat: 39.9614712\n    alerts: \n    elevation: []\n  notes: \n  alerts: \n  routeShortName: \n  routeLongName: \n  boardRule: \n  alightRule: \n  rentedBike: false\n  duration: 702.0\n","cost":"1.6","hidden":false,"created_at":"2015-06-15T16:14:10.590-04:00","updated_at":"2015-06-15T16:14:10.633-04:00","ride_count":null,"external_info":null,"match_score":2.7755575615628914e-17,"missing_information":false,"accommodation_mismatch":false,"missing_information_text":null,"date_mismatch":false,"time_mismatch":false,"too_late":false,"missing_accommodations":"","cost_comments":null,"selected":null,"start_time":"2015-06-24T19:41:49.000-04:00","end_time":"2015-06-24T20:27:53.000-04:00","is_bookable":false,"booking_confirmation":null,"duration_estimated":false,"map_image":{"url":null},"too_early":false,"returned_mode_code":"mode_transit","order_xml":null,"discounts":null,"segment_index":0,"start_location":{"address_components":[{"long_name":"1829 W Market St","short_name":"1829 W Market St","types":["street_address"]},{"long_name":"York","short_name":"York","types":["locality","political"]},{"long_name":"Pennsylvania","short_name":"Pennsylvania","types":["administrative_area_level_1","political"]},{"long_name":"17404","short_name":"17404","types":["postal_code"]}],"formatted_address":"1829 W Market St, York, Pennsylvania 17404","geometry":{"location":{"lat":39.953249,"lng":-76.7679579}},"id":4319,"name":"1829 W Market St","scope":"user"},"end_location":{"address_components":[{"long_name":"701 Erlen Drive","short_name":"701 Erlen Drive","types":["street_address"]},{"long_name":"York","short_name":"York","types":["locality","political"]},{"long_name":"Pennsylvania","short_name":"Pennsylvania","types":["administrative_area_level_1","political"]},{"long_name":"17402","short_name":"17402","types":["postal_code"]}],"formatted_address":"701 Erlen Drive, York, Pennsylvania 17402","geometry":{"location":{"lat":39.964296,"lng":-76.678936}},"id":4320,"name":"East York Elementary School","scope":"user"},"prebooking_questions":[{"question":"Will you be traveling with an approved escort","choices":[true,false],"code":"assistant"},{"question":"How many children or family members will be traveling with you?","choices":[0,1,2],"code":"children"}],"bookable":false,"json_legs":[{"startTime":1435189309000,"endTime":1435189379000,"departureDelay":0,"arrivalDelay":0,"realTime":false,"isNonExactFrequency":null,"headway":null,"distance":86.65877198238739,"from":{"name":"West Market Street","stopId":null,"stopCode":null,"platformCode":null,"lon":-76.76788573568848,"lat":39.95297156023158,"arrival":null,"departure":1435189309000,"orig":"","zoneId":null,"stopIndex":null},"to":{"name":"W Market St At Diamond St Ib","stopId":{"agencyId":"210","id":"766447"},"stopCode":null,"platformCode":null,"lon":-76.76878412778319,"lat":39.95293343815699,"arrival":1435189379000,"departure":1435189380000,"orig":null,"zoneId":null,"stopIndex":null},"legGeometry":{"points":"aizrFhvpsMZlDQDA?","levels":null,"length":4},"transitLeg":false,"mode":"WALK","route":"","agencyName":null,"agencyUrl":null,"agencyTimeZoneOffset":-14400000,"routeColor":null,"routeType":null,"routeId":null,"routeTextColor":null,"interlineWithPreviousLeg":false,"tripShortName":null,"tripBlockId":null,"headsign":null,"agencyId":null,"tripId":null,"serviceDate":null,"intermediateStops":null,"steps":[{"distance":75.84173737731417,"relativeDirection":"DEPART","streetName":"West Market Street","absoluteDirection":"WEST","exit":null,"stayOn":false,"area":false,"bogusName":false,"lon":-76.76788573568848,"lat":39.95297156023158,"alerts":null,"elevation":[]},{"distance":10.817034605073214,"relativeDirection":"RIGHT","streetName":"North Diamond Street","absoluteDirection":"NORTH","exit":null,"stayOn":false,"area":false,"bogusName":false,"lon":-76.7687589,"lat":39.9528381,"alerts":null,"elevation":[]}],"notes":null,"alerts":null,"routeShortName":null,"routeLongName":null,"boardRule":null,"alightRule":null,"rentedBike":false,"duration":70.0},{"startTime":1435189380000,"endTime":1435190400000,"departureDelay":0,"arrivalDelay":0,"realTime":false,"isNonExactFrequency":null,"headway":null,"distance":3402.844344321629,"from":{"name":"W Market St At Diamond St Ib","stopId":{"agencyId":"210","id":"766447"},"stopCode":null,"platformCode":null,"lon":-76.76870836193655,"lat":39.95295348683858,"arrival":1435189379000,"departure":1435189380000,"orig":null,"zoneId":null,"stopIndex":0},"to":{"name":"Transfer Center","stopId":{"agencyId":"210","id":"765237"},"stopCode":null,"platformCode":null,"lon":-76.731524,"lat":39.959945,"arrival":1435190400000,"departure":1435190400000,"orig":null,"zoneId":"0","stopIndex":14},"legGeometry":{"points":"{hzrFz{psMgGjA_AqLYkKdG[\\Co@cW[kLm@}R?CgAuFgA{FOaAMu@fCgAbCeAOs@y@wDQ{@iAuFUcAIc@iAkFiAwFOo@CKsAyG_CcLyAuGI_@qAiGG_@aAyEoBcJG[Kg@Q_AwB{JMg@@?eCuKu@A","levels":null,"length":42},"transitLeg":true,"mode":"BUS","route":"5W","agencyName":null,"agencyUrl":null,"agencyTimeZoneOffset":-14400000,"routeColor":"800080","routeType":3,"routeId":"1270","routeTextColor":"FFFFFF","interlineWithPreviousLeg":false,"tripShortName":null,"tripBlockId":null,"headsign":"5w Downtown","agencyId":"210","tripId":"54017A1024B1797","serviceDate":"20150624","intermediateStops":null,"steps":[],"notes":null,"alerts":null,"routeShortName":"5W","routeLongName":"West York  West York Ind Park","boardRule":null,"alightRule":null,"rentedBike":false,"duration":1020.0},{"startTime":1435190400000,"endTime":1435191370000,"departureDelay":0,"arrivalDelay":0,"realTime":false,"isNonExactFrequency":null,"headway":null,"distance":4786.37466854201,"from":{"name":"Transfer Center","stopId":{"agencyId":"210","id":"765237"},"stopCode":null,"platformCode":null,"lon":-76.731524,"lat":39.959945,"arrival":1435190400000,"departure":1435190400000,"orig":null,"zoneId":"0","stopIndex":0},"to":{"name":"Camp Betty At Mt Rose Ave Ob","stopId":{"agencyId":"210","id":"765016"},"stopCode":null,"platformCode":null,"lon":-76.682706,"lat":39.957379,"arrival":1435191370000,"departure":1435191371000,"orig":null,"zoneId":"0","stopIndex":17},"legGeometry":{"points":"ot{rFzsisMv@?mCyM??QcA}@_E_AmEy@aEOw@k@cCy@_E[cB[eB_AqEq@cDIa@dAg@`Ae@dBm@b@OzB{@f@UCuCMaFCgCAo@EsBM}EOgHAo@EuAKmEIaHCq@Ck@McFGgBIiBMeDGeBUsISiJ?SAa@O}IMoHC{@uAHwAJiBDCaDCeBA_AfHa@TA~FYpCGb@CxAIX_I\\oGFmBb@wLBsALeFDkENqBT}BHkG@kB?gDBeACwB?m@AwBOkELa@JELCXB~At@RN","levels":null,"length":82},"transitLeg":true,"mode":"BUS","route":"5E","agencyName":null,"agencyUrl":null,"agencyTimeZoneOffset":-14400000,"routeColor":"DB7093","routeType":3,"routeId":"1271","routeTextColor":"000000","interlineWithPreviousLeg":false,"tripShortName":null,"tripBlockId":null,"headsign":"Kmart Greensprings","agencyId":"210","tripId":"54044A1024B1797","serviceDate":"20150624","intermediateStops":null,"steps":[],"notes":null,"alerts":null,"routeShortName":"5E","routeLongName":"Haines Rd  Kmart  Greensprings","boardRule":null,"alightRule":null,"rentedBike":false,"duration":970.0},{"startTime":1435191371000,"endTime":1435192073000,"departureDelay":0,"arrivalDelay":0,"realTime":false,"isNonExactFrequency":null,"headway":null,"distance":912.4087335487009,"from":{"name":"Camp Betty At Mt Rose Ave Ob","stopId":{"agencyId":"210","id":"765016"},"stopCode":null,"platformCode":null,"lon":-76.68266362675077,"lat":39.95734572174098,"arrival":1435191370000,"departure":1435191371000,"orig":null,"zoneId":null,"stopIndex":null},"to":{"name":"Erlen Drive","stopId":null,"stopCode":null,"platformCode":null,"lon":-76.67966600881111,"lat":39.96437079412677,"arrival":1435192073000,"departure":null,"orig":"","zoneId":null,"stopIndex":null},"legGeometry":{"points":"kd{rFta`sMSO_Bw@cAYSEaB_@qDu@OEmAUeCi@mCe@VcFaDUaDG_Gk@","levels":null,"length":15},"transitLeg":false,"mode":"WALK","route":"","agencyName":null,"agencyUrl":null,"agencyTimeZoneOffset":-14400000,"routeColor":null,"routeType":null,"routeId":null,"routeTextColor":null,"interlineWithPreviousLeg":false,"tripShortName":null,"tripBlockId":null,"headsign":null,"agencyId":null,"tripId":null,"serviceDate":null,"intermediateStops":null,"steps":[{"distance":489.6573354632666,"relativeDirection":"DEPART","streetName":"Haines Road","absoluteDirection":"NORTHEAST","exit":null,"stayOn":false,"area":false,"bogusName":false,"lon":-76.68266362675077,"lat":39.95734572174098,"alerts":null,"elevation":[]},{"distance":98.53025812689052,"relativeDirection":"RIGHT","streetName":"Raleigh Drive","absoluteDirection":"EAST","exit":null,"stayOn":false,"area":false,"bogusName":false,"lon":-76.68118,"lat":39.9615941,"alerts":null,"elevation":[]},{"distance":324.22113995854363,"relativeDirection":"LEFT","streetName":"Erlen Drive","absoluteDirection":"NORTH","exit":null,"stayOn":false,"area":false,"bogusName":false,"lon":-76.6800351,"lat":39.9614712,"alerts":null,"elevation":[]}],"notes":null,"alerts":null,"routeShortName":null,"routeLongName":null,"boardRule":null,"alightRule":null,"rentedBike":false,"duration":702.0}]},{"id":13671,"trip_part_id":3460,"mode_id":1,"service_id":3,"server_status":200,"server_message":null,"duration":3367,"walk_time":1099,"transit_time":2266,"wait_time":2,"walk_distance":1434.2171556838953,"transfers":1,"count":null,"legs":"---\n- startTime: 1435193238000\n  endTime: 1435194277000\n  departureDelay: 0\n  arrivalDelay: 0\n  realTime: false\n  isNonExactFrequency: \n  headway: \n  distance: 1354.3885533569828\n  from:\n    name: Erlen Drive\n    stopId: \n    stopCode: \n    platformCode: \n    lon: -76.67966600881111\n    lat: 39.96437079412677\n    arrival: \n    departure: 1435193238000\n    orig: ''\n    zoneId: \n    stopIndex: \n  to:\n    name: E Market At Royal St Ib\n    stopId:\n      agencyId: '210'\n      id: '765014'\n    stopCode: \n    platformCode: \n    lon: -76.68196293590873\n    lat: 39.97404613313894\n    arrival: 1435194277000\n    departure: 1435194278000\n    orig: \n    zoneId: \n    stopIndex: \n  legGeometry:\n    points: ip|rF|n_sMgEa@iBO}CYkCS[nEgEUcHaAkCSuFUcBIQDeDp@oDt@KBG@v@rJ\n    levels: \n    length: 17\n  transitLeg: false\n  mode: WALK\n  route: ''\n  agencyName: \n  agencyUrl: \n  agencyTimeZoneOffset: -14400000\n  routeColor: \n  routeType: \n  routeId: \n  routeTextColor: \n  interlineWithPreviousLeg: false\n  tripShortName: \n  tripBlockId: \n  headsign: \n  agencyId: \n  tripId: \n  serviceDate: \n  intermediateStops: \n  steps:\n  - distance: 339.0844467376189\n    relativeDirection: DEPART\n    streetName: Erlen Drive\n    absoluteDirection: NORTH\n    exit: \n    stayOn: false\n    area: false\n    bogusName: false\n    lon: -76.67966600881111\n    lat: 39.96437079412677\n    alerts: \n    elevation: []\n  - distance: 89.69541481797756\n    relativeDirection: LEFT\n    streetName: Cambridge Road\n    absoluteDirection: WEST\n    exit: \n    stayOn: false\n    area: false\n    bogusName: false\n    lon: -76.679188\n    lat: 39.967398\n    alerts: \n    elevation: []\n  - distance: 759.4662688674723\n    relativeDirection: RIGHT\n    streetName: Haines Road\n    absoluteDirection: NORTH\n    exit: \n    stayOn: false\n    area: false\n    bogusName: false\n    lon: -76.6802246\n    lat: 39.9675377\n    alerts: \n    elevation: []\n  - distance: 4.986198586413033\n    relativeDirection: CONTINUE\n    streetName: Memory Lane\n    absoluteDirection: NORTH\n    exit: \n    stayOn: false\n    area: false\n    bogusName: false\n    lon: -76.6800973\n    lat: 39.9742842\n    alerts: \n    elevation: []\n  - distance: 161.15622434750082\n    relativeDirection: LEFT\n    streetName: East Market Street\n    absoluteDirection: WEST\n    exit: \n    stayOn: false\n    area: false\n    bogusName: false\n    lon: -76.6801079\n    lat: 39.9743283\n    alerts: \n    elevation: []\n  notes: \n  alerts: \n  routeShortName: \n  routeLongName: \n  boardRule: \n  alightRule: \n  rentedBike: false\n  duration: 1039.0\n- startTime: 1435194278000\n  endTime: 1435195800000\n  departureDelay: 0\n  arrivalDelay: 0\n  realTime: false\n  isNonExactFrequency: \n  headway: \n  distance: 4971.1642893979815\n  from:\n    name: E Market At Royal St Ib\n    stopId:\n      agencyId: '210'\n      id: '765014'\n    stopCode: \n    platformCode: \n    lon: -76.681969\n    lat: 39.974086\n    arrival: 1435194277000\n    departure: 1435194278000\n    orig: \n    zoneId: '0'\n    stopIndex: 11\n  to:\n    name: Transfer Center\n    stopId:\n      agencyId: '210'\n      id: '765237'\n    stopCode: \n    platformCode: \n    lon: -76.731524\n    lat: 39.959945\n    arrival: 1435195800000\n    departure: 1435195800000\n    orig: \n    zoneId: '0'\n    stopIndex: 32\n  legGeometry:\n    points: wl~rFh}_sMHbA^lFJjE@NJfENhE@^LfDLdE@b@JlDNpE@d@HdDDdAFjCDf@@`@@LLlBJ`C@RB`@RxCRnDLjADb@l@hKB`@`@dHZlFDl@DfAFt@HfBWFwBb@sC^iC^LZ`BzEjAdDhCnHJ\\LZdBjERj@xDbLb@nA`@jA??zAdEPr@FLhBrFN`@tBdGt@lBh@bBLPNf@hAtDFPVt@`@~@lBlFh@l@RPTZDJFN`CnLFXf@hCR`ADNj@dD^bBZvAz@fEPt@Jf@^`B|@fE^fB^bBr@nDLf@A?hBhJzEqBtEmB\\xAfAG\n    levels: \n    length: 95\n  transitLeg: true\n  mode: BUS\n  route: 1E\n  agencyName: \n  agencyUrl: \n  agencyTimeZoneOffset: -14400000\n  routeColor: FF0000\n  routeType: 3\n  routeId: '1265'\n  routeTextColor: '000000'\n  interlineWithPreviousLeg: false\n  tripShortName: \n  tripBlockId: \n  headsign: 1e Downtown\n  agencyId: '210'\n  tripId: 53850A1024B1797\n  serviceDate: '20150624'\n  intermediateStops: \n  steps: []\n  notes: \n  alerts: \n  routeShortName: 1E\n  routeLongName: East York\n  boardRule: \n  alightRule: \n  rentedBike: false\n  duration: 1522.0\n- startTime: 1435195800000\n  endTime: 1435196544000\n  departureDelay: 0\n  arrivalDelay: 0\n  realTime: false\n  isNonExactFrequency: \n  headway: \n  distance: 3518.2812630961444\n  from:\n    name: Transfer Center\n    stopId:\n      agencyId: '210'\n      id: '765237'\n    stopCode: \n    platformCode: \n    lon: -76.731524\n    lat: 39.959945\n    arrival: 1435195800000\n    departure: 1435195800000\n    orig: \n    zoneId: '0'\n    stopIndex: 0\n  to:\n    name: W Market At Clinton St Ob\n    stopId:\n      agencyId: '210'\n      id: '765390'\n    stopCode: \n    platformCode: \n    lon: -76.766975\n    lat: 39.953165\n    arrival: 1435196544000\n    departure: 1435196545000\n    orig: \n    zoneId: '0'\n    stopIndex: 16\n  legGeometry:\n    points: qt{rFxsisMz@@o@{CvGkCtDnQA@BJZjBtApGPp@Nh@p@vCrA|FXvAl@nCDZFf@r@hDP~@xAtGJd@nBfJDTlBlIhAvFFXh@|Bx@`EKD}@\\cA`@zArHaA^{@^OFbAxEDPjBdJ?BfCxLHZfAjFjAlFHZgAb@o@X_@LkCRgDRDzARtHDvAPhHBf@TdIZjKBX\n    levels: \n    length: 57\n  transitLeg: true\n  mode: BUS\n  route: 5W\n  agencyName: \n  agencyUrl: \n  agencyTimeZoneOffset: -14400000\n  routeColor: '800080'\n  routeType: 3\n  routeId: '1270'\n  routeTextColor: FFFFFF\n  interlineWithPreviousLeg: false\n  tripShortName: \n  tripBlockId: \n  headsign: West York\n  agencyId: '210'\n  tripId: 53989A1024B1797\n  serviceDate: '20150624'\n  intermediateStops: \n  steps: []\n  notes: \n  alerts: \n  routeShortName: 5W\n  routeLongName: West York  West York Ind Park\n  boardRule: \n  alightRule: \n  rentedBike: false\n  duration: 744.0\n- startTime: 1435196545000\n  endTime: 1435196605000\n  departureDelay: 0\n  arrivalDelay: 0\n  realTime: false\n  isNonExactFrequency: \n  headway: \n  distance: 79.71899244898218\n  from:\n    name: W Market At Clinton St Ob\n    stopId:\n      agencyId: '210'\n      id: '765390'\n    stopCode: \n    platformCode: \n    lon: -76.76696635238902\n    lat: 39.95310085572663\n    arrival: 1435196544000\n    departure: 1435196545000\n    orig: \n    zoneId: \n    stopIndex: \n  to:\n    name: West Market Street\n    stopId: \n    stopCode: \n    platformCode: \n    lon: -76.76788573568848\n    lat: 39.95297156023158\n    arrival: 1435196605000\n    departure: \n    orig: ''\n    zoneId: \n    stopIndex: \n  legGeometry:\n    points: \"{izrFpppsMPzBFz@\"\n    levels: \n    length: 3\n  transitLeg: false\n  mode: WALK\n  route: ''\n  agencyName: \n  agencyUrl: \n  agencyTimeZoneOffset: -14400000\n  routeColor: \n  routeType: \n  routeId: \n  routeTextColor: \n  interlineWithPreviousLeg: false\n  tripShortName: \n  tripBlockId: \n  headsign: \n  agencyId: \n  tripId: \n  serviceDate: \n  intermediateStops: \n  steps:\n  - distance: 79.71899244898218\n    relativeDirection: DEPART\n    streetName: West Market Street\n    absoluteDirection: WEST\n    exit: \n    stayOn: false\n    area: false\n    bogusName: false\n    lon: -76.76696635238902\n    lat: 39.95310085572663\n    alerts: \n    elevation: []\n  notes: \n  alerts: \n  routeShortName: \n  routeLongName: \n  boardRule: \n  alightRule: \n  rentedBike: false\n  duration: 60.0\n","cost":"1.6","hidden":false,"created_at":"2015-06-15T16:14:11.596-04:00","updated_at":"2015-06-15T16:14:11.671-04:00","ride_count":null,"external_info":null,"match_score":-0.3,"missing_information":false,"accommodation_mismatch":false,"missing_information_text":null,"date_mismatch":false,"time_mismatch":false,"too_late":false,"missing_accommodations":"","cost_comments":null,"selected":null,"start_time":"2015-06-24T20:47:18.000-04:00","end_time":"2015-06-24T21:43:25.000-04:00","is_bookable":false,"booking_confirmation":null,"duration_estimated":false,"map_image":{"url":null},"too_early":false,"returned_mode_code":"mode_transit","order_xml":null,"discounts":null,"segment_index":1,"start_location":{"address_components":[{"long_name":"701 Erlen Drive","short_name":"701 Erlen Drive","types":["street_address"]},{"long_name":"York","short_name":"York","types":["locality","political"]},{"long_name":"Pennsylvania","short_name":"Pennsylvania","types":["administrative_area_level_1","political"]},{"long_name":"17402","short_name":"17402","types":["postal_code"]}],"formatted_address":"701 Erlen Drive, York, Pennsylvania 17402","geometry":{"location":{"lat":39.964296,"lng":-76.678936}},"id":4320,"name":"East York Elementary School","scope":"user"},"end_location":{"address_components":[{"long_name":"1829 W Market St","short_name":"1829 W Market St","types":["street_address"]},{"long_name":"York","short_name":"York","types":["locality","political"]},{"long_name":"Pennsylvania","short_name":"Pennsylvania","types":["administrative_area_level_1","political"]},{"long_name":"17404","short_name":"17404","types":["postal_code"]}],"formatted_address":"1829 W Market St, York, Pennsylvania 17404","geometry":{"location":{"lat":39.953249,"lng":-76.7679579}},"id":4319,"name":"1829 W Market St","scope":"user"},"prebooking_questions":[{"question":"Will you be traveling with an approved escort","choices":[true,false],"code":"assistant"},{"question":"How many children or family members will be traveling with you?","choices":[0,1,2],"code":"children"}],"bookable":false,"json_legs":[{"startTime":1435193238000,"endTime":1435194277000,"departureDelay":0,"arrivalDelay":0,"realTime":false,"isNonExactFrequency":null,"headway":null,"distance":1354.3885533569828,"from":{"name":"Erlen Drive","stopId":null,"stopCode":null,"platformCode":null,"lon":-76.67966600881111,"lat":39.96437079412677,"arrival":null,"departure":1435193238000,"orig":"","zoneId":null,"stopIndex":null},"to":{"name":"E Market At Royal St Ib","stopId":{"agencyId":"210","id":"765014"},"stopCode":null,"platformCode":null,"lon":-76.68196293590873,"lat":39.97404613313894,"arrival":1435194277000,"departure":1435194278000,"orig":null,"zoneId":null,"stopIndex":null},"legGeometry":{"points":"ip|rF|n_sMgEa@iBO}CYkCS[nEgEUcHaAkCSuFUcBIQDeDp@oDt@KBG@v@rJ","levels":null,"length":17},"transitLeg":false,"mode":"WALK","route":"","agencyName":null,"agencyUrl":null,"agencyTimeZoneOffset":-14400000,"routeColor":null,"routeType":null,"routeId":null,"routeTextColor":null,"interlineWithPreviousLeg":false,"tripShortName":null,"tripBlockId":null,"headsign":null,"agencyId":null,"tripId":null,"serviceDate":null,"intermediateStops":null,"steps":[{"distance":339.0844467376189,"relativeDirection":"DEPART","streetName":"Erlen Drive","absoluteDirection":"NORTH","exit":null,"stayOn":false,"area":false,"bogusName":false,"lon":-76.67966600881111,"lat":39.96437079412677,"alerts":null,"elevation":[]},{"distance":89.69541481797756,"relativeDirection":"LEFT","streetName":"Cambridge Road","absoluteDirection":"WEST","exit":null,"stayOn":false,"area":false,"bogusName":false,"lon":-76.679188,"lat":39.967398,"alerts":null,"elevation":[]},{"distance":759.4662688674723,"relativeDirection":"RIGHT","streetName":"Haines Road","absoluteDirection":"NORTH","exit":null,"stayOn":false,"area":false,"bogusName":false,"lon":-76.6802246,"lat":39.9675377,"alerts":null,"elevation":[]},{"distance":4.986198586413033,"relativeDirection":"CONTINUE","streetName":"Memory Lane","absoluteDirection":"NORTH","exit":null,"stayOn":false,"area":false,"bogusName":false,"lon":-76.6800973,"lat":39.9742842,"alerts":null,"elevation":[]},{"distance":161.15622434750082,"relativeDirection":"LEFT","streetName":"East Market Street","absoluteDirection":"WEST","exit":null,"stayOn":false,"area":false,"bogusName":false,"lon":-76.6801079,"lat":39.9743283,"alerts":null,"elevation":[]}],"notes":null,"alerts":null,"routeShortName":null,"routeLongName":null,"boardRule":null,"alightRule":null,"rentedBike":false,"duration":1039.0},{"startTime":1435194278000,"endTime":1435195800000,"departureDelay":0,"arrivalDelay":0,"realTime":false,"isNonExactFrequency":null,"headway":null,"distance":4971.1642893979815,"from":{"name":"E Market At Royal St Ib","stopId":{"agencyId":"210","id":"765014"},"stopCode":null,"platformCode":null,"lon":-76.681969,"lat":39.974086,"arrival":1435194277000,"departure":1435194278000,"orig":null,"zoneId":"0","stopIndex":11},"to":{"name":"Transfer Center","stopId":{"agencyId":"210","id":"765237"},"stopCode":null,"platformCode":null,"lon":-76.731524,"lat":39.959945,"arrival":1435195800000,"departure":1435195800000,"orig":null,"zoneId":"0","stopIndex":32},"legGeometry":{"points":"wl~rFh}_sMHbA^lFJjE@NJfENhE@^LfDLdE@b@JlDNpE@d@HdDDdAFjCDf@@`@@LLlBJ`C@RB`@RxCRnDLjADb@l@hKB`@`@dHZlFDl@DfAFt@HfBWFwBb@sC^iC^LZ`BzEjAdDhCnHJ\\LZdBjERj@xDbLb@nA`@jA??zAdEPr@FLhBrFN`@tBdGt@lBh@bBLPNf@hAtDFPVt@`@~@lBlFh@l@RPTZDJFN`CnLFXf@hCR`ADNj@dD^bBZvAz@fEPt@Jf@^`B|@fE^fB^bBr@nDLf@A?hBhJzEqBtEmB\\xAfAG","levels":null,"length":95},"transitLeg":true,"mode":"BUS","route":"1E","agencyName":null,"agencyUrl":null,"agencyTimeZoneOffset":-14400000,"routeColor":"FF0000","routeType":3,"routeId":"1265","routeTextColor":"000000","interlineWithPreviousLeg":false,"tripShortName":null,"tripBlockId":null,"headsign":"1e Downtown","agencyId":"210","tripId":"53850A1024B1797","serviceDate":"20150624","intermediateStops":null,"steps":[],"notes":null,"alerts":null,"routeShortName":"1E","routeLongName":"East York","boardRule":null,"alightRule":null,"rentedBike":false,"duration":1522.0},{"startTime":1435195800000,"endTime":1435196544000,"departureDelay":0,"arrivalDelay":0,"realTime":false,"isNonExactFrequency":null,"headway":null,"distance":3518.2812630961444,"from":{"name":"Transfer Center","stopId":{"agencyId":"210","id":"765237"},"stopCode":null,"platformCode":null,"lon":-76.731524,"lat":39.959945,"arrival":1435195800000,"departure":1435195800000,"orig":null,"zoneId":"0","stopIndex":0},"to":{"name":"W Market At Clinton St Ob","stopId":{"agencyId":"210","id":"765390"},"stopCode":null,"platformCode":null,"lon":-76.766975,"lat":39.953165,"arrival":1435196544000,"departure":1435196545000,"orig":null,"zoneId":"0","stopIndex":16},"legGeometry":{"points":"qt{rFxsisMz@@o@{CvGkCtDnQA@BJZjBtApGPp@Nh@p@vCrA|FXvAl@nCDZFf@r@hDP~@xAtGJd@nBfJDTlBlIhAvFFXh@|Bx@`EKD}@\\cA`@zArHaA^{@^OFbAxEDPjBdJ?BfCxLHZfAjFjAlFHZgAb@o@X_@LkCRgDRDzARtHDvAPhHBf@TdIZjKBX","levels":null,"length":57},"transitLeg":true,"mode":"BUS","route":"5W","agencyName":null,"agencyUrl":null,"agencyTimeZoneOffset":-14400000,"routeColor":"800080","routeType":3,"routeId":"1270","routeTextColor":"FFFFFF","interlineWithPreviousLeg":false,"tripShortName":null,"tripBlockId":null,"headsign":"West York","agencyId":"210","tripId":"53989A1024B1797","serviceDate":"20150624","intermediateStops":null,"steps":[],"notes":null,"alerts":null,"routeShortName":"5W","routeLongName":"West York  West York Ind Park","boardRule":null,"alightRule":null,"rentedBike":false,"duration":744.0},{"startTime":1435196545000,"endTime":1435196605000,"departureDelay":0,"arrivalDelay":0,"realTime":false,"isNonExactFrequency":null,"headway":null,"distance":79.71899244898218,"from":{"name":"W Market At Clinton St Ob","stopId":{"agencyId":"210","id":"765390"},"stopCode":null,"platformCode":null,"lon":-76.76696635238902,"lat":39.95310085572663,"arrival":1435196544000,"departure":1435196545000,"orig":null,"zoneId":null,"stopIndex":null},"to":{"name":"West Market Street","stopId":null,"stopCode":null,"platformCode":null,"lon":-76.76788573568848,"lat":39.95297156023158,"arrival":1435196605000,"departure":null,"orig":"","zoneId":null,"stopIndex":null},"legGeometry":{"points":"{izrFpppsMPzBFz@","levels":null,"length":3},"transitLeg":false,"mode":"WALK","route":"","agencyName":null,"agencyUrl":null,"agencyTimeZoneOffset":-14400000,"routeColor":null,"routeType":null,"routeId":null,"routeTextColor":null,"interlineWithPreviousLeg":false,"tripShortName":null,"tripBlockId":null,"headsign":null,"agencyId":null,"tripId":null,"serviceDate":null,"intermediateStops":null,"steps":[{"distance":79.71899244898218,"relativeDirection":"DEPART","streetName":"West Market Street","absoluteDirection":"WEST","exit":null,"stayOn":false,"area":false,"bogusName":false,"lon":-76.76696635238902,"lat":39.95310085572663,"alerts":null,"elevation":[]}],"notes":null,"alerts":null,"routeShortName":null,"routeLongName":null,"boardRule":null,"alightRule":null,"rentedBike":false,"duration":60.0}]},{"id":13672,"trip_part_id":3460,"mode_id":1,"service_id":3,"server_status":200,"server_message":null,"duration":5297,"walk_time":4542,"transit_time":753,"wait_time":2,"walk_distance":5927.003953461648,"transfers":0,"count":null,"legs":"---\n- startTime: 1435192784000\n  endTime: 1435194926000\n  departureDelay: 0\n  arrivalDelay: 0\n  realTime: false\n  isNonExactFrequency: \n  headway: \n  distance: 2772.2889501648897\n  from:\n    name: Erlen Drive\n    stopId: \n    stopCode: \n    platformCode: \n    lon: -76.67966600881111\n    lat: 39.96437079412677\n    arrival: \n    departure: 1435192784000\n    orig: ''\n    zoneId: \n    stopIndex: \n  to:\n    name: Third Ave At Belmont St Ib\n    stopId:\n      agencyId: '210'\n      id: '765050'\n    stopCode: \n    platformCode: \n    lon: -76.69424149668707\n    lat: 39.96812919135299\n    arrival: 1435194926000\n    departure: 1435194927000\n    orig: \n    zoneId: \n    stopIndex: \n  legGeometry:\n    points: ip|rF|n_sMgEa@SjEWdHkHg@OnEStE{GUMhFPdENnEFlEFzAFtB?hCC`AyE`@uJt@_@fAc@h@m@d@k@b@e@PWPOJy@p@i@r@F~A?JDh@B^NrBHbCDv@NxC~Cu@rCs@\\IpCq@dB[nAYxAYxASrAQDp@\n    levels: \n    length: 45\n  transitLeg: false\n  mode: WALK\n  route: ''\n  agencyName: \n  agencyUrl: \n  agencyTimeZoneOffset: -14400000\n  routeColor: \n  routeType: \n  routeId: \n  routeTextColor: \n  interlineWithPreviousLeg: false\n  tripShortName: \n  tripBlockId: \n  headsign: \n  agencyId: \n  tripId: \n  serviceDate: \n  intermediateStops: \n  steps:\n  - distance: 113.08234710250626\n    relativeDirection: DEPART\n    streetName: Erlen Drive\n    absoluteDirection: NORTH\n    exit: \n    stayOn: false\n    area: false\n    bogusName: false\n    lon: -76.67966600881111\n    lat: 39.96437079412677\n    alerts: \n    elevation: []\n  - distance: 214.26441832231393\n    relativeDirection: LEFT\n    streetName: 7th Avenue\n    absoluteDirection: WEST\n    exit: \n    stayOn: false\n    area: false\n    bogusName: false\n    lon: -76.6794902\n    lat: 39.9653788\n    alerts: \n    elevation: []\n  - distance: 167.66127362012043\n    relativeDirection: RIGHT\n    streetName: South Royal Street\n    absoluteDirection: NORTH\n    exit: \n    stayOn: false\n    area: false\n    bogusName: false\n    lon: -76.681988\n    lat: 39.965598\n    alerts: \n    elevation: []\n  - distance: 180.6433549186031\n    relativeDirection: LEFT\n    streetName: 5th Avenue\n    absoluteDirection: WEST\n    exit: \n    stayOn: false\n    area: false\n    bogusName: false\n    lon: -76.681788\n    lat: 39.967098\n    alerts: \n    elevation: []\n  - distance: 158.9840556539091\n    relativeDirection: RIGHT\n    streetName: South Kershaw Street\n    absoluteDirection: NORTH\n    exit: \n    stayOn: false\n    area: false\n    bogusName: false\n    lon: -76.6838955\n    lat: 39.9672706\n    alerts: \n    elevation: []\n  - distance: 538.7166024712035\n    relativeDirection: LEFT\n    streetName: 3rd Avenue\n    absoluteDirection: WEST\n    exit: \n    stayOn: false\n    area: false\n    bogusName: false\n    lon: -76.683788\n    lat: 39.968698\n    alerts: \n    elevation: []\n  - distance: 330.728406101577\n    relativeDirection: RIGHT\n    streetName: South Marshall Street\n    absoluteDirection: NORTH\n    exit: \n    stayOn: false\n    area: false\n    bogusName: false\n    lon: -76.690088\n    lat: 39.968498\n    alerts: \n    elevation: []\n  - distance: 240.65257342133935\n    relativeDirection: LEFT\n    streetName: Eastern Boulevard\n    absoluteDirection: NORTHWEST\n    exit: \n    stayOn: false\n    area: false\n    bogusName: false\n    lon: -76.6905209\n    lat: 39.9714537\n    alerts: \n    elevation: []\n  - distance: 275.9221825062198\n    relativeDirection: LEFT\n    streetName: East Market Street\n    absoluteDirection: WEST\n    exit: \n    stayOn: false\n    area: false\n    bogusName: false\n    lon: -76.6922107\n    lat: 39.9731351\n    alerts: \n    elevation: []\n  - distance: 530.6458592729704\n    relativeDirection: LEFT\n    streetName: South Belmont Street\n    absoluteDirection: SOUTH\n    exit: \n    stayOn: false\n    area: false\n    bogusName: false\n    lon: -76.6954184\n    lat: 39.972803\n    alerts: \n    elevation: []\n  - distance: 20.987876774126523\n    relativeDirection: RIGHT\n    streetName: 3rd Avenue\n    absoluteDirection: WEST\n    exit: \n    stayOn: false\n    area: false\n    bogusName: false\n    lon: -76.6939985\n    lat: 39.9681599\n    alerts: \n    elevation: []\n  notes: \n  alerts: \n  routeShortName: \n  routeLongName: \n  boardRule: \n  alightRule: \n  rentedBike: false\n  duration: 2142.0\n- startTime: 1435194927000\n  endTime: 1435195680000\n  departureDelay: 0\n  arrivalDelay: 0\n  realTime: false\n  isNonExactFrequency: \n  headway: \n  distance: 3544.8920294080885\n  from:\n    name: Third Ave At Belmont St Ib\n    stopId:\n      agencyId: '210'\n      id: '765050'\n    stopCode: \n    platformCode: \n    lon: -76.694244\n    lat: 39.968149\n    arrival: 1435194926000\n    departure: 1435194927000\n    orig: \n    zoneId: '0'\n    stopIndex: 1\n  to:\n    name: W King St At Newberry St Ib\n    stopId:\n      agencyId: '210'\n      id: '765256'\n    stopCode: \n    platformCode: \n    lon: -76.733698\n    lat: 39.958965\n    arrival: 1435195680000\n    departure: 1435195681000\n    orig: \n    zoneId: '0'\n    stopIndex: 15\n  legGeometry:\n    points: sg}rF~ibsMb@dI@Nh@jKDr@^fHB`@FVtAdI~AtIHf@t@rERjATzADRR`Ad@hCl@hDTbBDXJf@j@xCj@`DF`@VpARxAPpA^`BFl@Fh@j@pCj@hD\\`BBPx@pEjAdFr@`Cz@xBx@hBXtAdAdFZzADVT`A~@pE`@nBThAH\\ZxAx@`EXrA\\dBx@|D~@pEz@hEF\\b@nBjApFv@tDLj@Nx@FZh@dCn@zCiChAeC`AMg@\n    levels: \n    length: 67\n  transitLeg: true\n  mode: BUS\n  route: 4E\n  agencyName: \n  agencyUrl: \n  agencyTimeZoneOffset: -14400000\n  routeColor: ADD8E6\n  routeType: 3\n  routeId: '1269'\n  routeTextColor: '000000'\n  interlineWithPreviousLeg: false\n  tripShortName: \n  tripBlockId: \n  headsign: 4e Downtown\n  agencyId: '210'\n  tripId: 53956A1024B1797\n  serviceDate: '20150624'\n  intermediateStops: \n  steps: []\n  notes: \n  alerts: \n  routeShortName: 4E\n  routeLongName: Memorial Hospital\n  boardRule: \n  alightRule: \n  rentedBike: false\n  duration: 753.0\n- startTime: 1435195681000\n  endTime: 1435198081000\n  departureDelay: 0\n  arrivalDelay: 0\n  realTime: false\n  isNonExactFrequency: \n  headway: \n  distance: 3154.298187502456\n  from:\n    name: W King St At Newberry St Ib\n    stopId:\n      agencyId: '210'\n      id: '765256'\n    stopCode: \n    platformCode: \n    lon: -76.73370339627947\n    lat: 39.958981878790404\n    arrival: 1435195680000\n    departure: 1435195681000\n    orig: \n    zoneId: \n    stopIndex: \n  to:\n    name: West Market Street\n    stopId: \n    stopCode: \n    platformCode: \n    lon: -76.76788573568848\n    lat: 39.95297156023158\n    arrival: 1435198081000\n    departure: \n    orig: ''\n    zoneId: \n    stopIndex: \n  legGeometry:\n    points: sn{rFt`jsMLf@vBzJP~@Jf@FZnBdJ`AvEF^pAhGH^xAvGpBrJLn@rAvGBJNn@p@bDVrAhAjFHb@TbAl@rCZ`BPz@cChAgCjAfAbFLt@N`AhAzFdApF@BTnHRpIBn@DzARvHDtAPhHBf@RdI\\jK@XPzBFz@\n    levels: \n    length: 46\n  transitLeg: false\n  mode: WALK\n  route: ''\n  agencyName: \n  agencyUrl: \n  agencyTimeZoneOffset: -14400000\n  routeColor: \n  routeType: \n  routeId: \n  routeTextColor: \n  interlineWithPreviousLeg: false\n  tripShortName: \n  tripBlockId: \n  headsign: \n  agencyId: \n  tripId: \n  serviceDate: \n  intermediateStops: \n  steps:\n  - distance: 1557.0828507695765\n    relativeDirection: DEPART\n    streetName: West King Street\n    absoluteDirection: SOUTHWEST\n    exit: \n    stayOn: false\n    area: false\n    bogusName: false\n    lon: -76.73370339627947\n    lat: 39.958981878790404\n    alerts: \n    elevation: []\n  - distance: 162.21531203244706\n    relativeDirection: RIGHT\n    streetName: Dewey Street\n    absoluteDirection: NORTHWEST\n    exit: \n    stayOn: false\n    area: false\n    bogusName: false\n    lon: -76.7506556\n    lat: 39.9537659\n    alerts: \n    elevation: []\n  - distance: 1435.0000247004318\n    relativeDirection: LEFT\n    streetName: West Market Street\n    absoluteDirection: SOUTHWEST\n    exit: \n    stayOn: false\n    area: false\n    bogusName: false\n    lon: -76.7514099\n    lat: 39.9551052\n    alerts: \n    elevation: []\n  notes: \n  alerts: \n  routeShortName: \n  routeLongName: \n  boardRule: \n  alightRule: \n  rentedBike: false\n  duration: 2400.0\n","cost":"1.6","hidden":false,"created_at":"2015-06-15T16:14:11.623-04:00","updated_at":"2015-06-15T16:14:11.674-04:00","ride_count":null,"external_info":null,"match_score":-0.19999999999999998,"missing_information":false,"accommodation_mismatch":false,"missing_information_text":null,"date_mismatch":false,"time_mismatch":false,"too_late":false,"missing_accommodations":"","cost_comments":null,"selected":null,"start_time":"2015-06-24T20:39:44.000-04:00","end_time":"2015-06-24T22:08:01.000-04:00","is_bookable":false,"booking_confirmation":null,"duration_estimated":false,"map_image":{"url":null},"too_early":false,"returned_mode_code":"mode_transit","order_xml":null,"discounts":null,"segment_index":1,"start_location":{"address_components":[{"long_name":"701 Erlen Drive","short_name":"701 Erlen Drive","types":["street_address"]},{"long_name":"York","short_name":"York","types":["locality","political"]},{"long_name":"Pennsylvania","short_name":"Pennsylvania","types":["administrative_area_level_1","political"]},{"long_name":"17402","short_name":"17402","types":["postal_code"]}],"formatted_address":"701 Erlen Drive, York, Pennsylvania 17402","geometry":{"location":{"lat":39.964296,"lng":-76.678936}},"id":4320,"name":"East York Elementary School","scope":"user"},"end_location":{"address_components":[{"long_name":"1829 W Market St","short_name":"1829 W Market St","types":["street_address"]},{"long_name":"York","short_name":"York","types":["locality","political"]},{"long_name":"Pennsylvania","short_name":"Pennsylvania","types":["administrative_area_level_1","political"]},{"long_name":"17404","short_name":"17404","types":["postal_code"]}],"formatted_address":"1829 W Market St, York, Pennsylvania 17404","geometry":{"location":{"lat":39.953249,"lng":-76.7679579}},"id":4319,"name":"1829 W Market St","scope":"user"},"prebooking_questions":[{"question":"Will you be traveling with an approved escort","choices":[true,false],"code":"assistant"},{"question":"How many children or family members will be traveling with you?","choices":[0,1,2],"code":"children"}],"bookable":false,"json_legs":[{"startTime":1435192784000,"endTime":1435194926000,"departureDelay":0,"arrivalDelay":0,"realTime":false,"isNonExactFrequency":null,"headway":null,"distance":2772.2889501648897,"from":{"name":"Erlen Drive","stopId":null,"stopCode":null,"platformCode":null,"lon":-76.67966600881111,"lat":39.96437079412677,"arrival":null,"departure":1435192784000,"orig":"","zoneId":null,"stopIndex":null},"to":{"name":"Third Ave At Belmont St Ib","stopId":{"agencyId":"210","id":"765050"},"stopCode":null,"platformCode":null,"lon":-76.69424149668707,"lat":39.96812919135299,"arrival":1435194926000,"departure":1435194927000,"orig":null,"zoneId":null,"stopIndex":null},"legGeometry":{"points":"ip|rF|n_sMgEa@SjEWdHkHg@OnEStE{GUMhFPdENnEFlEFzAFtB?hCC`AyE`@uJt@_@fAc@h@m@d@k@b@e@PWPOJy@p@i@r@F~A?JDh@B^NrBHbCDv@NxC~Cu@rCs@\\IpCq@dB[nAYxAYxASrAQDp@","levels":null,"length":45},"transitLeg":false,"mode":"WALK","route":"","agencyName":null,"agencyUrl":null,"agencyTimeZoneOffset":-14400000,"routeColor":null,"routeType":null,"routeId":null,"routeTextColor":null,"interlineWithPreviousLeg":false,"tripShortName":null,"tripBlockId":null,"headsign":null,"agencyId":null,"tripId":null,"serviceDate":null,"intermediateStops":null,"steps":[{"distance":113.08234710250626,"relativeDirection":"DEPART","streetName":"Erlen Drive","absoluteDirection":"NORTH","exit":null,"stayOn":false,"area":false,"bogusName":false,"lon":-76.67966600881111,"lat":39.96437079412677,"alerts":null,"elevation":[]},{"distance":214.26441832231393,"relativeDirection":"LEFT","streetName":"7th Avenue","absoluteDirection":"WEST","exit":null,"stayOn":false,"area":false,"bogusName":false,"lon":-76.6794902,"lat":39.9653788,"alerts":null,"elevation":[]},{"distance":167.66127362012043,"relativeDirection":"RIGHT","streetName":"South Royal Street","absoluteDirection":"NORTH","exit":null,"stayOn":false,"area":false,"bogusName":false,"lon":-76.681988,"lat":39.965598,"alerts":null,"elevation":[]},{"distance":180.6433549186031,"relativeDirection":"LEFT","streetName":"5th Avenue","absoluteDirection":"WEST","exit":null,"stayOn":false,"area":false,"bogusName":false,"lon":-76.681788,"lat":39.967098,"alerts":null,"elevation":[]},{"distance":158.9840556539091,"relativeDirection":"RIGHT","streetName":"South Kershaw Street","absoluteDirection":"NORTH","exit":null,"stayOn":false,"area":false,"bogusName":false,"lon":-76.6838955,"lat":39.9672706,"alerts":null,"elevation":[]},{"distance":538.7166024712035,"relativeDirection":"LEFT","streetName":"3rd Avenue","absoluteDirection":"WEST","exit":null,"stayOn":false,"area":false,"bogusName":false,"lon":-76.683788,"lat":39.968698,"alerts":null,"elevation":[]},{"distance":330.728406101577,"relativeDirection":"RIGHT","streetName":"South Marshall Street","absoluteDirection":"NORTH","exit":null,"stayOn":false,"area":false,"bogusName":false,"lon":-76.690088,"lat":39.968498,"alerts":null,"elevation":[]},{"distance":240.65257342133935,"relativeDirection":"LEFT","streetName":"Eastern Boulevard","absoluteDirection":"NORTHWEST","exit":null,"stayOn":false,"area":false,"bogusName":false,"lon":-76.6905209,"lat":39.9714537,"alerts":null,"elevation":[]},{"distance":275.9221825062198,"relativeDirection":"LEFT","streetName":"East Market Street","absoluteDirection":"WEST","exit":null,"stayOn":false,"area":false,"bogusName":false,"lon":-76.6922107,"lat":39.9731351,"alerts":null,"elevation":[]},{"distance":530.6458592729704,"relativeDirection":"LEFT","streetName":"South Belmont Street","absoluteDirection":"SOUTH","exit":null,"stayOn":false,"area":false,"bogusName":false,"lon":-76.6954184,"lat":39.972803,"alerts":null,"elevation":[]},{"distance":20.987876774126523,"relativeDirection":"RIGHT","streetName":"3rd Avenue","absoluteDirection":"WEST","exit":null,"stayOn":false,"area":false,"bogusName":false,"lon":-76.6939985,"lat":39.9681599,"alerts":null,"elevation":[]}],"notes":null,"alerts":null,"routeShortName":null,"routeLongName":null,"boardRule":null,"alightRule":null,"rentedBike":false,"duration":2142.0},{"startTime":1435194927000,"endTime":1435195680000,"departureDelay":0,"arrivalDelay":0,"realTime":false,"isNonExactFrequency":null,"headway":null,"distance":3544.8920294080885,"from":{"name":"Third Ave At Belmont St Ib","stopId":{"agencyId":"210","id":"765050"},"stopCode":null,"platformCode":null,"lon":-76.694244,"lat":39.968149,"arrival":1435194926000,"departure":1435194927000,"orig":null,"zoneId":"0","stopIndex":1},"to":{"name":"W King St At Newberry St Ib","stopId":{"agencyId":"210","id":"765256"},"stopCode":null,"platformCode":null,"lon":-76.733698,"lat":39.958965,"arrival":1435195680000,"departure":1435195681000,"orig":null,"zoneId":"0","stopIndex":15},"legGeometry":{"points":"sg}rF~ibsMb@dI@Nh@jKDr@^fHB`@FVtAdI~AtIHf@t@rERjATzADRR`Ad@hCl@hDTbBDXJf@j@xCj@`DF`@VpARxAPpA^`BFl@Fh@j@pCj@hD\\`BBPx@pEjAdFr@`Cz@xBx@hBXtAdAdFZzADVT`A~@pE`@nBThAH\\ZxAx@`EXrA\\dBx@|D~@pEz@hEF\\b@nBjApFv@tDLj@Nx@FZh@dCn@zCiChAeC`AMg@","levels":null,"length":67},"transitLeg":true,"mode":"BUS","route":"4E","agencyName":null,"agencyUrl":null,"agencyTimeZoneOffset":-14400000,"routeColor":"ADD8E6","routeType":3,"routeId":"1269","routeTextColor":"000000","interlineWithPreviousLeg":false,"tripShortName":null,"tripBlockId":null,"headsign":"4e Downtown","agencyId":"210","tripId":"53956A1024B1797","serviceDate":"20150624","intermediateStops":null,"steps":[],"notes":null,"alerts":null,"routeShortName":"4E","routeLongName":"Memorial Hospital","boardRule":null,"alightRule":null,"rentedBike":false,"duration":753.0},{"startTime":1435195681000,"endTime":1435198081000,"departureDelay":0,"arrivalDelay":0,"realTime":false,"isNonExactFrequency":null,"headway":null,"distance":3154.298187502456,"from":{"name":"W King St At Newberry St Ib","stopId":{"agencyId":"210","id":"765256"},"stopCode":null,"platformCode":null,"lon":-76.73370339627947,"lat":39.958981878790404,"arrival":1435195680000,"departure":1435195681000,"orig":null,"zoneId":null,"stopIndex":null},"to":{"name":"West Market Street","stopId":null,"stopCode":null,"platformCode":null,"lon":-76.76788573568848,"lat":39.95297156023158,"arrival":1435198081000,"departure":null,"orig":"","zoneId":null,"stopIndex":null},"legGeometry":{"points":"sn{rFt`jsMLf@vBzJP~@Jf@FZnBdJ`AvEF^pAhGH^xAvGpBrJLn@rAvGBJNn@p@bDVrAhAjFHb@TbAl@rCZ`BPz@cChAgCjAfAbFLt@N`AhAzFdApF@BTnHRpIBn@DzARvHDtAPhHBf@RdI\\jK@XPzBFz@","levels":null,"length":46},"transitLeg":false,"mode":"WALK","route":"","agencyName":null,"agencyUrl":null,"agencyTimeZoneOffset":-14400000,"routeColor":null,"routeType":null,"routeId":null,"routeTextColor":null,"interlineWithPreviousLeg":false,"tripShortName":null,"tripBlockId":null,"headsign":null,"agencyId":null,"tripId":null,"serviceDate":null,"intermediateStops":null,"steps":[{"distance":1557.0828507695765,"relativeDirection":"DEPART","streetName":"West King Street","absoluteDirection":"SOUTHWEST","exit":null,"stayOn":false,"area":false,"bogusName":false,"lon":-76.73370339627947,"lat":39.958981878790404,"alerts":null,"elevation":[]},{"distance":162.21531203244706,"relativeDirection":"RIGHT","streetName":"Dewey Street","absoluteDirection":"NORTHWEST","exit":null,"stayOn":false,"area":false,"bogusName":false,"lon":-76.7506556,"lat":39.9537659,"alerts":null,"elevation":[]},{"distance":1435.0000247004318,"relativeDirection":"LEFT","streetName":"West Market Street","absoluteDirection":"SOUTHWEST","exit":null,"stayOn":false,"area":false,"bogusName":false,"lon":-76.7514099,"lat":39.9551052,"alerts":null,"elevation":[]}],"notes":null,"alerts":null,"routeShortName":null,"routeLongName":null,"boardRule":null,"alightRule":null,"rentedBike":false,"duration":2400.0}]},{"id":13673,"trip_part_id":3460,"mode_id":1,"service_id":3,"server_status":200,"server_message":null,"duration":2899,"walk_time":653,"transit_time":2244,"wait_time":2,"walk_distance":843.2516314673696,"transfers":1,"count":null,"legs":"---\n- startTime: 1435191906000\n  endTime: 1435192499000\n  departureDelay: 0\n  arrivalDelay: 0\n  realTime: false\n  isNonExactFrequency: \n  headway: \n  distance: 763.3969315504737\n  from:\n    name: Erlen Drive\n    stopId: \n    stopCode: \n    platformCode: \n    lon: -76.67966600881111\n    lat: 39.96437079412677\n    arrival: \n    departure: 1435191906000\n    orig: ''\n    zoneId: \n    stopIndex: \n  to:\n    name: Haines Rd K-Mart\n    stopId:\n      agencyId: '210'\n      id: '765018'\n    stopCode: \n    platformCode: \n    lon: -76.6832710419985\n    lat: 39.9597295760251\n    arrival: 1435192499000\n    departure: 1435192500000\n    orig: \n    zoneId: \n    stopIndex: \n  legGeometry:\n    points: ip|rF|n_sM~Fj@`DF`DTWbFlCd@dCh@lATKdBBV\\|DA@\n    levels: \n    length: 12\n  transitLeg: false\n  mode: WALK\n  route: ''\n  agencyName: \n  agencyUrl: \n  agencyTimeZoneOffset: -14400000\n  routeColor: \n  routeType: \n  routeId: \n  routeTextColor: \n  interlineWithPreviousLeg: false\n  tripShortName: \n  tripBlockId: \n  headsign: \n  agencyId: \n  tripId: \n  serviceDate: \n  intermediateStops: \n  steps:\n  - distance: 324.22113995854363\n    relativeDirection: DEPART\n    streetName: Erlen Drive\n    absoluteDirection: SOUTH\n    exit: \n    stayOn: false\n    area: false\n    bogusName: false\n    lon: -76.67966600881111\n    lat: 39.96437079412677\n    alerts: \n    elevation: []\n  - distance: 98.53025812689052\n    relativeDirection: RIGHT\n    streetName: Raleigh Drive\n    absoluteDirection: WEST\n    exit: \n    stayOn: false\n    area: false\n    bogusName: false\n    lon: -76.6800351\n    lat: 39.9614712\n    alerts: \n    elevation: []\n  - distance: 201.8719325153749\n    relativeDirection: LEFT\n    streetName: Haines Road\n    absoluteDirection: SOUTH\n    exit: \n    stayOn: false\n    area: false\n    bogusName: false\n    lon: -76.68118\n    lat: 39.9615941\n    alerts: \n    elevation: []\n  - distance: 138.77360094966465\n    relativeDirection: RIGHT\n    streetName: service road\n    absoluteDirection: WEST\n    exit: \n    stayOn: false\n    area: false\n    bogusName: true\n    lon: -76.6816898\n    lat: 39.9598213\n    alerts: \n    elevation: []\n  notes: \n  alerts: \n  routeShortName: \n  routeLongName: \n  boardRule: \n  alightRule: \n  rentedBike: false\n  duration: 593.0\n- startTime: 1435192500000\n  endTime: 1435194000000\n  departureDelay: 0\n  arrivalDelay: 0\n  realTime: false\n  isNonExactFrequency: \n  headway: \n  distance: 4999.767934170017\n  from:\n    name: Haines Rd K-Mart\n    stopId:\n      agencyId: '210'\n      id: '765018'\n    stopCode: \n    platformCode: \n    lon: -76.683279\n    lat: 39.959727\n    arrival: 1435192499000\n    departure: 1435192500000\n    orig: \n    zoneId: '0'\n    stopIndex: 0\n  to:\n    name: Transfer Center\n    stopId:\n      agencyId: '210'\n      id: '765237'\n    stopCode: \n    platformCode: \n    lon: -76.731524\n    lat: 39.959945\n    arrival: 1435194000000\n    departure: 1435194000000\n    orig: \n    zoneId: '0'\n    stopIndex: 16\n  legGeometry:\n    points: is{rFne`sMBA]}DVyBpDt@`B`@LdGBhC@p@BlB?fA?pB?hDQbKOpBEjEOfGAp@i@zNAh@]nGY~Ha@lIEz@MpBQfEMtBC\\OfAm@dCoCjLCDyClMXhQb@bS??Bn@PvI@h@JrDFbD@jB@Zi@HYLq@^w@L_BSoAKeAEoCVS@uAb@aEjBmCrAaDbBRPTZDJFN`CnLFXf@hCR`ADNj@dD^bBZvAz@fEPt@Jf@^`B|@fE^fB^bBr@nDLf@A?hBhJzEqBtEmB\\xAfAG\n    levels: \n    length: 83\n  transitLeg: true\n  mode: BUS\n  route: 5E\n  agencyName: \n  agencyUrl: \n  agencyTimeZoneOffset: -14400000\n  routeColor: DB7093\n  routeType: 3\n  routeId: '1271'\n  routeTextColor: '000000'\n  interlineWithPreviousLeg: false\n  tripShortName: \n  tripBlockId: \n  headsign: 5e Downtown\n  agencyId: '210'\n  tripId: 54067A1024B1797\n  serviceDate: '20150624'\n  intermediateStops: \n  steps: []\n  notes: \n  alerts: \n  routeShortName: 5E\n  routeLongName: Haines Rd  Kmart  Greensprings\n  boardRule: \n  alightRule: \n  rentedBike: false\n  duration: 1500.0\n- startTime: 1435194000000\n  endTime: 1435194744000\n  departureDelay: 0\n  arrivalDelay: 0\n  realTime: false\n  isNonExactFrequency: \n  headway: \n  distance: 3518.2812630961444\n  from:\n    name: Transfer Center\n    stopId:\n      agencyId: '210'\n      id: '765237'\n    stopCode: \n    platformCode: \n    lon: -76.731524\n    lat: 39.959945\n    arrival: 1435194000000\n    departure: 1435194000000\n    orig: \n    zoneId: '0'\n    stopIndex: 0\n  to:\n    name: W Market At Clinton St Ob\n    stopId:\n      agencyId: '210'\n      id: '765390'\n    stopCode: \n    platformCode: \n    lon: -76.766975\n    lat: 39.953165\n    arrival: 1435194744000\n    departure: 1435194745000\n    orig: \n    zoneId: '0'\n    stopIndex: 16\n  legGeometry:\n    points: qt{rFxsisMz@@o@{CvGkCtDnQA@BJZjBtApGPp@Nh@p@vCrA|FXvAl@nCDZFf@r@hDP~@xAtGJd@nBfJDTlBlIhAvFFXh@|Bx@`EKD}@\\cA`@zArHaA^{@^OFbAxEDPjBdJ?BfCxLHZfAjFjAlFHZgAb@o@X_@LkCRgDRDzARtHDvAPhHBf@TdIZjKBX\n    levels: \n    length: 57\n  transitLeg: true\n  mode: BUS\n  route: 5W\n  agencyName: \n  agencyUrl: \n  agencyTimeZoneOffset: -14400000\n  routeColor: '800080'\n  routeType: 3\n  routeId: '1270'\n  routeTextColor: FFFFFF\n  interlineWithPreviousLeg: false\n  tripShortName: \n  tripBlockId: \n  headsign: West York\n  agencyId: '210'\n  tripId: 53988A1024B1797\n  serviceDate: '20150624'\n  intermediateStops: \n  steps: []\n  notes: \n  alerts: \n  routeShortName: 5W\n  routeLongName: West York  West York Ind Park\n  boardRule: \n  alightRule: \n  rentedBike: false\n  duration: 744.0\n- startTime: 1435194745000\n  endTime: 1435194805000\n  departureDelay: 0\n  arrivalDelay: 0\n  realTime: false\n  isNonExactFrequency: \n  headway: \n  distance: 79.71899244898218\n  from:\n    name: W Market At Clinton St Ob\n    stopId:\n      agencyId: '210'\n      id: '765390'\n    stopCode: \n    platformCode: \n    lon: -76.76696635238902\n    lat: 39.95310085572663\n    arrival: 1435194744000\n    departure: 1435194745000\n    orig: \n    zoneId: \n    stopIndex: \n  to:\n    name: West Market Street\n    stopId: \n    stopCode: \n    platformCode: \n    lon: -76.76788573568848\n    lat: 39.95297156023158\n    arrival: 1435194805000\n    departure: \n    orig: ''\n    zoneId: \n    stopIndex: \n  legGeometry:\n    points: \"{izrFpppsMPzBFz@\"\n    levels: \n    length: 3\n  transitLeg: false\n  mode: WALK\n  route: ''\n  agencyName: \n  agencyUrl: \n  agencyTimeZoneOffset: -14400000\n  routeColor: \n  routeType: \n  routeId: \n  routeTextColor: \n  interlineWithPreviousLeg: false\n  tripShortName: \n  tripBlockId: \n  headsign: \n  agencyId: \n  tripId: \n  serviceDate: \n  intermediateStops: \n  steps:\n  - distance: 79.71899244898218\n    relativeDirection: DEPART\n    streetName: West Market Street\n    absoluteDirection: WEST\n    exit: \n    stayOn: false\n    area: false\n    bogusName: false\n    lon: -76.76696635238902\n    lat: 39.95310085572663\n    alerts: \n    elevation: []\n  notes: \n  alerts: \n  routeShortName: \n  routeLongName: \n  boardRule: \n  alightRule: \n  rentedBike: false\n  duration: 60.0\n","cost":"1.6","hidden":false,"created_at":"2015-06-15T16:14:11.650-04:00","updated_at":"2015-06-15T16:14:11.677-04:00","ride_count":null,"external_info":null,"match_score":-0.09999999999999998,"missing_information":false,"accommodation_mismatch":false,"missing_information_text":null,"date_mismatch":false,"time_mismatch":false,"too_late":false,"missing_accommodations":"","cost_comments":null,"selected":null,"start_time":"2015-06-24T20:25:06.000-04:00","end_time":"2015-06-24T21:13:25.000-04:00","is_bookable":false,"booking_confirmation":null,"duration_estimated":false,"map_image":{"url":null},"too_early":false,"returned_mode_code":"mode_transit","order_xml":null,"discounts":null,"segment_index":1,"start_location":{"address_components":[{"long_name":"701 Erlen Drive","short_name":"701 Erlen Drive","types":["street_address"]},{"long_name":"York","short_name":"York","types":["locality","political"]},{"long_name":"Pennsylvania","short_name":"Pennsylvania","types":["administrative_area_level_1","political"]},{"long_name":"17402","short_name":"17402","types":["postal_code"]}],"formatted_address":"701 Erlen Drive, York, Pennsylvania 17402","geometry":{"location":{"lat":39.964296,"lng":-76.678936}},"id":4320,"name":"East York Elementary School","scope":"user"},"end_location":{"address_components":[{"long_name":"1829 W Market St","short_name":"1829 W Market St","types":["street_address"]},{"long_name":"York","short_name":"York","types":["locality","political"]},{"long_name":"Pennsylvania","short_name":"Pennsylvania","types":["administrative_area_level_1","political"]},{"long_name":"17404","short_name":"17404","types":["postal_code"]}],"formatted_address":"1829 W Market St, York, Pennsylvania 17404","geometry":{"location":{"lat":39.953249,"lng":-76.7679579}},"id":4319,"name":"1829 W Market St","scope":"user"},"prebooking_questions":[{"question":"Will you be traveling with an approved escort","choices":[true,false],"code":"assistant"},{"question":"How many children or family members will be traveling with you?","choices":[0,1,2],"code":"children"}],"bookable":false,"json_legs":[{"startTime":1435191906000,"endTime":1435192499000,"departureDelay":0,"arrivalDelay":0,"realTime":false,"isNonExactFrequency":null,"headway":null,"distance":763.3969315504737,"from":{"name":"Erlen Drive","stopId":null,"stopCode":null,"platformCode":null,"lon":-76.67966600881111,"lat":39.96437079412677,"arrival":null,"departure":1435191906000,"orig":"","zoneId":null,"stopIndex":null},"to":{"name":"Haines Rd K-Mart","stopId":{"agencyId":"210","id":"765018"},"stopCode":null,"platformCode":null,"lon":-76.6832710419985,"lat":39.9597295760251,"arrival":1435192499000,"departure":1435192500000,"orig":null,"zoneId":null,"stopIndex":null},"legGeometry":{"points":"ip|rF|n_sM~Fj@`DF`DTWbFlCd@dCh@lATKdBBV\\|DA@","levels":null,"length":12},"transitLeg":false,"mode":"WALK","route":"","agencyName":null,"agencyUrl":null,"agencyTimeZoneOffset":-14400000,"routeColor":null,"routeType":null,"routeId":null,"routeTextColor":null,"interlineWithPreviousLeg":false,"tripShortName":null,"tripBlockId":null,"headsign":null,"agencyId":null,"tripId":null,"serviceDate":null,"intermediateStops":null,"steps":[{"distance":324.22113995854363,"relativeDirection":"DEPART","streetName":"Erlen Drive","absoluteDirection":"SOUTH","exit":null,"stayOn":false,"area":false,"bogusName":false,"lon":-76.67966600881111,"lat":39.96437079412677,"alerts":null,"elevation":[]},{"distance":98.53025812689052,"relativeDirection":"RIGHT","streetName":"Raleigh Drive","absoluteDirection":"WEST","exit":null,"stayOn":false,"area":false,"bogusName":false,"lon":-76.6800351,"lat":39.9614712,"alerts":null,"elevation":[]},{"distance":201.8719325153749,"relativeDirection":"LEFT","streetName":"Haines Road","absoluteDirection":"SOUTH","exit":null,"stayOn":false,"area":false,"bogusName":false,"lon":-76.68118,"lat":39.9615941,"alerts":null,"elevation":[]},{"distance":138.77360094966465,"relativeDirection":"RIGHT","streetName":"service road","absoluteDirection":"WEST","exit":null,"stayOn":false,"area":false,"bogusName":true,"lon":-76.6816898,"lat":39.9598213,"alerts":null,"elevation":[]}],"notes":null,"alerts":null,"routeShortName":null,"routeLongName":null,"boardRule":null,"alightRule":null,"rentedBike":false,"duration":593.0},{"startTime":1435192500000,"endTime":1435194000000,"departureDelay":0,"arrivalDelay":0,"realTime":false,"isNonExactFrequency":null,"headway":null,"distance":4999.767934170017,"from":{"name":"Haines Rd K-Mart","stopId":{"agencyId":"210","id":"765018"},"stopCode":null,"platformCode":null,"lon":-76.683279,"lat":39.959727,"arrival":1435192499000,"departure":1435192500000,"orig":null,"zoneId":"0","stopIndex":0},"to":{"name":"Transfer Center","stopId":{"agencyId":"210","id":"765237"},"stopCode":null,"platformCode":null,"lon":-76.731524,"lat":39.959945,"arrival":1435194000000,"departure":1435194000000,"orig":null,"zoneId":"0","stopIndex":16},"legGeometry":{"points":"is{rFne`sMBA]}DVyBpDt@`B`@LdGBhC@p@BlB?fA?pB?hDQbKOpBEjEOfGAp@i@zNAh@]nGY~Ha@lIEz@MpBQfEMtBC\\OfAm@dCoCjLCDyClMXhQb@bS??Bn@PvI@h@JrDFbD@jB@Zi@HYLq@^w@L_BSoAKeAEoCVS@uAb@aEjBmCrAaDbBRPTZDJFN`CnLFXf@hCR`ADNj@dD^bBZvAz@fEPt@Jf@^`B|@fE^fB^bBr@nDLf@A?hBhJzEqBtEmB\\xAfAG","levels":null,"length":83},"transitLeg":true,"mode":"BUS","route":"5E","agencyName":null,"agencyUrl":null,"agencyTimeZoneOffset":-14400000,"routeColor":"DB7093","routeType":3,"routeId":"1271","routeTextColor":"000000","interlineWithPreviousLeg":false,"tripShortName":null,"tripBlockId":null,"headsign":"5e Downtown","agencyId":"210","tripId":"54067A1024B1797","serviceDate":"20150624","intermediateStops":null,"steps":[],"notes":null,"alerts":null,"routeShortName":"5E","routeLongName":"Haines Rd  Kmart  Greensprings","boardRule":null,"alightRule":null,"rentedBike":false,"duration":1500.0},{"startTime":1435194000000,"endTime":1435194744000,"departureDelay":0,"arrivalDelay":0,"realTime":false,"isNonExactFrequency":null,"headway":null,"distance":3518.2812630961444,"from":{"name":"Transfer Center","stopId":{"agencyId":"210","id":"765237"},"stopCode":null,"platformCode":null,"lon":-76.731524,"lat":39.959945,"arrival":1435194000000,"departure":1435194000000,"orig":null,"zoneId":"0","stopIndex":0},"to":{"name":"W Market At Clinton St Ob","stopId":{"agencyId":"210","id":"765390"},"stopCode":null,"platformCode":null,"lon":-76.766975,"lat":39.953165,"arrival":1435194744000,"departure":1435194745000,"orig":null,"zoneId":"0","stopIndex":16},"legGeometry":{"points":"qt{rFxsisMz@@o@{CvGkCtDnQA@BJZjBtApGPp@Nh@p@vCrA|FXvAl@nCDZFf@r@hDP~@xAtGJd@nBfJDTlBlIhAvFFXh@|Bx@`EKD}@\\cA`@zArHaA^{@^OFbAxEDPjBdJ?BfCxLHZfAjFjAlFHZgAb@o@X_@LkCRgDRDzARtHDvAPhHBf@TdIZjKBX","levels":null,"length":57},"transitLeg":true,"mode":"BUS","route":"5W","agencyName":null,"agencyUrl":null,"agencyTimeZoneOffset":-14400000,"routeColor":"800080","routeType":3,"routeId":"1270","routeTextColor":"FFFFFF","interlineWithPreviousLeg":false,"tripShortName":null,"tripBlockId":null,"headsign":"West York","agencyId":"210","tripId":"53988A1024B1797","serviceDate":"20150624","intermediateStops":null,"steps":[],"notes":null,"alerts":null,"routeShortName":"5W","routeLongName":"West York  West York Ind Park","boardRule":null,"alightRule":null,"rentedBike":false,"duration":744.0},{"startTime":1435194745000,"endTime":1435194805000,"departureDelay":0,"arrivalDelay":0,"realTime":false,"isNonExactFrequency":null,"headway":null,"distance":79.71899244898218,"from":{"name":"W Market At Clinton St Ob","stopId":{"agencyId":"210","id":"765390"},"stopCode":null,"platformCode":null,"lon":-76.76696635238902,"lat":39.95310085572663,"arrival":1435194744000,"departure":1435194745000,"orig":null,"zoneId":null,"stopIndex":null},"to":{"name":"West Market Street","stopId":null,"stopCode":null,"platformCode":null,"lon":-76.76788573568848,"lat":39.95297156023158,"arrival":1435194805000,"departure":null,"orig":"","zoneId":null,"stopIndex":null},"legGeometry":{"points":"{izrFpppsMPzBFz@","levels":null,"length":3},"transitLeg":false,"mode":"WALK","route":"","agencyName":null,"agencyUrl":null,"agencyTimeZoneOffset":-14400000,"routeColor":null,"routeType":null,"routeId":null,"routeTextColor":null,"interlineWithPreviousLeg":false,"tripShortName":null,"tripBlockId":null,"headsign":null,"agencyId":null,"tripId":null,"serviceDate":null,"intermediateStops":null,"steps":[{"distance":79.71899244898218,"relativeDirection":"DEPART","streetName":"West Market Street","absoluteDirection":"WEST","exit":null,"stayOn":false,"area":false,"bogusName":false,"lon":-76.76696635238902,"lat":39.95310085572663,"alerts":null,"elevation":[]}],"notes":null,"alerts":null,"routeShortName":null,"routeLongName":null,"boardRule":null,"alightRule":null,"rentedBike":false,"duration":60.0}]}]}
