{"trip_id":2056,"trip_token":null,"itineraries":[{"id":14589,"trip_part_id":3697,"mode_id":2,"service_id":2,"server_status":200,"server_message":null,"duration":null,"walk_time":0,"transit_time":null,"wait_time":null,"walk_distance":0.0,"transfers":null,"count":null,"legs":null,"cost":null,"hidden":false,"created_at":"2015-06-26T20:56:57.167-04:00","updated_at":"2015-06-26T20:56:57.167-04:00","ride_count":null,"external_info":null,"match_score":0.25,"missing_information":true,"accommodation_mismatch":false,"missing_information_text":"disabled_missing_info:ada_eligible_missing_info:matp_missing_info:age_min60","date_mismatch":false,"time_mismatch":false,"too_late":false,"missing_accommodations":"","cost_comments":null,"selected":null,"start_time":null,"end_time":null,"is_bookable":false,"booking_confirmation":null,"duration_estimated":false,"map_image":{"url":null},"too_early":false,"returned_mode_code":"mode_paratransit","order_xml":null,"discounts":[{"fare":2.35,"comment":null,"funding_source":"Lottery","base_fare":null},{"fare":2.35,"comment":null,"funding_source":"PWD","base_fare":null},{"fare":3.2,"comment":null,"funding_source":"ADAYORK1","base_fare":null},{"fare":15.65,"comment":null,"funding_source":"Gen Pub","base_fare":null}],"segment_index":0,"start_location":{"address_components":[{"long_name":"1800 Bannister Street","short_name":"1800 Bannister Street","types":["street_address"]},{"long_name":"York","short_name":"York","types":["locality","political"]},{"long_name":"Pennsylvania","short_name":"Pennsylvania","types":["administrative_area_level_1","political"]},{"long_name":"17404","short_name":"17404","types":["postal_code"]}],"formatted_address":"1800 Bannister Street, York, Pennsylvania 17404","geometry":{"location":{"lat":39.958989,"lng":-76.763218}},"id":4717,"name":"West York Area High School","scope":"user"},"end_location":{"address_components":[{"long_name":"701 Erlen Drive","short_name":"701 Erlen Drive","types":["street_address"]},{"long_name":"York","short_name":"York","types":["locality","political"]},{"long_name":"Pennsylvania","short_name":"Pennsylvania","types":["administrative_area_level_1","political"]},{"long_name":"17402","short_name":"17402","types":["postal_code"]}],"formatted_address":"701 Erlen Drive, York, Pennsylvania 17402","geometry":{"location":{"lat":39.964296,"lng":-76.678936}},"id":4718,"name":"East York Elementary School","scope":"user"},"prebooking_questions":[{"question":"Will you be traveling with an approved escort","choices":[true,false],"code":"assistant"},{"question":"How many children or family members will be traveling with you?","choices":[0,1,2],"code":"children"}],"bookable":false,"json_legs":null},{"id":14590,"trip_part_id":3697,"mode_id":2,"service_id":7,"server_status":200,"server_message":null,"duration":null,"walk_time":0,"transit_time":null,"wait_time":null,"walk_distance":0.0,"transfers":null,"count":null,"legs":null,"cost":null,"hidden":false,"created_at":"2015-06-26T20:57:04.995-04:00","updated_at":"2015-06-26T20:57:04.995-04:00","ride_count":null,"external_info":null,"match_score":0.0,"missing_information":false,"accommodation_mismatch":false,"missing_information_text":"","date_mismatch":false,"time_mismatch":false,"too_late":false,"missing_accommodations":"","cost_comments":null,"selected":null,"start_time":null,"end_time":null,"is_bookable":false,"booking_confirmation":null,"duration_estimated":false,"map_image":{"url":null},"too_early":false,"returned_mode_code":"mode_paratransit","order_xml":null,"discounts":[{"fare":2.35,"comment":null,"funding_source":"Lottery","base_fare":null},{"fare":2.35,"comment":null,"funding_source":"PWD","base_fare":null},{"fare":3.2,"comment":null,"funding_source":"ADAYORK1","base_fare":null}],"segment_index":0,"start_location":{"address_components":[{"long_name":"1800 Bannister Street","short_name":"1800 Bannister Street","types":["street_address"]},{"long_name":"York","short_name":"York","types":["locality","political"]},{"long_name":"Pennsylvania","short_name":"Pennsylvania","types":["administrative_area_level_1","political"]},{"long_name":"17404","short_name":"17404","types":["postal_code"]}],"formatted_address":"1800 Bannister Street, York, Pennsylvania 17404","geometry":{"location":{"lat":39.958989,"lng":-76.763218}},"id":4717,"name":"West York Area High School","scope":"user"},"end_location":{"address_components":[{"long_name":"701 Erlen Drive","short_name":"701 Erlen Drive","types":["street_address"]},{"long_name":"York","short_name":"York","types":["locality","political"]},{"long_name":"Pennsylvania","short_name":"Pennsylvania","types":["administrative_area_level_1","political"]},{"long_name":"17402","short_name":"17402","types":["postal_code"]}],"formatted_address":"701 Erlen Drive, York, Pennsylvania 17402","geometry":{"location":{"lat":39.964296,"lng":-76.678936}},"id":4718,"name":"East York Elementary School","scope":"user"},"prebooking_questions":[{"question":"Will you be traveling with an approved escort","choices":[true,false],"code":"assistant"},{"question":"How many children or family members will be traveling with you?","choices":[0,1,2],"code":"children"}],"bookable":false,"json_legs":null},{"id":14589,"trip_part_id":3697,"mode_id":2,"service_id":2,"server_status":200,"server_message":null,"duration":4308,"walk_time":0,"transit_time":null,"wait_time":null,"walk_distance":0.0,"transfers":null,"count":null,"legs":null,"cost":null,"hidden":false,"created_at":"2015-06-26T20:56:57.167-04:00","updated_at":"2015-06-26T20:57:06.555-04:00","ride_count":null,"external_info":null,"match_score":0.25,"missing_information":true,"accommodation_mismatch":false,"missing_information_text":"disabled_missing_info:ada_eligible_missing_info:matp_missing_info:age_min60","date_mismatch":false,"time_mismatch":false,"too_late":false,"missing_accommodations":"","cost_comments":null,"selected":null,"start_time":"2015-06-29T14:44:33.000-04:00","end_time":"2015-06-29T15:56:21.000-04:00","is_bookable":false,"booking_confirmation":null,"duration_estimated":true,"map_image":{"url":null},"too_early":false,"returned_mode_code":"mode_paratransit","order_xml":null,"discounts":[{"fare":2.35,"comment":null,"funding_source":"Lottery","base_fare":null},{"fare":2.35,"comment":null,"funding_source":"PWD","base_fare":null},{"fare":3.2,"comment":null,"funding_source":"ADAYORK1","base_fare":null},{"fare":15.65,"comment":null,"funding_source":"Gen Pub","base_fare":null}],"segment_index":0,"start_location":{"address_components":[{"long_name":"1800 Bannister Street","short_name":"1800 Bannister Street","types":["street_address"]},{"long_name":"York","short_name":"York","types":["locality","political"]},{"long_name":"Pennsylvania","short_name":"Pennsylvania","types":["administrative_area_level_1","political"]},{"long_name":"17404","short_name":"17404","types":["postal_code"]}],"formatted_address":"1800 Bannister Street, York, Pennsylvania 17404","geometry":{"location":{"lat":39.958989,"lng":-76.763218}},"id":4717,"name":"West York Area High School","scope":"user"},"end_location":{"address_components":[{"long_name":"701 Erlen Drive","short_name":"701 Erlen Drive","types":["street_address"]},{"long_name":"York","short_name":"York","types":["locality","political"]},{"long_name":"Pennsylvania","short_name":"Pennsylvania","types":["administrative_area_level_1","political"]},{"long_name":"17402","short_name":"17402","types":["postal_code"]}],"formatted_address":"701 Erlen Drive, York, Pennsylvania 17402","geometry":{"location":{"lat":39.964296,"lng":-76.67893600000002}},"id":4718,"name":"East York Elementary School","scope":"user"},"prebooking_questions":[{"question":"Will you be traveling with an approved escort","choices":[true,false],"code":"assistant"},{"question":"How many children or family members will be traveling with you?","choices":[0,1,2],"code":"children"}],"bookable":false,"json_legs":null},{"id":14590,"trip_part_id":3697,"mode_id":2,"service_id":7,"server_status":200,"server_message":null,"duration":4308,"walk_time":0,"transit_time":null,"wait_time":null,"walk_distance":0.0,"transfers":null,"count":null,"legs":null,"cost":null,"hidden":false,"created_at":"2015-06-26T20:57:04.995-04:00","updated_at":"2015-06-26T20:57:06.575-04:00","ride_count":null,"external_info":null,"match_score":0.0,"missing_information":false,"accommodation_mismatch":false,"missing_information_text":"","date_mismatch":false,"time_mismatch":false,"too_late":false,"missing_accommodations":"","cost_comments":null,"selected":null,"start_time":"2015-06-29T14:44:33.000-04:00","end_time":"2015-06-29T15:56:21.000-04:00","is_bookable":false,"booking_confirmation":null,"duration_estimated":true,"map_image":{"url":null},"too_early":false,"returned_mode_code":"mode_paratransit","order_xml":null,"discounts":[{"fare":2.35,"comment":null,"funding_source":"Lottery","base_fare":null},{"fare":2.35,"comment":null,"funding_source":"PWD","base_fare":null},{"fare":3.2,"comment":null,"funding_source":"ADAYORK1","base_fare":null}],"segment_index":0,"start_location":{"address_components":[{"long_name":"1800 Bannister Street","short_name":"1800 Bannister Street","types":["street_address"]},{"long_name":"York","short_name":"York","types":["locality","political"]},{"long_name":"Pennsylvania","short_name":"Pennsylvania","types":["administrative_area_level_1","political"]},{"long_name":"17404","short_name":"17404","types":["postal_code"]}],"formatted_address":"1800 Bannister Street, York, Pennsylvania 17404","geometry":{"location":{"lat":39.958989,"lng":-76.763218}},"id":4717,"name":"West York Area High School","scope":"user"},"end_location":{"address_components":[{"long_name":"701 Erlen Drive","short_name":"701 Erlen Drive","types":["street_address"]},{"long_name":"York","short_name":"York","types":["locality","political"]},{"long_name":"Pennsylvania","short_name":"Pennsylvania","types":["administrative_area_level_1","political"]},{"long_name":"17402","short_name":"17402","types":["postal_code"]}],"formatted_address":"701 Erlen Drive, York, Pennsylvania 17402","geometry":{"location":{"lat":39.964296,"lng":-76.67893600000002}},"id":4718,"name":"East York Elementary School","scope":"user"},"prebooking_questions":[{"question":"Will you be traveling with an approved escort","choices":[true,false],"code":"assistant"},{"question":"How many children or family members will be traveling with you?","choices":[0,1,2],"code":"children"}],"bookable":false,"json_legs":null},{"id":14591,"trip_part_id":3697,"mode_id":1,"service_id":3,"server_status":200,"server_message":null,"duration":3934,"walk_time":3032,"transit_time":900,"wait_time":2,"walk_distance":3936.5020765002146,"transfers":0,"count":null,"legs":"---\n- startTime: 1435603460000\n  endTime: 1435605899000\n  departureDelay: 0\n  arrivalDelay: 0\n  realTime: false\n  isNonExactFrequency: \n  headway: \n  distance: 3172.699886659569\n  from:\n    name: service road\n    stopId: \n    stopCode: \n    platformCode: \n    lon: -76.7633366\n    lat: 39.9591893\n    arrival: \n    departure: 1435603460000\n    orig: ''\n    zoneId: \n    stopIndex: \n  to:\n    name: Transfer Center\n    stopId:\n      agencyId: '210'\n      id: '765237'\n    stopCode: \n    platformCode: \n    lon: -76.73144552366078\n    lat: 39.95969730580617\n    arrival: 1435605899000\n    departure: 1435605900000\n    orig: \n    zoneId: \n    stopIndex: \n  legGeometry:\n    points: \"{o{rFzyosMIOIMKKKEMAm@@e@@KgEC}@UeK_DLSiH~BsKBMh@cC`@eBHa@l@}Bn@kCh@_Cr@cCj@_CBKFWPw@ZcAj@iCn@oCv@uCPi@DQh@_Cd@gBR{@Ry@d@eCo@aDnCkAdCiAMo@qBsJyAwGI_@qAiGG_@aAwEoBeJG[Kg@Q_AwB{JMg@iAkFg@{BCQWiA\"\n    levels: \n    length: 57\n  transitLeg: false\n  mode: WALK\n  route: ''\n  agencyName: \n  agencyUrl: \n  agencyTimeZoneOffset: -14400000\n  routeColor: \n  routeType: \n  routeId: \n  routeTextColor: \n  interlineWithPreviousLeg: false\n  tripShortName: \n  tripBlockId: \n  headsign: \n  agencyId: \n  tripId: \n  serviceDate: \n  intermediateStops: \n  steps:\n  - distance: 195.21231664460507\n    relativeDirection: DEPART\n    streetName: service road\n    absoluteDirection: NORTHEAST\n    exit: \n    stayOn: false\n    area: false\n    bogusName: false\n    lon: -76.7633366\n    lat: 39.9591893\n    alerts: \n    elevation: []\n  - distance: 166.2552711331465\n    relativeDirection: CONTINUE\n    streetName: White Street\n    absoluteDirection: EAST\n    exit: \n    stayOn: false\n    area: false\n    bogusName: false\n    lon: -76.7617945\n    lat: 39.9599766\n    alerts: \n    elevation: []\n  - distance: 88.85889525716554\n    relativeDirection: LEFT\n    streetName: North Highland Avenue\n    absoluteDirection: NORTH\n    exit: \n    stayOn: false\n    area: false\n    bogusName: false\n    lon: -76.7598493\n    lat: 39.9600884\n    alerts: \n    elevation: []\n  - distance: 127.32248217223012\n    relativeDirection: RIGHT\n    streetName: Bannister Street\n    absoluteDirection: EAST\n    exit: \n    stayOn: false\n    area: false\n    bogusName: false\n    lon: -76.7599137\n    lat: 39.960886\n    alerts: \n    elevation: []\n  - distance: 1154.7886194409039\n    relativeDirection: SLIGHTLY_RIGHT\n    streetName: Carlisle Avenue\n    absoluteDirection: EAST\n    exit: \n    stayOn: false\n    area: false\n    bogusName: false\n    lon: -76.7584255\n    lat: 39.9609858\n    alerts: \n    elevation: []\n  - distance: 73.50747021022647\n    relativeDirection: LEFT\n    streetName: West Market Street\n    absoluteDirection: EAST\n    exit: \n    stayOn: false\n    area: false\n    bogusName: false\n    lon: -76.7460416\n    lat: 39.95679\n    alerts:\n    - alertHeaderText:\n        translations:\n          en: no longer a state highway by 1987\n        someTranslation: no longer a state highway by 1987\n      alertDescriptionText: \n      alertUrl: \n      effectiveStartDate: \n    elevation: []\n  - distance: 167.64725077825054\n    relativeDirection: RIGHT\n    streetName: South Belvidere Avenue\n    absoluteDirection: SOUTH\n    exit: \n    stayOn: false\n    area: false\n    bogusName: false\n    lon: -76.7452392\n    lat: 39.9570323\n    alerts: \n    elevation: []\n  - distance: 1199.1075810230402\n    relativeDirection: LEFT\n    streetName: West King Street\n    absoluteDirection: EAST\n    exit: \n    stayOn: false\n    area: false\n    bogusName: false\n    lon: -76.7444804\n    lat: 39.9556414\n    alerts: \n    elevation: []\n  notes:\n  - text: no longer a state highway by 1987\n  alerts:\n  - alertHeaderText:\n      translations:\n        en: no longer a state highway by 1987\n      someTranslation: no longer a state highway by 1987\n    alertDescriptionText: \n    alertUrl: \n    effectiveStartDate: \n  routeShortName: \n  routeLongName: \n  boardRule: \n  alightRule: \n  rentedBike: false\n  duration: 2439.0\n- startTime: 1435605900000\n  endTime: 1435606800000\n  departureDelay: 0\n  arrivalDelay: 0\n  realTime: false\n  isNonExactFrequency: \n  headway: \n  distance: 4112.015514885083\n  from:\n    name: Transfer Center\n    stopId:\n      agencyId: '210'\n      id: '765237'\n    stopCode: \n    platformCode: \n    lon: -76.731524\n    lat: 39.959945\n    arrival: 1435605899000\n    departure: 1435605900000\n    orig: \n    zoneId: '0'\n    stopIndex: 0\n  to:\n    name: Haines Rd K-Mart\n    stopId:\n      agencyId: '210'\n      id: '765018'\n    stopCode: \n    platformCode: \n    lon: -76.683279\n    lat: 39.959727\n    arrival: 1435606800000\n    departure: 1435606801000\n    orig: \n    zoneId: '0'\n    stopIndex: 1\n  legGeometry:\n    points: ut{rFzsisM~@AyGc\\dPaHmEsScHm]iBu{@@aA`Jw_@TuBnDey@TwH?oFZyEP{IH_@FyECmFWkKsH{AOtBe@Hb@|D\\K\n    levels: \n    length: 24\n  transitLeg: true\n  mode: BUS\n  route: 83N\n  agencyName: \n  agencyUrl: \n  agencyTimeZoneOffset: -14400000\n  routeColor: 7685B8\n  routeType: 3\n  routeId: '1263'\n  routeTextColor: FFFFFF\n  interlineWithPreviousLeg: false\n  tripShortName: \n  tripBlockId: \n  headsign: HACC Campus\n  agencyId: '210'\n  tripId: 49160A1024B1797\n  serviceDate: '20150629'\n  intermediateStops: \n  steps: []\n  notes: \n  alerts: \n  routeShortName: 83N\n  routeLongName: Harrisburg Express\n  boardRule: \n  alightRule: \n  rentedBike: false\n  duration: 900.0\n- startTime: 1435606801000\n  endTime: 1435607394000\n  departureDelay: 0\n  arrivalDelay: 0\n  realTime: false\n  isNonExactFrequency: \n  headway: \n  distance: 763.3969315504738\n  from:\n    name: Haines Rd K-Mart\n    stopId:\n      agencyId: '210'\n      id: '765018'\n    stopCode: \n    platformCode: \n    lon: -76.6832710419985\n    lat: 39.9597295760251\n    arrival: 1435606800000\n    departure: 1435606801000\n    orig: \n    zoneId: \n    stopIndex: \n  to:\n    name: Erlen Drive\n    stopId: \n    stopCode: \n    platformCode: \n    lon: -76.67966600881111\n    lat: 39.96437079412677\n    arrival: 1435607394000\n    departure: \n    orig: ''\n    zoneId: \n    stopIndex: \n  legGeometry:\n    points: gs{rFne`sM@A]}DCWJeBmAUeCi@mCe@VcFaDUaDG_Gk@\n    levels: \n    length: 12\n  transitLeg: false\n  mode: WALK\n  route: ''\n  agencyName: \n  agencyUrl: \n  agencyTimeZoneOffset: -14400000\n  routeColor: \n  routeType: \n  routeId: \n  routeTextColor: \n  interlineWithPreviousLeg: false\n  tripShortName: \n  tripBlockId: \n  headsign: \n  agencyId: \n  tripId: \n  serviceDate: \n  intermediateStops: \n  steps:\n  - distance: 138.77360094966463\n    relativeDirection: DEPART\n    streetName: service road\n    absoluteDirection: SOUTH\n    exit: \n    stayOn: false\n    area: false\n    bogusName: false\n    lon: -76.6832710419985\n    lat: 39.9597295760251\n    alerts: \n    elevation: []\n  - distance: 201.8719325153749\n    relativeDirection: LEFT\n    streetName: Haines Road\n    absoluteDirection: NORTH\n    exit: \n    stayOn: false\n    area: false\n    bogusName: false\n    lon: -76.6816898\n    lat: 39.9598213\n    alerts: \n    elevation: []\n  - distance: 98.53025812689052\n    relativeDirection: RIGHT\n    streetName: Raleigh Drive\n    absoluteDirection: EAST\n    exit: \n    stayOn: false\n    area: false\n    bogusName: false\n    lon: -76.68118\n    lat: 39.9615941\n    alerts: \n    elevation: []\n  - distance: 324.22113995854363\n    relativeDirection: LEFT\n    streetName: Erlen Drive\n    absoluteDirection: NORTH\n    exit: \n    stayOn: false\n    area: false\n    bogusName: false\n    lon: -76.6800351\n    lat: 39.9614712\n    alerts: \n    elevation: []\n  notes: \n  alerts: \n  routeShortName: \n  routeLongName: \n  boardRule: \n  alightRule: \n  rentedBike: false\n  duration: 593.0\n","cost":"3.5","hidden":false,"created_at":"2015-06-26T20:57:06.185-04:00","updated_at":"2015-06-26T20:57:06.584-04:00","ride_count":null,"external_info":null,"match_score":-0.3,"missing_information":false,"accommodation_mismatch":false,"missing_information_text":null,"date_mismatch":false,"time_mismatch":false,"too_late":false,"missing_accommodations":"","cost_comments":null,"selected":null,"start_time":"2015-06-29T14:44:20.000-04:00","end_time":"2015-06-29T15:49:54.000-04:00","is_bookable":false,"booking_confirmation":null,"duration_estimated":false,"map_image":{"url":null},"too_early":false,"returned_mode_code":"mode_transit","order_xml":null,"discounts":null,"segment_index":0,"start_location":{"address_components":[{"long_name":"1800 Bannister Street","short_name":"1800 Bannister Street","types":["street_address"]},{"long_name":"York","short_name":"York","types":["locality","political"]},{"long_name":"Pennsylvania","short_name":"Pennsylvania","types":["administrative_area_level_1","political"]},{"long_name":"17404","short_name":"17404","types":["postal_code"]}],"formatted_address":"1800 Bannister Street, York, Pennsylvania 17404","geometry":{"location":{"lat":39.958989,"lng":-76.763218}},"id":4717,"name":"West York Area High School","scope":"user"},"end_location":{"address_components":[{"long_name":"701 Erlen Drive","short_name":"701 Erlen Drive","types":["street_address"]},{"long_name":"York","short_name":"York","types":["locality","political"]},{"long_name":"Pennsylvania","short_name":"Pennsylvania","types":["administrative_area_level_1","political"]},{"long_name":"17402","short_name":"17402","types":["postal_code"]}],"formatted_address":"701 Erlen Drive, York, Pennsylvania 17402","geometry":{"location":{"lat":39.964296,"lng":-76.678936}},"id":4718,"name":"East York Elementary School","scope":"user"},"prebooking_questions":[{"question":"Will you be traveling with an approved escort","choices":[true,false],"code":"assistant"},{"question":"How many children or family members will be traveling with you?","choices":[0,1,2],"code":"children"}],"bookable":false,"json_legs":[{"startTime":1435603460000,"endTime":1435605899000,"departureDelay":0,"arrivalDelay":0,"realTime":false,"isNonExactFrequency":null,"headway":null,"distance":3172.699886659569,"from":{"name":"service road","stopId":null,"stopCode":null,"platformCode":null,"lon":-76.7633366,"lat":39.9591893,"arrival":null,"departure":1435603460000,"orig":"","zoneId":null,"stopIndex":null},"to":{"name":"Transfer Center","stopId":{"agencyId":"210","id":"765237"},"stopCode":null,"platformCode":null,"lon":-76.73144552366078,"lat":39.95969730580617,"arrival":1435605899000,"departure":1435605900000,"orig":null,"zoneId":null,"stopIndex":null},"legGeometry":{"points":"{o{rFzyosMIOIMKKKEMAm@@e@@KgEC}@UeK_DLSiH~BsKBMh@cC`@eBHa@l@}Bn@kCh@_Cr@cCj@_CBKFWPw@ZcAj@iCn@oCv@uCPi@DQh@_Cd@gBR{@Ry@d@eCo@aDnCkAdCiAMo@qBsJyAwGI_@qAiGG_@aAwEoBeJG[Kg@Q_AwB{JMg@iAkFg@{BCQWiA","levels":null,"length":57},"transitLeg":false,"mode":"WALK","route":"","agencyName":null,"agencyUrl":null,"agencyTimeZoneOffset":-14400000,"routeColor":null,"routeType":null,"routeId":null,"routeTextColor":null,"interlineWithPreviousLeg":false,"tripShortName":null,"tripBlockId":null,"headsign":null,"agencyId":null,"tripId":null,"serviceDate":null,"intermediateStops":null,"steps":[{"distance":195.21231664460507,"relativeDirection":"DEPART","streetName":"service road","absoluteDirection":"NORTHEAST","exit":null,"stayOn":false,"area":false,"bogusName":false,"lon":-76.7633366,"lat":39.9591893,"alerts":null,"elevation":[]},{"distance":166.2552711331465,"relativeDirection":"CONTINUE","streetName":"White Street","absoluteDirection":"EAST","exit":null,"stayOn":false,"area":false,"bogusName":false,"lon":-76.7617945,"lat":39.9599766,"alerts":null,"elevation":[]},{"distance":88.85889525716554,"relativeDirection":"LEFT","streetName":"North Highland Avenue","absoluteDirection":"NORTH","exit":null,"stayOn":false,"area":false,"bogusName":false,"lon":-76.7598493,"lat":39.9600884,"alerts":null,"elevation":[]},{"distance":127.32248217223012,"relativeDirection":"RIGHT","streetName":"Bannister Street","absoluteDirection":"EAST","exit":null,"stayOn":false,"area":false,"bogusName":false,"lon":-76.7599137,"lat":39.960886,"alerts":null,"elevation":[]},{"distance":1154.7886194409039,"relativeDirection":"SLIGHTLY_RIGHT","streetName":"Carlisle Avenue","absoluteDirection":"EAST","exit":null,"stayOn":false,"area":false,"bogusName":false,"lon":-76.7584255,"lat":39.9609858,"alerts":null,"elevation":[]},{"distance":73.50747021022647,"relativeDirection":"LEFT","streetName":"West Market Street","absoluteDirection":"EAST","exit":null,"stayOn":false,"area":false,"bogusName":false,"lon":-76.7460416,"lat":39.95679,"alerts":[{"alertHeaderText":{"translations":{"en":"no longer a state highway by 1987"},"someTranslation":"no longer a state highway by 1987"},"alertDescriptionText":null,"alertUrl":null,"effectiveStartDate":null}],"elevation":[]},{"distance":167.64725077825054,"relativeDirection":"RIGHT","streetName":"South Belvidere Avenue","absoluteDirection":"SOUTH","exit":null,"stayOn":false,"area":false,"bogusName":false,"lon":-76.7452392,"lat":39.9570323,"alerts":null,"elevation":[]},{"distance":1199.1075810230402,"relativeDirection":"LEFT","streetName":"West King Street","absoluteDirection":"EAST","exit":null,"stayOn":false,"area":false,"bogusName":false,"lon":-76.7444804,"lat":39.9556414,"alerts":null,"elevation":[]}],"notes":[{"text":"no longer a state highway by 1987"}],"alerts":[{"alertHeaderText":{"translations":{"en":"no longer a state highway by 1987"},"someTranslation":"no longer a state highway by 1987"},"alertDescriptionText":null,"alertUrl":null,"effectiveStartDate":null}],"routeShortName":null,"routeLongName":null,"boardRule":null,"alightRule":null,"rentedBike":false,"duration":2439.0},{"startTime":1435605900000,"endTime":1435606800000,"departureDelay":0,"arrivalDelay":0,"realTime":false,"isNonExactFrequency":null,"headway":null,"distance":4112.015514885083,"from":{"name":"Transfer Center","stopId":{"agencyId":"210","id":"765237"},"stopCode":null,"platformCode":null,"lon":-76.731524,"lat":39.959945,"arrival":1435605899000,"departure":1435605900000,"orig":null,"zoneId":"0","stopIndex":0},"to":{"name":"Haines Rd K-Mart","stopId":{"agencyId":"210","id":"765018"},"stopCode":null,"platformCode":null,"lon":-76.683279,"lat":39.959727,"arrival":1435606800000,"departure":1435606801000,"orig":null,"zoneId":"0","stopIndex":1},"legGeometry":{"points":"ut{rFzsisM~@AyGc\\dPaHmEsScHm]iBu{@@aA`Jw_@TuBnDey@TwH?oFZyEP{IH_@FyECmFWkKsH{AOtBe@Hb@|D\\K","levels":null,"length":24},"transitLeg":true,"mode":"BUS","route":"83N","agencyName":null,"agencyUrl":null,"agencyTimeZoneOffset":-14400000,"routeColor":"7685B8","routeType":3,"routeId":"1263","routeTextColor":"FFFFFF","interlineWithPreviousLeg":false,"tripShortName":null,"tripBlockId":null,"headsign":"HACC Campus","agencyId":"210","tripId":"49160A1024B1797","serviceDate":"20150629","intermediateStops":null,"steps":[],"notes":null,"alerts":null,"routeShortName":"83N","routeLongName":"Harrisburg Express","boardRule":null,"alightRule":null,"rentedBike":false,"duration":900.0},{"startTime":1435606801000,"endTime":1435607394000,"departureDelay":0,"arrivalDelay":0,"realTime":false,"isNonExactFrequency":null,"headway":null,"distance":763.3969315504738,"from":{"name":"Haines Rd K-Mart","stopId":{"agencyId":"210","id":"765018"},"stopCode":null,"platformCode":null,"lon":-76.6832710419985,"lat":39.9597295760251,"arrival":1435606800000,"departure":1435606801000,"orig":null,"zoneId":null,"stopIndex":null},"to":{"name":"Erlen Drive","stopId":null,"stopCode":null,"platformCode":null,"lon":-76.67966600881111,"lat":39.96437079412677,"arrival":1435607394000,"departure":null,"orig":"","zoneId":null,"stopIndex":null},"legGeometry":{"points":"gs{rFne`sM@A]}DCWJeBmAUeCi@mCe@VcFaDUaDG_Gk@","levels":null,"length":12},"transitLeg":false,"mode":"WALK","route":"","agencyName":null,"agencyUrl":null,"agencyTimeZoneOffset":-14400000,"routeColor":null,"routeType":null,"routeId":null,"routeTextColor":null,"interlineWithPreviousLeg":false,"tripShortName":null,"tripBlockId":null,"headsign":null,"agencyId":null,"tripId":null,"serviceDate":null,"intermediateStops":null,"steps":[{"distance":138.77360094966463,"relativeDirection":"DEPART","streetName":"service road","absoluteDirection":"SOUTH","exit":null,"stayOn":false,"area":false,"bogusName":false,"lon":-76.6832710419985,"lat":39.9597295760251,"alerts":null,"elevation":[]},{"distance":201.8719325153749,"relativeDirection":"LEFT","streetName":"Haines Road","absoluteDirection":"NORTH","exit":null,"stayOn":false,"area":false,"bogusName":false,"lon":-76.6816898,"lat":39.9598213,"alerts":null,"elevation":[]},{"distance":98.53025812689052,"relativeDirection":"RIGHT","streetName":"Raleigh Drive","absoluteDirection":"EAST","exit":null,"stayOn":false,"area":false,"bogusName":false,"lon":-76.68118,"lat":39.9615941,"alerts":null,"elevation":[]},{"distance":324.22113995854363,"relativeDirection":"LEFT","streetName":"Erlen Drive","absoluteDirection":"NORTH","exit":null,"stayOn":false,"area":false,"bogusName":false,"lon":-76.6800351,"lat":39.9614712,"alerts":null,"elevation":[]}],"notes":null,"alerts":null,"routeShortName":null,"routeLongName":null,"boardRule":null,"alightRule":null,"rentedBike":false,"duration":593.0}]},{"id":14592,"trip_part_id":3697,"mode_id":1,"service_id":3,"server_status":200,"server_message":null,"duration":4111,"walk_time":809,"transit_time":1800,"wait_time":1502,"walk_distance":1038.0392232887273,"transfers":1,"count":null,"legs":"---\n- startTime: 1435603283000\n  endTime: 1435603499000\n  departureDelay: 0\n  arrivalDelay: 0\n  realTime: false\n  isNonExactFrequency: \n  headway: \n  distance: 274.4320197275302\n  from:\n    name: service road\n    stopId: \n    stopCode: \n    platformCode: \n    lon: -76.7633366\n    lat: 39.9591893\n    arrival: \n    departure: 1435603283000\n    orig: ''\n    zoneId: \n    stopIndex: \n  to:\n    name: Bannister St At Seward Ib\n    stopId:\n      agencyId: '210'\n      id: '765383'\n    stopCode: \n    platformCode: \n    lon: -76.76322304443343\n    lat: 39.96070416002769\n    arrival: 1435603499000\n    departure: 1435603500000\n    orig: \n    zoneId: \n    stopIndex: \n  legGeometry:\n    points: \"{o{rFzyosM?R?RCPGRK\\\\ILGHI?I?IAIIEEAICKCMM?M?YFWBO@U@]?u@@EuB\"\n    levels: \n    length: 25\n  transitLeg: false\n  mode: WALK\n  route: ''\n  agencyName: \n  agencyUrl: \n  agencyTimeZoneOffset: -14400000\n  routeColor: \n  routeType: \n  routeId: \n  routeTextColor: \n  interlineWithPreviousLeg: false\n  tripShortName: \n  tripBlockId: \n  headsign: \n  agencyId: \n  tripId: \n  serviceDate: \n  intermediateStops: \n  steps:\n  - distance: 223.6672587997366\n    relativeDirection: DEPART\n    streetName: service road\n    absoluteDirection: WEST\n    exit: \n    stayOn: false\n    area: false\n    bogusName: false\n    lon: -76.7633366\n    lat: 39.9591893\n    alerts: \n    elevation: []\n  - distance: 50.7647609277936\n    relativeDirection: RIGHT\n    streetName: Bannister Street\n    absoluteDirection: EAST\n    exit: \n    stayOn: false\n    area: false\n    bogusName: false\n    lon: -76.763817\n    lat: 39.96067\n    alerts: \n    elevation: []\n  notes: \n  alerts: \n  routeShortName: \n  routeLongName: \n  boardRule: \n  alightRule: \n  rentedBike: false\n  duration: 216.0\n- startTime: 1435603500000\n  endTime: 1435604400000\n  departureDelay: 0\n  arrivalDelay: 0\n  realTime: false\n  isNonExactFrequency: \n  headway: \n  distance: 2845.5746582983893\n  from:\n    name: Bannister St At Seward Ib\n    stopId:\n      agencyId: '210'\n      id: '765383'\n    stopCode: \n    platformCode: \n    lon: -76.763222\n    lat: 39.960686\n    arrival: 1435603499000\n    departure: 1435603500000\n    orig: \n    zoneId: '0'\n    stopIndex: 7\n  to:\n    name: Transfer Center\n    stopId:\n      agencyId: '210'\n      id: '765237'\n    stopCode: \n    platformCode: \n    lon: -76.731524\n    lat: 39.959945\n    arrival: 1435604400000\n    departure: 1435605900000\n    orig: \n    zoneId: '0'\n    stopIndex: 16\n  legGeometry:\n    points: ky{rFdyosMOmGSgKSiHbCaLj@eCh@eCJa@`@{An@mCr@oCh@qBj@_CBKXoAZcAj@iCn@oCv@uCPi@DSh@_Cd@eBf@uBd@gCo@_DScAoBcJUcAcD{NOw@qDmQSaAyBwKa@cBCB}C_OvCgAZxAvAC\n    levels: \n    length: 40\n  transitLeg: true\n  mode: BUS\n  route: 1W\n  agencyName: \n  agencyUrl: \n  agencyTimeZoneOffset: -14400000\n  routeColor: FF0000\n  routeType: 3\n  routeId: '1264'\n  routeTextColor: '000000'\n  interlineWithPreviousLeg: false\n  tripShortName: \n  tripBlockId: \n  headsign: 1w Downtown\n  agencyId: '210'\n  tripId: 53771A1024B1797\n  serviceDate: '20150629'\n  intermediateStops: \n  steps: []\n  notes: \n  alerts: \n  routeShortName: 1W\n  routeLongName: West Manchester Mall\n  boardRule: \n  alightRule: \n  rentedBike: false\n  duration: 900.0\n- startTime: 1435605900000\n  endTime: 1435606800000\n  departureDelay: 0\n  arrivalDelay: 0\n  realTime: false\n  isNonExactFrequency: \n  headway: \n  distance: 4112.015514885083\n  from:\n    name: Transfer Center\n    stopId:\n      agencyId: '210'\n      id: '765237'\n    stopCode: \n    platformCode: \n    lon: -76.731524\n    lat: 39.959945\n    arrival: 1435604400000\n    departure: 1435605900000\n    orig: \n    zoneId: '0'\n    stopIndex: 0\n  to:\n    name: Haines Rd K-Mart\n    stopId:\n      agencyId: '210'\n      id: '765018'\n    stopCode: \n    platformCode: \n    lon: -76.683279\n    lat: 39.959727\n    arrival: 1435606800000\n    departure: 1435606801000\n    orig: \n    zoneId: '0'\n    stopIndex: 1\n  legGeometry:\n    points: ut{rFzsisM~@AyGc\\dPaHmEsScHm]iBu{@@aA`Jw_@TuBnDey@TwH?oFZyEP{IH_@FyECmFWkKsH{AOtBe@Hb@|D\\K\n    levels: \n    length: 24\n  transitLeg: true\n  mode: BUS\n  route: 83N\n  agencyName: \n  agencyUrl: \n  agencyTimeZoneOffset: -14400000\n  routeColor: 7685B8\n  routeType: 3\n  routeId: '1263'\n  routeTextColor: FFFFFF\n  interlineWithPreviousLeg: false\n  tripShortName: \n  tripBlockId: \n  headsign: HACC Campus\n  agencyId: '210'\n  tripId: 49160A1024B1797\n  serviceDate: '20150629'\n  intermediateStops: \n  steps: []\n  notes: \n  alerts: \n  routeShortName: 83N\n  routeLongName: Harrisburg Express\n  boardRule: \n  alightRule: \n  rentedBike: false\n  duration: 900.0\n- startTime: 1435606801000\n  endTime: 1435607394000\n  departureDelay: 0\n  arrivalDelay: 0\n  realTime: false\n  isNonExactFrequency: \n  headway: \n  distance: 763.3969315504738\n  from:\n    name: Haines Rd K-Mart\n    stopId:\n      agencyId: '210'\n      id: '765018'\n    stopCode: \n    platformCode: \n    lon: -76.6832710419985\n    lat: 39.9597295760251\n    arrival: 1435606800000\n    departure: 1435606801000\n    orig: \n    zoneId: \n    stopIndex: \n  to:\n    name: Erlen Drive\n    stopId: \n    stopCode: \n    platformCode: \n    lon: -76.67966600881111\n    lat: 39.96437079412677\n    arrival: 1435607394000\n    departure: \n    orig: ''\n    zoneId: \n    stopIndex: \n  legGeometry:\n    points: gs{rFne`sM@A]}DCWJeBmAUeCi@mCe@VcFaDUaDG_Gk@\n    levels: \n    length: 12\n  transitLeg: false\n  mode: WALK\n  route: ''\n  agencyName: \n  agencyUrl: \n  agencyTimeZoneOffset: -14400000\n  routeColor: \n  routeType: \n  routeId: \n  routeTextColor: \n  interlineWithPreviousLeg: false\n  tripShortName: \n  tripBlockId: \n  headsign: \n  agencyId: \n  tripId: \n  serviceDate: \n  intermediateStops: \n  steps:\n  - distance: 138.77360094966463\n    relativeDirection: DEPART\n    streetName: service road\n    absoluteDirection: SOUTH\n    exit: \n    stayOn: false\n    area: false\n    bogusName: false\n    lon: -76.6832710419985\n    lat: 39.9597295760251\n    alerts: \n    elevation: []\n  - distance: 201.8719325153749\n    relativeDirection: LEFT\n    streetName: Haines Road\n    absoluteDirection: NORTH\n    exit: \n    stayOn: false\n    area: false\n    bogusName: false\n    lon: -76.6816898\n    lat: 39.9598213\n    alerts: \n    elevation: []\n  - distance: 98.53025812689052\n    relativeDirection: RIGHT\n    streetName: Raleigh Drive\n    absoluteDirection: EAST\n    exit: \n    stayOn: false\n    area: false\n    bogusName: false\n    lon: -76.68118\n    lat: 39.9615941\n    alerts: \n    elevation: []\n  - distance: 324.22113995854363\n    relativeDirection: LEFT\n    streetName: Erlen Drive\n    absoluteDirection: NORTH\n    exit: \n    stayOn: false\n    area: false\n    bogusName: false\n    lon: -76.6800351\n    lat: 39.9614712\n    alerts: \n    elevation: []\n  notes: \n  alerts: \n  routeShortName: \n  routeLongName: \n  boardRule: \n  alightRule: \n  rentedBike: false\n  duration: 593.0\n","cost":"5.1","hidden":false,"created_at":"2015-06-26T20:57:06.307-04:00","updated_at":"2015-06-26T20:57:06.591-04:00","ride_count":null,"external_info":null,"match_score":-0.19999999999999998,"missing_information":false,"accommodation_mismatch":false,"missing_information_text":null,"date_mismatch":false,"time_mismatch":false,"too_late":false,"missing_accommodations":"","cost_comments":null,"selected":null,"start_time":"2015-06-29T14:41:23.000-04:00","end_time":"2015-06-29T15:49:54.000-04:00","is_bookable":false,"booking_confirmation":null,"duration_estimated":false,"map_image":{"url":null},"too_early":false,"returned_mode_code":"mode_transit","order_xml":null,"discounts":null,"segment_index":0,"start_location":{"address_components":[{"long_name":"1800 Bannister Street","short_name":"1800 Bannister Street","types":["street_address"]},{"long_name":"York","short_name":"York","types":["locality","political"]},{"long_name":"Pennsylvania","short_name":"Pennsylvania","types":["administrative_area_level_1","political"]},{"long_name":"17404","short_name":"17404","types":["postal_code"]}],"formatted_address":"1800 Bannister Street, York, Pennsylvania 17404","geometry":{"location":{"lat":39.958989,"lng":-76.763218}},"id":4717,"name":"West York Area High School","scope":"user"},"end_location":{"address_components":[{"long_name":"701 Erlen Drive","short_name":"701 Erlen Drive","types":["street_address"]},{"long_name":"York","short_name":"York","types":["locality","political"]},{"long_name":"Pennsylvania","short_name":"Pennsylvania","types":["administrative_area_level_1","political"]},{"long_name":"17402","short_name":"17402","types":["postal_code"]}],"formatted_address":"701 Erlen Drive, York, Pennsylvania 17402","geometry":{"location":{"lat":39.964296,"lng":-76.678936}},"id":4718,"name":"East York Elementary School","scope":"user"},"prebooking_questions":[{"question":"Will you be traveling with an approved escort","choices":[true,false],"code":"assistant"},{"question":"How many children or family members will be traveling with you?","choices":[0,1,2],"code":"children"}],"bookable":false,"json_legs":[{"startTime":1435603283000,"endTime":1435603499000,"departureDelay":0,"arrivalDelay":0,"realTime":false,"isNonExactFrequency":null,"headway":null,"distance":274.4320197275302,"from":{"name":"service road","stopId":null,"stopCode":null,"platformCode":null,"lon":-76.7633366,"lat":39.9591893,"arrival":null,"departure":1435603283000,"orig":"","zoneId":null,"stopIndex":null},"to":{"name":"Bannister St At Seward Ib","stopId":{"agencyId":"210","id":"765383"},"stopCode":null,"platformCode":null,"lon":-76.76322304443343,"lat":39.96070416002769,"arrival":1435603499000,"departure":1435603500000,"orig":null,"zoneId":null,"stopIndex":null},"legGeometry":{"points":"{o{rFzyosM?R?RCPGRK\\ILGHI?I?IAIIEEAICKCMM?M?YFWBO@U@]?u@@EuB","levels":null,"length":25},"transitLeg":false,"mode":"WALK","route":"","agencyName":null,"agencyUrl":null,"agencyTimeZoneOffset":-14400000,"routeColor":null,"routeType":null,"routeId":null,"routeTextColor":null,"interlineWithPreviousLeg":false,"tripShortName":null,"tripBlockId":null,"headsign":null,"agencyId":null,"tripId":null,"serviceDate":null,"intermediateStops":null,"steps":[{"distance":223.6672587997366,"relativeDirection":"DEPART","streetName":"service road","absoluteDirection":"WEST","exit":null,"stayOn":false,"area":false,"bogusName":false,"lon":-76.7633366,"lat":39.9591893,"alerts":null,"elevation":[]},{"distance":50.7647609277936,"relativeDirection":"RIGHT","streetName":"Bannister Street","absoluteDirection":"EAST","exit":null,"stayOn":false,"area":false,"bogusName":false,"lon":-76.763817,"lat":39.96067,"alerts":null,"elevation":[]}],"notes":null,"alerts":null,"routeShortName":null,"routeLongName":null,"boardRule":null,"alightRule":null,"rentedBike":false,"duration":216.0},{"startTime":1435603500000,"endTime":1435604400000,"departureDelay":0,"arrivalDelay":0,"realTime":false,"isNonExactFrequency":null,"headway":null,"distance":2845.5746582983893,"from":{"name":"Bannister St At Seward Ib","stopId":{"agencyId":"210","id":"765383"},"stopCode":null,"platformCode":null,"lon":-76.763222,"lat":39.960686,"arrival":1435603499000,"departure":1435603500000,"orig":null,"zoneId":"0","stopIndex":7},"to":{"name":"Transfer Center","stopId":{"agencyId":"210","id":"765237"},"stopCode":null,"platformCode":null,"lon":-76.731524,"lat":39.959945,"arrival":1435604400000,"departure":1435605900000,"orig":null,"zoneId":"0","stopIndex":16},"legGeometry":{"points":"ky{rFdyosMOmGSgKSiHbCaLj@eCh@eCJa@`@{An@mCr@oCh@qBj@_CBKXoAZcAj@iCn@oCv@uCPi@DSh@_Cd@eBf@uBd@gCo@_DScAoBcJUcAcD{NOw@qDmQSaAyBwKa@cBCB}C_OvCgAZxAvAC","levels":null,"length":40},"transitLeg":true,"mode":"BUS","route":"1W","agencyName":null,"agencyUrl":null,"agencyTimeZoneOffset":-14400000,"routeColor":"FF0000","routeType":3,"routeId":"1264","routeTextColor":"000000","interlineWithPreviousLeg":false,"tripShortName":null,"tripBlockId":null,"headsign":"1w Downtown","agencyId":"210","tripId":"53771A1024B1797","serviceDate":"20150629","intermediateStops":null,"steps":[],"notes":null,"alerts":null,"routeShortName":"1W","routeLongName":"West Manchester Mall","boardRule":null,"alightRule":null,"rentedBike":false,"duration":900.0},{"startTime":1435605900000,"endTime":1435606800000,"departureDelay":0,"arrivalDelay":0,"realTime":false,"isNonExactFrequency":null,"headway":null,"distance":4112.015514885083,"from":{"name":"Transfer Center","stopId":{"agencyId":"210","id":"765237"},"stopCode":null,"platformCode":null,"lon":-76.731524,"lat":39.959945,"arrival":1435604400000,"departure":1435605900000,"orig":null,"zoneId":"0","stopIndex":0},"to":{"name":"Haines Rd K-Mart","stopId":{"agencyId":"210","id":"765018"},"stopCode":null,"platformCode":null,"lon":-76.683279,"lat":39.959727,"arrival":1435606800000,"departure":1435606801000,"orig":null,"zoneId":"0","stopIndex":1},"legGeometry":{"points":"ut{rFzsisM~@AyGc\\dPaHmEsScHm]iBu{@@aA`Jw_@TuBnDey@TwH?oFZyEP{IH_@FyECmFWkKsH{AOtBe@Hb@|D\\K","levels":null,"length":24},"transitLeg":true,"mode":"BUS","route":"83N","agencyName":null,"agencyUrl":null,"agencyTimeZoneOffset":-14400000,"routeColor":"7685B8","routeType":3,"routeId":"1263","routeTextColor":"FFFFFF","interlineWithPreviousLeg":false,"tripShortName":null,"tripBlockId":null,"headsign":"HACC Campus","agencyId":"210","tripId":"49160A1024B1797","serviceDate":"20150629","intermediateStops":null,"steps":[],"notes":null,"alerts":null,"routeShortName":"83N","routeLongName":"Harrisburg Express","boardRule":null,"alightRule":null,"rentedBike":false,"duration":900.0},{"startTime":1435606801000,"endTime":1435607394000,"departureDelay":0,"arrivalDelay":0,"realTime":false,"isNonExactFrequency":null,"headway":null,"distance":763.3969315504738,"from":{"name":"Haines Rd K-Mart","stopId":{"agencyId":"210","id":"765018"},"stopCode":null,"platformCode":null,"lon":-76.6832710419985,"lat":39.9597295760251,"arrival":1435606800000,"departure":1435606801000,"orig":null,"zoneId":null,"stopIndex":null},"to":{"name":"Erlen Drive","stopId":null,"stopCode":null,"platformCode":null,"lon":-76.67966600881111,"lat":39.96437079412677,"arrival":1435607394000,"departure":null,"orig":"","zoneId":null,"stopIndex":null},"legGeometry":{"points":"gs{rFne`sM@A]}DCWJeBmAUeCi@mCe@VcFaDUaDG_Gk@","levels":null,"length":12},"transitLeg":false,"mode":"WALK","route":"","agencyName":null,"agencyUrl":null,"agencyTimeZoneOffset":-14400000,"routeColor":null,"routeType":null,"routeId":null,"routeTextColor":null,"interlineWithPreviousLeg":false,"tripShortName":null,"tripBlockId":null,"headsign":null,"agencyId":null,"tripId":null,"serviceDate":null,"intermediateStops":null,"steps":[{"distance":138.77360094966463,"relativeDirection":"DEPART","streetName":"service road","absoluteDirection":"SOUTH","exit":null,"stayOn":false,"area":false,"bogusName":false,"lon":-76.6832710419985,"lat":39.9597295760251,"alerts":null,"elevation":[]},{"distance":201.8719325153749,"relativeDirection":"LEFT","streetName":"Haines Road","absoluteDirection":"NORTH","exit":null,"stayOn":false,"area":false,"bogusName":false,"lon":-76.6816898,"lat":39.9598213,"alerts":null,"elevation":[]},{"distance":98.53025812689052,"relativeDirection":"RIGHT","streetName":"Raleigh Drive","absoluteDirection":"EAST","exit":null,"stayOn":false,"area":false,"bogusName":false,"lon":-76.68118,"lat":39.9615941,"alerts":null,"elevation":[]},{"distance":324.22113995854363,"relativeDirection":"LEFT","streetName":"Erlen Drive","absoluteDirection":"NORTH","exit":null,"stayOn":false,"area":false,"bogusName":false,"lon":-76.6800351,"lat":39.9614712,"alerts":null,"elevation":[]}],"notes":null,"alerts":null,"routeShortName":null,"routeLongName":null,"boardRule":null,"alightRule":null,"rentedBike":false,"duration":593.0}]},{"id":14593,"trip_part_id":3697,"mode_id":1,"service_id":3,"server_status":200,"server_message":null,"duration":3365,"walk_time":1423,"transit_time":1940,"wait_time":2,"walk_distance":1841.686054096731,"transfers":1,"count":null,"legs":"---\n- startTime: 1435602708000\n  endTime: 1435603429000\n  departureDelay: 0\n  arrivalDelay: 0\n  realTime: false\n  isNonExactFrequency: \n  headway: \n  distance: 929.0991112907146\n  from:\n    name: service road\n    stopId: \n    stopCode: \n    platformCode: \n    lon: -76.7633366\n    lat: 39.9591893\n    arrival: \n    departure: 1435602708000\n    orig: ''\n    zoneId: \n    stopIndex: \n  to:\n    name: W Market St At Adams St Ib\n    stopId:\n      agencyId: '210'\n      id: '765381'\n    stopCode: \n    platformCode: \n    lon: -76.7610941586006\n    lat: 39.95340171100949\n    arrival: 1435603429000\n    departure: 1435603430000\n    orig: \n    zoneId: \n    stopIndex: \n  legGeometry:\n    points: \"{o{rFzyosMIOIMKKKEMAm@@e@@KgEnCCDABGA{@rCOvBOr@IrAGrACvAKnAEzAKdBMjCOrCKRA\"\n    levels: \n    length: 25\n  transitLeg: false\n  mode: WALK\n  route: ''\n  agencyName: \n  agencyUrl: \n  agencyTimeZoneOffset: -14400000\n  routeColor: \n  routeType: \n  routeId: \n  routeTextColor: \n  interlineWithPreviousLeg: false\n  tripShortName: \n  tripBlockId: \n  headsign: \n  agencyId: \n  tripId: \n  serviceDate: \n  intermediateStops: \n  steps:\n  - distance: 282.4454721231507\n    relativeDirection: DEPART\n    streetName: service road\n    absoluteDirection: NORTHEAST\n    exit: \n    stayOn: false\n    area: false\n    bogusName: false\n    lon: -76.7633366\n    lat: 39.9591893\n    alerts: \n    elevation: []\n  - distance: 635.4486831604651\n    relativeDirection: RIGHT\n    streetName: North Adams Street\n    absoluteDirection: SOUTH\n    exit: \n    stayOn: false\n    area: false\n    bogusName: false\n    lon: -76.7617334\n    lat: 39.9591955\n    alerts: \n    elevation: []\n  - distance: 11.204956007098843\n    relativeDirection: CONTINUE\n    streetName: South Adams Street\n    absoluteDirection: SOUTH\n    exit: \n    stayOn: false\n    area: false\n    bogusName: false\n    lon: -76.761102\n    lat: 39.9535023\n    alerts: \n    elevation: []\n  notes: \n  alerts: \n  routeShortName: \n  routeLongName: \n  boardRule: \n  alightRule: \n  rentedBike: false\n  duration: 721.0\n- startTime: 1435603430000\n  endTime: 1435604400000\n  departureDelay: 0\n  arrivalDelay: 0\n  realTime: false\n  isNonExactFrequency: \n  headway: \n  distance: 2739.7950110811676\n  from:\n    name: W Market St At Adams St Ib\n    stopId:\n      agencyId: '210'\n      id: '765381'\n    stopCode: \n    platformCode: \n    lon: -76.760975\n    lat: 39.953411\n    arrival: 1435603429000\n    departure: 1435603430000\n    orig: \n    zoneId: '0'\n    stopIndex: 7\n  to:\n    name: Transfer Center\n    stopId:\n      agencyId: '210'\n      id: '765237'\n    stopCode: \n    platformCode: \n    lon: -76.731524\n    lat: 39.959945\n    arrival: 1435604400000\n    departure: 1435604400000\n    orig: \n    zoneId: '0'\n    stopIndex: 19\n  legGeometry:\n    points: ilzrFdkosM[kLm@}R?CgAuFgA{FOaAMu@fCgAbCeAOs@y@wDQ{@iAuFUcAIc@iAkFiAwFOo@CKsAyG_CcLyAuGI_@qAiGG_@aAyEoBcJG[Kg@Q_AwB{JMg@@?eCuKu@A\n    levels: \n    length: 36\n  transitLeg: true\n  mode: BUS\n  route: 5W\n  agencyName: \n  agencyUrl: \n  agencyTimeZoneOffset: -14400000\n  routeColor: '800080'\n  routeType: 3\n  routeId: '1270'\n  routeTextColor: FFFFFF\n  interlineWithPreviousLeg: false\n  tripShortName: \n  tripBlockId: \n  headsign: 5w Downtown\n  agencyId: '210'\n  tripId: 54007A1024B1797\n  serviceDate: '20150629'\n  intermediateStops: \n  steps: []\n  notes: \n  alerts: \n  routeShortName: 5W\n  routeLongName: West York  West York Ind Park\n  boardRule: \n  alightRule: \n  rentedBike: false\n  duration: 970.0\n- startTime: 1435604400000\n  endTime: 1435605370000\n  departureDelay: 0\n  arrivalDelay: 0\n  realTime: false\n  isNonExactFrequency: \n  headway: \n  distance: 4786.37466854201\n  from:\n    name: Transfer Center\n    stopId:\n      agencyId: '210'\n      id: '765237'\n    stopCode: \n    platformCode: \n    lon: -76.731524\n    lat: 39.959945\n    arrival: 1435604400000\n    departure: 1435604400000\n    orig: \n    zoneId: '0'\n    stopIndex: 0\n  to:\n    name: Camp Betty At Mt Rose Ave Ob\n    stopId:\n      agencyId: '210'\n      id: '765016'\n    stopCode: \n    platformCode: \n    lon: -76.682706\n    lat: 39.957379\n    arrival: 1435605370000\n    departure: 1435605371000\n    orig: \n    zoneId: '0'\n    stopIndex: 17\n  legGeometry:\n    points: ot{rFzsisMv@?mCyM??QcA}@_E_AmEy@aEOw@k@cCy@_E[cB[eB_AqEq@cDIa@dAg@`Ae@dBm@b@OzB{@f@UCuCMaFCgCAo@EsBM}EOgHAo@EuAKmEIaHCq@Ck@McFGgBIiBMeDGeBUsISiJ?SAa@O}IMoHC{@uAHwAJiBDCaDCeBA_AfHa@TA~FYpCGb@CxAIX_I\\oGFmBb@wLBsALeFDkENqBT}BHkG@kB?gDBeACwB?m@AwBOkELa@JELCXB~At@RN\n    levels: \n    length: 82\n  transitLeg: true\n  mode: BUS\n  route: 5E\n  agencyName: \n  agencyUrl: \n  agencyTimeZoneOffset: -14400000\n  routeColor: DB7093\n  routeType: 3\n  routeId: '1271'\n  routeTextColor: '000000'\n  interlineWithPreviousLeg: false\n  tripShortName: \n  tripBlockId: \n  headsign: Kmart Greensprings\n  agencyId: '210'\n  tripId: 54037A1024B1797\n  serviceDate: '20150629'\n  intermediateStops: \n  steps: []\n  notes: \n  alerts: \n  routeShortName: 5E\n  routeLongName: Haines Rd  Kmart  Greensprings\n  boardRule: \n  alightRule: \n  rentedBike: false\n  duration: 970.0\n- startTime: 1435605371000\n  endTime: 1435606073000\n  departureDelay: 0\n  arrivalDelay: 0\n  realTime: false\n  isNonExactFrequency: \n  headway: \n  distance: 912.4087335487009\n  from:\n    name: Camp Betty At Mt Rose Ave Ob\n    stopId:\n      agencyId: '210'\n      id: '765016'\n    stopCode: \n    platformCode: \n    lon: -76.68266362675077\n    lat: 39.95734572174098\n    arrival: 1435605370000\n    departure: 1435605371000\n    orig: \n    zoneId: \n    stopIndex: \n  to:\n    name: Erlen Drive\n    stopId: \n    stopCode: \n    platformCode: \n    lon: -76.67966600881111\n    lat: 39.96437079412677\n    arrival: 1435606073000\n    departure: \n    orig: ''\n    zoneId: \n    stopIndex: \n  legGeometry:\n    points: kd{rFta`sMSO_Bw@cAYSEaB_@qDu@OEmAUeCi@mCe@VcFaDUaDG_Gk@\n    levels: \n    length: 15\n  transitLeg: false\n  mode: WALK\n  route: ''\n  agencyName: \n  agencyUrl: \n  agencyTimeZoneOffset: -14400000\n  routeColor: \n  routeType: \n  routeId: \n  routeTextColor: \n  interlineWithPreviousLeg: false\n  tripShortName: \n  tripBlockId: \n  headsign: \n  agencyId: \n  tripId: \n  serviceDate: \n  intermediateStops: \n  steps:\n  - distance: 489.6573354632666\n    relativeDirection: DEPART\n    streetName: Haines Road\n    absoluteDirection: NORTHEAST\n    exit: \n    stayOn: false\n    area: false\n    bogusName: false\n    lon: -76.68266362675077\n    lat: 39.95734572174098\n    alerts: \n    elevation: []\n  - distance: 98.53025812689052\n    relativeDirection: RIGHT\n    streetName: Raleigh Drive\n    absoluteDirection: EAST\n    exit: \n    stayOn: false\n    area: false\n    bogusName: false\n    lon: -76.68118\n    lat: 39.9615941\n    alerts: \n    elevation: []\n  - distance: 324.22113995854363\n    relativeDirection: LEFT\n    streetName: Erlen Drive\n    absoluteDirection: NORTH\n    exit: \n    stayOn: false\n    area: false\n    bogusName: false\n    lon: -76.6800351\n    lat: 39.9614712\n    alerts: \n    elevation: []\n  notes: \n  alerts: \n  routeShortName: \n  routeLongName: \n  boardRule: \n  alightRule: \n  rentedBike: false\n  duration: 702.0\n","cost":"1.6","hidden":false,"created_at":"2015-06-26T20:57:06.371-04:00","updated_at":"2015-06-26T20:57:06.601-04:00","ride_count":null,"external_info":null,"match_score":-0.09999999999999998,"missing_information":false,"accommodation_mismatch":false,"missing_information_text":null,"date_mismatch":false,"time_mismatch":false,"too_late":false,"missing_accommodations":"","cost_comments":null,"selected":null,"start_time":"2015-06-29T14:31:48.000-04:00","end_time":"2015-06-29T15:27:53.000-04:00","is_bookable":false,"booking_confirmation":null,"duration_estimated":false,"map_image":{"url":null},"too_early":false,"returned_mode_code":"mode_transit","order_xml":null,"discounts":null,"segment_index":0,"start_location":{"address_components":[{"long_name":"1800 Bannister Street","short_name":"1800 Bannister Street","types":["street_address"]},{"long_name":"York","short_name":"York","types":["locality","political"]},{"long_name":"Pennsylvania","short_name":"Pennsylvania","types":["administrative_area_level_1","political"]},{"long_name":"17404","short_name":"17404","types":["postal_code"]}],"formatted_address":"1800 Bannister Street, York, Pennsylvania 17404","geometry":{"location":{"lat":39.958989,"lng":-76.763218}},"id":4717,"name":"West York Area High School","scope":"user"},"end_location":{"address_components":[{"long_name":"701 Erlen Drive","short_name":"701 Erlen Drive","types":["street_address"]},{"long_name":"York","short_name":"York","types":["locality","political"]},{"long_name":"Pennsylvania","short_name":"Pennsylvania","types":["administrative_area_level_1","political"]},{"long_name":"17402","short_name":"17402","types":["postal_code"]}],"formatted_address":"701 Erlen Drive, York, Pennsylvania 17402","geometry":{"location":{"lat":39.964296,"lng":-76.678936}},"id":4718,"name":"East York Elementary School","scope":"user"},"prebooking_questions":[{"question":"Will you be traveling with an approved escort","choices":[true,false],"code":"assistant"},{"question":"How many children or family members will be traveling with you?","choices":[0,1,2],"code":"children"}],"bookable":false,"json_legs":[{"startTime":1435602708000,"endTime":1435603429000,"departureDelay":0,"arrivalDelay":0,"realTime":false,"isNonExactFrequency":null,"headway":null,"distance":929.0991112907146,"from":{"name":"service road","stopId":null,"stopCode":null,"platformCode":null,"lon":-76.7633366,"lat":39.9591893,"arrival":null,"departure":1435602708000,"orig":"","zoneId":null,"stopIndex":null},"to":{"name":"W Market St At Adams St Ib","stopId":{"agencyId":"210","id":"765381"},"stopCode":null,"platformCode":null,"lon":-76.7610941586006,"lat":39.95340171100949,"arrival":1435603429000,"departure":1435603430000,"orig":null,"zoneId":null,"stopIndex":null},"legGeometry":{"points":"{o{rFzyosMIOIMKKKEMAm@@e@@KgEnCCDABGA{@rCOvBOr@IrAGrACvAKnAEzAKdBMjCOrCKRA","levels":null,"length":25},"transitLeg":false,"mode":"WALK","route":"","agencyName":null,"agencyUrl":null,"agencyTimeZoneOffset":-14400000,"routeColor":null,"routeType":null,"routeId":null,"routeTextColor":null,"interlineWithPreviousLeg":false,"tripShortName":null,"tripBlockId":null,"headsign":null,"agencyId":null,"tripId":null,"serviceDate":null,"intermediateStops":null,"steps":[{"distance":282.4454721231507,"relativeDirection":"DEPART","streetName":"service road","absoluteDirection":"NORTHEAST","exit":null,"stayOn":false,"area":false,"bogusName":false,"lon":-76.7633366,"lat":39.9591893,"alerts":null,"elevation":[]},{"distance":635.4486831604651,"relativeDirection":"RIGHT","streetName":"North Adams Street","absoluteDirection":"SOUTH","exit":null,"stayOn":false,"area":false,"bogusName":false,"lon":-76.7617334,"lat":39.9591955,"alerts":null,"elevation":[]},{"distance":11.204956007098843,"relativeDirection":"CONTINUE","streetName":"South Adams Street","absoluteDirection":"SOUTH","exit":null,"stayOn":false,"area":false,"bogusName":false,"lon":-76.761102,"lat":39.9535023,"alerts":null,"elevation":[]}],"notes":null,"alerts":null,"routeShortName":null,"routeLongName":null,"boardRule":null,"alightRule":null,"rentedBike":false,"duration":721.0},{"startTime":1435603430000,"endTime":1435604400000,"departureDelay":0,"arrivalDelay":0,"realTime":false,"isNonExactFrequency":null,"headway":null,"distance":2739.7950110811676,"from":{"name":"W Market St At Adams St Ib","stopId":{"agencyId":"210","id":"765381"},"stopCode":null,"platformCode":null,"lon":-76.760975,"lat":39.953411,"arrival":1435603429000,"departure":1435603430000,"orig":null,"zoneId":"0","stopIndex":7},"to":{"name":"Transfer Center","stopId":{"agencyId":"210","id":"765237"},"stopCode":null,"platformCode":null,"lon":-76.731524,"lat":39.959945,"arrival":1435604400000,"departure":1435604400000,"orig":null,"zoneId":"0","stopIndex":19},"legGeometry":{"points":"ilzrFdkosM[kLm@}R?CgAuFgA{FOaAMu@fCgAbCeAOs@y@wDQ{@iAuFUcAIc@iAkFiAwFOo@CKsAyG_CcLyAuGI_@qAiGG_@aAyEoBcJG[Kg@Q_AwB{JMg@@?eCuKu@A","levels":null,"length":36},"transitLeg":true,"mode":"BUS","route":"5W","agencyName":null,"agencyUrl":null,"agencyTimeZoneOffset":-14400000,"routeColor":"800080","routeType":3,"routeId":"1270","routeTextColor":"FFFFFF","interlineWithPreviousLeg":false,"tripShortName":null,"tripBlockId":null,"headsign":"5w Downtown","agencyId":"210","tripId":"54007A1024B1797","serviceDate":"20150629","intermediateStops":null,"steps":[],"notes":null,"alerts":null,"routeShortName":"5W","routeLongName":"West York  West York Ind Park","boardRule":null,"alightRule":null,"rentedBike":false,"duration":970.0},{"startTime":1435604400000,"endTime":1435605370000,"departureDelay":0,"arrivalDelay":0,"realTime":false,"isNonExactFrequency":null,"headway":null,"distance":4786.37466854201,"from":{"name":"Transfer Center","stopId":{"agencyId":"210","id":"765237"},"stopCode":null,"platformCode":null,"lon":-76.731524,"lat":39.959945,"arrival":1435604400000,"departure":1435604400000,"orig":null,"zoneId":"0","stopIndex":0},"to":{"name":"Camp Betty At Mt Rose Ave Ob","stopId":{"agencyId":"210","id":"765016"},"stopCode":null,"platformCode":null,"lon":-76.682706,"lat":39.957379,"arrival":1435605370000,"departure":1435605371000,"orig":null,"zoneId":"0","stopIndex":17},"legGeometry":{"points":"ot{rFzsisMv@?mCyM??QcA}@_E_AmEy@aEOw@k@cCy@_E[cB[eB_AqEq@cDIa@dAg@`Ae@dBm@b@OzB{@f@UCuCMaFCgCAo@EsBM}EOgHAo@EuAKmEIaHCq@Ck@McFGgBIiBMeDGeBUsISiJ?SAa@O}IMoHC{@uAHwAJiBDCaDCeBA_AfHa@TA~FYpCGb@CxAIX_I\\oGFmBb@wLBsALeFDkENqBT}BHkG@kB?gDBeACwB?m@AwBOkELa@JELCXB~At@RN","levels":null,"length":82},"transitLeg":true,"mode":"BUS","route":"5E","agencyName":null,"agencyUrl":null,"agencyTimeZoneOffset":-14400000,"routeColor":"DB7093","routeType":3,"routeId":"1271","routeTextColor":"000000","interlineWithPreviousLeg":false,"tripShortName":null,"tripBlockId":null,"headsign":"Kmart Greensprings","agencyId":"210","tripId":"54037A1024B1797","serviceDate":"20150629","intermediateStops":null,"steps":[],"notes":null,"alerts":null,"routeShortName":"5E","routeLongName":"Haines Rd  Kmart  Greensprings","boardRule":null,"alightRule":null,"rentedBike":false,"duration":970.0},{"startTime":1435605371000,"endTime":1435606073000,"departureDelay":0,"arrivalDelay":0,"realTime":false,"isNonExactFrequency":null,"headway":null,"distance":912.4087335487009,"from":{"name":"Camp Betty At Mt Rose Ave Ob","stopId":{"agencyId":"210","id":"765016"},"stopCode":null,"platformCode":null,"lon":-76.68266362675077,"lat":39.95734572174098,"arrival":1435605370000,"departure":1435605371000,"orig":null,"zoneId":null,"stopIndex":null},"to":{"name":"Erlen Drive","stopId":null,"stopCode":null,"platformCode":null,"lon":-76.67966600881111,"lat":39.96437079412677,"arrival":1435606073000,"departure":null,"orig":"","zoneId":null,"stopIndex":null},"legGeometry":{"points":"kd{rFta`sMSO_Bw@cAYSEaB_@qDu@OEmAUeCi@mCe@VcFaDUaDG_Gk@","levels":null,"length":15},"transitLeg":false,"mode":"WALK","route":"","agencyName":null,"agencyUrl":null,"agencyTimeZoneOffset":-14400000,"routeColor":null,"routeType":null,"routeId":null,"routeTextColor":null,"interlineWithPreviousLeg":false,"tripShortName":null,"tripBlockId":null,"headsign":null,"agencyId":null,"tripId":null,"serviceDate":null,"intermediateStops":null,"steps":[{"distance":489.6573354632666,"relativeDirection":"DEPART","streetName":"Haines Road","absoluteDirection":"NORTHEAST","exit":null,"stayOn":false,"area":false,"bogusName":false,"lon":-76.68266362675077,"lat":39.95734572174098,"alerts":null,"elevation":[]},{"distance":98.53025812689052,"relativeDirection":"RIGHT","streetName":"Raleigh Drive","absoluteDirection":"EAST","exit":null,"stayOn":false,"area":false,"bogusName":false,"lon":-76.68118,"lat":39.9615941,"alerts":null,"elevation":[]},{"distance":324.22113995854363,"relativeDirection":"LEFT","streetName":"Erlen Drive","absoluteDirection":"NORTH","exit":null,"stayOn":false,"area":false,"bogusName":false,"lon":-76.6800351,"lat":39.9614712,"alerts":null,"elevation":[]}],"notes":null,"alerts":null,"routeShortName":null,"routeLongName":null,"boardRule":null,"alightRule":null,"rentedBike":false,"duration":702.0}]},{"id":14594,"trip_part_id":3697,"mode_id":1,"service_id":3,"server_status":200,"server_message":null,"duration":2611,"walk_time":809,"transit_time":1800,"wait_time":2,"walk_distance":1038.0392232887273,"transfers":1,"count":null,"legs":"---\n- startTime: 1435601483000\n  endTime: 1435601699000\n  departureDelay: 0\n  arrivalDelay: 0\n  realTime: false\n  isNonExactFrequency: \n  headway: \n  distance: 274.4320197275302\n  from:\n    name: service road\n    stopId: \n    stopCode: \n    platformCode: \n    lon: -76.7633366\n    lat: 39.9591893\n    arrival: \n    departure: 1435601483000\n    orig: ''\n    zoneId: \n    stopIndex: \n  to:\n    name: Bannister St At Seward Ib\n    stopId:\n      agencyId: '210'\n      id: '765383'\n    stopCode: \n    platformCode: \n    lon: -76.76322304443343\n    lat: 39.96070416002769\n    arrival: 1435601699000\n    departure: 1435601700000\n    orig: \n    zoneId: \n    stopIndex: \n  legGeometry:\n    points: \"{o{rFzyosM?R?RCPGRK\\\\ILGHI?I?IAIIEEAICKCMM?M?YFWBO@U@]?u@@EuB\"\n    levels: \n    length: 25\n  transitLeg: false\n  mode: WALK\n  route: ''\n  agencyName: \n  agencyUrl: \n  agencyTimeZoneOffset: -14400000\n  routeColor: \n  routeType: \n  routeId: \n  routeTextColor: \n  interlineWithPreviousLeg: false\n  tripShortName: \n  tripBlockId: \n  headsign: \n  agencyId: \n  tripId: \n  serviceDate: \n  intermediateStops: \n  steps:\n  - distance: 223.6672587997366\n    relativeDirection: DEPART\n    streetName: service road\n    absoluteDirection: WEST\n    exit: \n    stayOn: false\n    area: false\n    bogusName: false\n    lon: -76.7633366\n    lat: 39.9591893\n    alerts: \n    elevation: []\n  - distance: 50.7647609277936\n    relativeDirection: RIGHT\n    streetName: Bannister Street\n    absoluteDirection: EAST\n    exit: \n    stayOn: false\n    area: false\n    bogusName: false\n    lon: -76.763817\n    lat: 39.96067\n    alerts: \n    elevation: []\n  notes: \n  alerts: \n  routeShortName: \n  routeLongName: \n  boardRule: \n  alightRule: \n  rentedBike: false\n  duration: 216.0\n- startTime: 1435601700000\n  endTime: 1435602600000\n  departureDelay: 0\n  arrivalDelay: 0\n  realTime: false\n  isNonExactFrequency: \n  headway: \n  distance: 2845.5746582983893\n  from:\n    name: Bannister St At Seward Ib\n    stopId:\n      agencyId: '210'\n      id: '765383'\n    stopCode: \n    platformCode: \n    lon: -76.763222\n    lat: 39.960686\n    arrival: 1435601699000\n    departure: 1435601700000\n    orig: \n    zoneId: '0'\n    stopIndex: 7\n  to:\n    name: Transfer Center\n    stopId:\n      agencyId: '210'\n      id: '765237'\n    stopCode: \n    platformCode: \n    lon: -76.731524\n    lat: 39.959945\n    arrival: 1435602600000\n    departure: 1435602600000\n    orig: \n    zoneId: '0'\n    stopIndex: 16\n  legGeometry:\n    points: ky{rFdyosMOmGSgKSiHbCaLj@eCh@eCJa@`@{An@mCr@oCh@qBj@_CBKXoAZcAj@iCn@oCv@uCPi@DSh@_Cd@eBf@uBd@gCo@_DScAoBcJUcAcD{NOw@qDmQSaAyBwKa@cBCB}C_OvCgAZxAvAC\n    levels: \n    length: 40\n  transitLeg: true\n  mode: BUS\n  route: 1W\n  agencyName: \n  agencyUrl: \n  agencyTimeZoneOffset: -14400000\n  routeColor: FF0000\n  routeType: 3\n  routeId: '1264'\n  routeTextColor: '000000'\n  interlineWithPreviousLeg: false\n  tripShortName: \n  tripBlockId: \n  headsign: 1w Downtown\n  agencyId: '210'\n  tripId: 53770A1024B1797\n  serviceDate: '20150629'\n  intermediateStops: \n  steps: []\n  notes: \n  alerts: \n  routeShortName: 1W\n  routeLongName: West Manchester Mall\n  boardRule: \n  alightRule: \n  rentedBike: false\n  duration: 900.0\n- startTime: 1435602600000\n  endTime: 1435603500000\n  departureDelay: 0\n  arrivalDelay: 0\n  realTime: false\n  isNonExactFrequency: \n  headway: \n  distance: 4112.015514885083\n  from:\n    name: Transfer Center\n    stopId:\n      agencyId: '210'\n      id: '765237'\n    stopCode: \n    platformCode: \n    lon: -76.731524\n    lat: 39.959945\n    arrival: 1435602600000\n    departure: 1435602600000\n    orig: \n    zoneId: '0'\n    stopIndex: 0\n  to:\n    name: Haines Rd K-Mart\n    stopId:\n      agencyId: '210'\n      id: '765018'\n    stopCode: \n    platformCode: \n    lon: -76.683279\n    lat: 39.959727\n    arrival: 1435603500000\n    departure: 1435603501000\n    orig: \n    zoneId: '0'\n    stopIndex: 1\n  legGeometry:\n    points: ut{rFzsisM~@AyGc\\dPaHmEsScHm]iBu{@@aA`Jw_@TuBnDey@TwH?oFZyEP{IH_@FyECmFWkKsH{AOtBe@Hb@|D\\K\n    levels: \n    length: 24\n  transitLeg: true\n  mode: BUS\n  route: 83N\n  agencyName: \n  agencyUrl: \n  agencyTimeZoneOffset: -14400000\n  routeColor: 7685B8\n  routeType: 3\n  routeId: '1263'\n  routeTextColor: FFFFFF\n  interlineWithPreviousLeg: false\n  tripShortName: \n  tripBlockId: \n  headsign: HACC Campus\n  agencyId: '210'\n  tripId: 49168A1024B1797\n  serviceDate: '20150629'\n  intermediateStops: \n  steps: []\n  notes: \n  alerts: \n  routeShortName: 83N\n  routeLongName: Harrisburg Express\n  boardRule: \n  alightRule: \n  rentedBike: false\n  duration: 900.0\n- startTime: 1435603501000\n  endTime: 1435604094000\n  departureDelay: 0\n  arrivalDelay: 0\n  realTime: false\n  isNonExactFrequency: \n  headway: \n  distance: 763.3969315504738\n  from:\n    name: Haines Rd K-Mart\n    stopId:\n      agencyId: '210'\n      id: '765018'\n    stopCode: \n    platformCode: \n    lon: -76.6832710419985\n    lat: 39.9597295760251\n    arrival: 1435603500000\n    departure: 1435603501000\n    orig: \n    zoneId: \n    stopIndex: \n  to:\n    name: Erlen Drive\n    stopId: \n    stopCode: \n    platformCode: \n    lon: -76.67966600881111\n    lat: 39.96437079412677\n    arrival: 1435604094000\n    departure: \n    orig: ''\n    zoneId: \n    stopIndex: \n  legGeometry:\n    points: gs{rFne`sM@A]}DCWJeBmAUeCi@mCe@VcFaDUaDG_Gk@\n    levels: \n    length: 12\n  transitLeg: false\n  mode: WALK\n  route: ''\n  agencyName: \n  agencyUrl: \n  agencyTimeZoneOffset: -14400000\n  routeColor: \n  routeType: \n  routeId: \n  routeTextColor: \n  interlineWithPreviousLeg: false\n  tripShortName: \n  tripBlockId: \n  headsign: \n  agencyId: \n  tripId: \n  serviceDate: \n  intermediateStops: \n  steps:\n  - distance: 138.77360094966463\n    relativeDirection: DEPART\n    streetName: service road\n    absoluteDirection: SOUTH\n    exit: \n    stayOn: false\n    area: false\n    bogusName: false\n    lon: -76.6832710419985\n    lat: 39.9597295760251\n    alerts: \n    elevation: []\n  - distance: 201.8719325153749\n    relativeDirection: LEFT\n    streetName: Haines Road\n    absoluteDirection: NORTH\n    exit: \n    stayOn: false\n    area: false\n    bogusName: false\n    lon: -76.6816898\n    lat: 39.9598213\n    alerts: \n    elevation: []\n  - distance: 98.53025812689052\n    relativeDirection: RIGHT\n    streetName: Raleigh Drive\n    absoluteDirection: EAST\n    exit: \n    stayOn: false\n    area: false\n    bogusName: false\n    lon: -76.68118\n    lat: 39.9615941\n    alerts: \n    elevation: []\n  - distance: 324.22113995854363\n    relativeDirection: LEFT\n    streetName: Erlen Drive\n    absoluteDirection: NORTH\n    exit: \n    stayOn: false\n    area: false\n    bogusName: false\n    lon: -76.6800351\n    lat: 39.9614712\n    alerts: \n    elevation: []\n  notes: \n  alerts: \n  routeShortName: \n  routeLongName: \n  boardRule: \n  alightRule: \n  rentedBike: false\n  duration: 593.0\n","cost":"5.1","hidden":false,"created_at":"2015-06-26T20:57:06.460-04:00","updated_at":"2015-06-26T20:57:06.608-04:00","ride_count":null,"external_info":null,"match_score":2.7755575615628914e-17,"missing_information":false,"accommodation_mismatch":false,"missing_information_text":null,"date_mismatch":false,"time_mismatch":false,"too_late":false,"missing_accommodations":"","cost_comments":null,"selected":null,"start_time":"2015-06-29T14:11:23.000-04:00","end_time":"2015-06-29T14:54:54.000-04:00","is_bookable":false,"booking_confirmation":null,"duration_estimated":false,"map_image":{"url":null},"too_early":false,"returned_mode_code":"mode_transit","order_xml":null,"discounts":null,"segment_index":0,"start_location":{"address_components":[{"long_name":"1800 Bannister Street","short_name":"1800 Bannister Street","types":["street_address"]},{"long_name":"York","short_name":"York","types":["locality","political"]},{"long_name":"Pennsylvania","short_name":"Pennsylvania","types":["administrative_area_level_1","political"]},{"long_name":"17404","short_name":"17404","types":["postal_code"]}],"formatted_address":"1800 Bannister Street, York, Pennsylvania 17404","geometry":{"location":{"lat":39.958989,"lng":-76.763218}},"id":4717,"name":"West York Area High School","scope":"user"},"end_location":{"address_components":[{"long_name":"701 Erlen Drive","short_name":"701 Erlen Drive","types":["street_address"]},{"long_name":"York","short_name":"York","types":["locality","political"]},{"long_name":"Pennsylvania","short_name":"Pennsylvania","types":["administrative_area_level_1","political"]},{"long_name":"17402","short_name":"17402","types":["postal_code"]}],"formatted_address":"701 Erlen Drive, York, Pennsylvania 17402","geometry":{"location":{"lat":39.964296,"lng":-76.678936}},"id":4718,"name":"East York Elementary School","scope":"user"},"prebooking_questions":[{"question":"Will you be traveling with an approved escort","choices":[true,false],"code":"assistant"},{"question":"How many children or family members will be traveling with you?","choices":[0,1,2],"code":"children"}],"bookable":false,"json_legs":[{"startTime":1435601483000,"endTime":1435601699000,"departureDelay":0,"arrivalDelay":0,"realTime":false,"isNonExactFrequency":null,"headway":null,"distance":274.4320197275302,"from":{"name":"service road","stopId":null,"stopCode":null,"platformCode":null,"lon":-76.7633366,"lat":39.9591893,"arrival":null,"departure":1435601483000,"orig":"","zoneId":null,"stopIndex":null},"to":{"name":"Bannister St At Seward Ib","stopId":{"agencyId":"210","id":"765383"},"stopCode":null,"platformCode":null,"lon":-76.76322304443343,"lat":39.96070416002769,"arrival":1435601699000,"departure":1435601700000,"orig":null,"zoneId":null,"stopIndex":null},"legGeometry":{"points":"{o{rFzyosM?R?RCPGRK\\ILGHI?I?IAIIEEAICKCMM?M?YFWBO@U@]?u@@EuB","levels":null,"length":25},"transitLeg":false,"mode":"WALK","route":"","agencyName":null,"agencyUrl":null,"agencyTimeZoneOffset":-14400000,"routeColor":null,"routeType":null,"routeId":null,"routeTextColor":null,"interlineWithPreviousLeg":false,"tripShortName":null,"tripBlockId":null,"headsign":null,"agencyId":null,"tripId":null,"serviceDate":null,"intermediateStops":null,"steps":[{"distance":223.6672587997366,"relativeDirection":"DEPART","streetName":"service road","absoluteDirection":"WEST","exit":null,"stayOn":false,"area":false,"bogusName":false,"lon":-76.7633366,"lat":39.9591893,"alerts":null,"elevation":[]},{"distance":50.7647609277936,"relativeDirection":"RIGHT","streetName":"Bannister Street","absoluteDirection":"EAST","exit":null,"stayOn":false,"area":false,"bogusName":false,"lon":-76.763817,"lat":39.96067,"alerts":null,"elevation":[]}],"notes":null,"alerts":null,"routeShortName":null,"routeLongName":null,"boardRule":null,"alightRule":null,"rentedBike":false,"duration":216.0},{"startTime":1435601700000,"endTime":1435602600000,"departureDelay":0,"arrivalDelay":0,"realTime":false,"isNonExactFrequency":null,"headway":null,"distance":2845.5746582983893,"from":{"name":"Bannister St At Seward Ib","stopId":{"agencyId":"210","id":"765383"},"stopCode":null,"platformCode":null,"lon":-76.763222,"lat":39.960686,"arrival":1435601699000,"departure":1435601700000,"orig":null,"zoneId":"0","stopIndex":7},"to":{"name":"Transfer Center","stopId":{"agencyId":"210","id":"765237"},"stopCode":null,"platformCode":null,"lon":-76.731524,"lat":39.959945,"arrival":1435602600000,"departure":1435602600000,"orig":null,"zoneId":"0","stopIndex":16},"legGeometry":{"points":"ky{rFdyosMOmGSgKSiHbCaLj@eCh@eCJa@`@{An@mCr@oCh@qBj@_CBKXoAZcAj@iCn@oCv@uCPi@DSh@_Cd@eBf@uBd@gCo@_DScAoBcJUcAcD{NOw@qDmQSaAyBwKa@cBCB}C_OvCgAZxAvAC","levels":null,"length":40},"transitLeg":true,"mode":"BUS","route":"1W","agencyName":null,"agencyUrl":null,"agencyTimeZoneOffset":-14400000,"routeColor":"FF0000","routeType":3,"routeId":"1264","routeTextColor":"000000","interlineWithPreviousLeg":false,"tripShortName":null,"tripBlockId":null,"headsign":"1w Downtown","agencyId":"210","tripId":"53770A1024B1797","serviceDate":"20150629","intermediateStops":null,"steps":[],"notes":null,"alerts":null,"routeShortName":"1W","routeLongName":"West Manchester Mall","boardRule":null,"alightRule":null,"rentedBike":false,"duration":900.0},{"startTime":1435602600000,"endTime":1435603500000,"departureDelay":0,"arrivalDelay":0,"realTime":false,"isNonExactFrequency":null,"headway":null,"distance":4112.015514885083,"from":{"name":"Transfer Center","stopId":{"agencyId":"210","id":"765237"},"stopCode":null,"platformCode":null,"lon":-76.731524,"lat":39.959945,"arrival":1435602600000,"departure":1435602600000,"orig":null,"zoneId":"0","stopIndex":0},"to":{"name":"Haines Rd K-Mart","stopId":{"agencyId":"210","id":"765018"},"stopCode":null,"platformCode":null,"lon":-76.683279,"lat":39.959727,"arrival":1435603500000,"departure":1435603501000,"orig":null,"zoneId":"0","stopIndex":1},"legGeometry":{"points":"ut{rFzsisM~@AyGc\\dPaHmEsScHm]iBu{@@aA`Jw_@TuBnDey@TwH?oFZyEP{IH_@FyECmFWkKsH{AOtBe@Hb@|D\\K","levels":null,"length":24},"transitLeg":true,"mode":"BUS","route":"83N","agencyName":null,"agencyUrl":null,"agencyTimeZoneOffset":-14400000,"routeColor":"7685B8","routeType":3,"routeId":"1263","routeTextColor":"FFFFFF","interlineWithPreviousLeg":false,"tripShortName":null,"tripBlockId":null,"headsign":"HACC Campus","agencyId":"210","tripId":"49168A1024B1797","serviceDate":"20150629","intermediateStops":null,"steps":[],"notes":null,"alerts":null,"routeShortName":"83N","routeLongName":"Harrisburg Express","boardRule":null,"alightRule":null,"rentedBike":false,"duration":900.0},{"startTime":1435603501000,"endTime":1435604094000,"departureDelay":0,"arrivalDelay":0,"realTime":false,"isNonExactFrequency":null,"headway":null,"distance":763.3969315504738,"from":{"name":"Haines Rd K-Mart","stopId":{"agencyId":"210","id":"765018"},"stopCode":null,"platformCode":null,"lon":-76.6832710419985,"lat":39.9597295760251,"arrival":1435603500000,"departure":1435603501000,"orig":null,"zoneId":null,"stopIndex":null},"to":{"name":"Erlen Drive","stopId":null,"stopCode":null,"platformCode":null,"lon":-76.67966600881111,"lat":39.96437079412677,"arrival":1435604094000,"departure":null,"orig":"","zoneId":null,"stopIndex":null},"legGeometry":{"points":"gs{rFne`sM@A]}DCWJeBmAUeCi@mCe@VcFaDUaDG_Gk@","levels":null,"length":12},"transitLeg":false,"mode":"WALK","route":"","agencyName":null,"agencyUrl":null,"agencyTimeZoneOffset":-14400000,"routeColor":null,"routeType":null,"routeId":null,"routeTextColor":null,"interlineWithPreviousLeg":false,"tripShortName":null,"tripBlockId":null,"headsign":null,"agencyId":null,"tripId":null,"serviceDate":null,"intermediateStops":null,"steps":[{"distance":138.77360094966463,"relativeDirection":"DEPART","streetName":"service road","absoluteDirection":"SOUTH","exit":null,"stayOn":false,"area":false,"bogusName":false,"lon":-76.6832710419985,"lat":39.9597295760251,"alerts":null,"elevation":[]},{"distance":201.8719325153749,"relativeDirection":"LEFT","streetName":"Haines Road","absoluteDirection":"NORTH","exit":null,"stayOn":false,"area":false,"bogusName":false,"lon":-76.6816898,"lat":39.9598213,"alerts":null,"elevation":[]},{"distance":98.53025812689052,"relativeDirection":"RIGHT","streetName":"Raleigh Drive","absoluteDirection":"EAST","exit":null,"stayOn":false,"area":false,"bogusName":false,"lon":-76.68118,"lat":39.9615941,"alerts":null,"elevation":[]},{"distance":324.22113995854363,"relativeDirection":"LEFT","streetName":"Erlen Drive","absoluteDirection":"NORTH","exit":null,"stayOn":false,"area":false,"bogusName":false,"lon":-76.6800351,"lat":39.9614712,"alerts":null,"elevation":[]}],"notes":null,"alerts":null,"routeShortName":null,"routeLongName":null,"boardRule":null,"alightRule":null,"rentedBike":false,"duration":593.0}]},{"id":14595,"trip_part_id":3698,"mode_id":2,"service_id":2,"server_status":200,"server_message":null,"duration":null,"walk_time":0,"transit_time":null,"wait_time":null,"walk_distance":0.0,"transfers":null,"count":null,"legs":null,"cost":null,"hidden":false,"created_at":"2015-06-26T20:57:08.668-04:00","updated_at":"2015-06-26T20:57:08.668-04:00","ride_count":null,"external_info":null,"match_score":0.25,"missing_information":true,"accommodation_mismatch":false,"missing_information_text":"disabled_missing_info:ada_eligible_missing_info:matp_missing_info:age_min60","date_mismatch":false,"time_mismatch":false,"too_late":false,"missing_accommodations":"","cost_comments":null,"selected":null,"start_time":null,"end_time":null,"is_bookable":false,"booking_confirmation":null,"duration_estimated":false,"map_image":{"url":null},"too_early":false,"returned_mode_code":"mode_paratransit","order_xml":null,"discounts":[{"fare":2.35,"comment":null,"funding_source":"Lottery","base_fare":null},{"fare":2.35,"comment":null,"funding_source":"PWD","base_fare":null},{"fare":3.2,"comment":null,"funding_source":"ADAYORK1","base_fare":null},{"fare":15.65,"comment":null,"funding_source":"Gen Pub","base_fare":null}],"segment_index":1,"start_location":{"address_components":[{"long_name":"701 Erlen Drive","short_name":"701 Erlen Drive","types":["street_address"]},{"long_name":"York","short_name":"York","types":["locality","political"]},{"long_name":"Pennsylvania","short_name":"Pennsylvania","types":["administrative_area_level_1","political"]},{"long_name":"17402","short_name":"17402","types":["postal_code"]}],"formatted_address":"701 Erlen Drive, York, Pennsylvania 17402","geometry":{"location":{"lat":39.964296,"lng":-76.678936}},"id":4718,"name":"East York Elementary School","scope":"user"},"end_location":{"address_components":[{"long_name":"1800 Bannister Street","short_name":"1800 Bannister Street","types":["street_address"]},{"long_name":"York","short_name":"York","types":["locality","political"]},{"long_name":"Pennsylvania","short_name":"Pennsylvania","types":["administrative_area_level_1","political"]},{"long_name":"17404","short_name":"17404","types":["postal_code"]}],"formatted_address":"1800 Bannister Street, York, Pennsylvania 17404","geometry":{"location":{"lat":39.958989,"lng":-76.763218}},"id":4717,"name":"West York Area High School","scope":"user"},"prebooking_questions":[{"question":"Will you be traveling with an approved escort","choices":[true,false],"code":"assistant"},{"question":"How many children or family members will be traveling with you?","choices":[0,1,2],"code":"children"}],"bookable":false,"json_legs":null},{"id":14596,"trip_part_id":3698,"mode_id":2,"service_id":7,"server_status":200,"server_message":null,"duration":null,"walk_time":0,"transit_time":null,"wait_time":null,"walk_distance":0.0,"transfers":null,"count":null,"legs":null,"cost":null,"hidden":false,"created_at":"2015-06-26T20:57:16.444-04:00","updated_at":"2015-06-26T20:57:16.444-04:00","ride_count":null,"external_info":null,"match_score":0.0,"missing_information":false,"accommodation_mismatch":false,"missing_information_text":"","date_mismatch":false,"time_mismatch":false,"too_late":false,"missing_accommodations":"","cost_comments":null,"selected":null,"start_time":null,"end_time":null,"is_bookable":false,"booking_confirmation":null,"duration_estimated":false,"map_image":{"url":null},"too_early":false,"returned_mode_code":"mode_paratransit","order_xml":null,"discounts":[{"fare":2.35,"comment":null,"funding_source":"Lottery","base_fare":null},{"fare":2.35,"comment":null,"funding_source":"PWD","base_fare":null},{"fare":3.2,"comment":null,"funding_source":"ADAYORK1","base_fare":null}],"segment_index":1,"start_location":{"address_components":[{"long_name":"701 Erlen Drive","short_name":"701 Erlen Drive","types":["street_address"]},{"long_name":"York","short_name":"York","types":["locality","political"]},{"long_name":"Pennsylvania","short_name":"Pennsylvania","types":["administrative_area_level_1","political"]},{"long_name":"17402","short_name":"17402","types":["postal_code"]}],"formatted_address":"701 Erlen Drive, York, Pennsylvania 17402","geometry":{"location":{"lat":39.964296,"lng":-76.678936}},"id":4718,"name":"East York Elementary School","scope":"user"},"end_location":{"address_components":[{"long_name":"1800 Bannister Street","short_name":"1800 Bannister Street","types":["street_address"]},{"long_name":"York","short_name":"York","types":["locality","political"]},{"long_name":"Pennsylvania","short_name":"Pennsylvania","types":["administrative_area_level_1","political"]},{"long_name":"17404","short_name":"17404","types":["postal_code"]}],"formatted_address":"1800 Bannister Street, York, Pennsylvania 17404","geometry":{"location":{"lat":39.958989,"lng":-76.763218}},"id":4717,"name":"West York Area High School","scope":"user"},"prebooking_questions":[{"question":"Will you be traveling with an approved escort","choices":[true,false],"code":"assistant"},{"question":"How many children or family members will be traveling with you?","choices":[0,1,2],"code":"children"}],"bookable":false,"json_legs":null},{"id":14595,"trip_part_id":3698,"mode_id":2,"service_id":2,"server_status":200,"server_message":null,"duration":4156,"walk_time":0,"transit_time":null,"wait_time":null,"walk_distance":0.0,"transfers":null,"count":null,"legs":null,"cost":null,"hidden":false,"created_at":"2015-06-26T20:57:08.668-04:00","updated_at":"2015-06-26T20:57:17.522-04:00","ride_count":null,"external_info":null,"match_score":0.25,"missing_information":true,"accommodation_mismatch":false,"missing_information_text":"disabled_missing_info:ada_eligible_missing_info:matp_missing_info:age_min60","date_mismatch":false,"time_mismatch":false,"too_late":false,"missing_accommodations":"","cost_comments":null,"selected":null,"start_time":"2015-06-29T16:47:05.000-04:00","end_time":"2015-06-29T17:56:21.000-04:00","is_bookable":false,"booking_confirmation":null,"duration_estimated":true,"map_image":{"url":null},"too_early":false,"returned_mode_code":"mode_paratransit","order_xml":null,"discounts":[{"fare":2.35,"comment":null,"funding_source":"Lottery","base_fare":null},{"fare":2.35,"comment":null,"funding_source":"PWD","base_fare":null},{"fare":3.2,"comment":null,"funding_source":"ADAYORK1","base_fare":null},{"fare":15.65,"comment":null,"funding_source":"Gen Pub","base_fare":null}],"segment_index":1,"start_location":{"address_components":[{"long_name":"701 Erlen Drive","short_name":"701 Erlen Drive","types":["street_address"]},{"long_name":"York","short_name":"York","types":["locality","political"]},{"long_name":"Pennsylvania","short_name":"Pennsylvania","types":["administrative_area_level_1","political"]},{"long_name":"17402","short_name":"17402","types":["postal_code"]}],"formatted_address":"701 Erlen Drive, York, Pennsylvania 17402","geometry":{"location":{"lat":39.964296,"lng":-76.67893600000002}},"id":4718,"name":"East York Elementary School","scope":"user"},"end_location":{"address_components":[{"long_name":"1800 Bannister Street","short_name":"1800 Bannister Street","types":["street_address"]},{"long_name":"York","short_name":"York","types":["locality","political"]},{"long_name":"Pennsylvania","short_name":"Pennsylvania","types":["administrative_area_level_1","political"]},{"long_name":"17404","short_name":"17404","types":["postal_code"]}],"formatted_address":"1800 Bannister Street, York, Pennsylvania 17404","geometry":{"location":{"lat":39.958989,"lng":-76.763218}},"id":4717,"name":"West York Area High School","scope":"user"},"prebooking_questions":[{"question":"Will you be traveling with an approved escort","choices":[true,false],"code":"assistant"},{"question":"How many children or family members will be traveling with you?","choices":[0,1,2],"code":"children"}],"bookable":false,"json_legs":null},{"id":14596,"trip_part_id":3698,"mode_id":2,"service_id":7,"server_status":200,"server_message":null,"duration":4156,"walk_time":0,"transit_time":null,"wait_time":null,"walk_distance":0.0,"transfers":null,"count":null,"legs":null,"cost":null,"hidden":false,"created_at":"2015-06-26T20:57:16.444-04:00","updated_at":"2015-06-26T20:57:17.526-04:00","ride_count":null,"external_info":null,"match_score":0.0,"missing_information":false,"accommodation_mismatch":false,"missing_information_text":"","date_mismatch":false,"time_mismatch":false,"too_late":false,"missing_accommodations":"","cost_comments":null,"selected":null,"start_time":"2015-06-29T16:47:05.000-04:00","end_time":"2015-06-29T17:56:21.000-04:00","is_bookable":false,"booking_confirmation":null,"duration_estimated":true,"map_image":{"url":null},"too_early":false,"returned_mode_code":"mode_paratransit","order_xml":null,"discounts":[{"fare":2.35,"comment":null,"funding_source":"Lottery","base_fare":null},{"fare":2.35,"comment":null,"funding_source":"PWD","base_fare":null},{"fare":3.2,"comment":null,"funding_source":"ADAYORK1","base_fare":null}],"segment_index":1,"start_location":{"address_components":[{"long_name":"701 Erlen Drive","short_name":"701 Erlen Drive","types":["street_address"]},{"long_name":"York","short_name":"York","types":["locality","political"]},{"long_name":"Pennsylvania","short_name":"Pennsylvania","types":["administrative_area_level_1","political"]},{"long_name":"17402","short_name":"17402","types":["postal_code"]}],"formatted_address":"701 Erlen Drive, York, Pennsylvania 17402","geometry":{"location":{"lat":39.964296,"lng":-76.67893600000002}},"id":4718,"name":"East York Elementary School","scope":"user"},"end_location":{"address_components":[{"long_name":"1800 Bannister Street","short_name":"1800 Bannister Street","types":["street_address"]},{"long_name":"York","short_name":"York","types":["locality","political"]},{"long_name":"Pennsylvania","short_name":"Pennsylvania","types":["administrative_area_level_1","political"]},{"long_name":"17404","short_name":"17404","types":["postal_code"]}],"formatted_address":"1800 Bannister Street, York, Pennsylvania 17404","geometry":{"location":{"lat":39.958989,"lng":-76.763218}},"id":4717,"name":"West York Area High School","scope":"user"},"prebooking_questions":[{"question":"Will you be traveling with an approved escort","choices":[true,false],"code":"assistant"},{"question":"How many children or family members will be traveling with you?","choices":[0,1,2],"code":"children"}],"bookable":false,"json_legs":null},{"id":14597,"trip_part_id":3698,"mode_id":1,"service_id":3,"server_status":200,"server_message":null,"duration":3086,"walk_time":779,"transit_time":2305,"wait_time":2,"walk_distance":997.8858845731818,"transfers":1,"count":null,"legs":"---\n- startTime: 1435611306000\n  endTime: 1435611899000\n  departureDelay: 0\n  arrivalDelay: 0\n  realTime: false\n  isNonExactFrequency: \n  headway: \n  distance: 763.3969315504737\n  from:\n    name: Erlen Drive\n    stopId: \n    stopCode: \n    platformCode: \n    lon: -76.67966600881111\n    lat: 39.96437079412677\n    arrival: \n    departure: 1435611306000\n    orig: ''\n    zoneId: \n    stopIndex: \n  to:\n    name: Haines Rd K-Mart\n    stopId:\n      agencyId: '210'\n      id: '765018'\n    stopCode: \n    platformCode: \n    lon: -76.6832710419985\n    lat: 39.9597295760251\n    arrival: 1435611899000\n    departure: 1435611900000\n    orig: \n    zoneId: \n    stopIndex: \n  legGeometry:\n    points: ip|rF|n_sM~Fj@`DF`DTWbFlCd@dCh@lATKdBBV\\|DA@\n    levels: \n    length: 12\n  transitLeg: false\n  mode: WALK\n  route: ''\n  agencyName: \n  agencyUrl: \n  agencyTimeZoneOffset: -14400000\n  routeColor: \n  routeType: \n  routeId: \n  routeTextColor: \n  interlineWithPreviousLeg: false\n  tripShortName: \n  tripBlockId: \n  headsign: \n  agencyId: \n  tripId: \n  serviceDate: \n  intermediateStops: \n  steps:\n  - distance: 324.22113995854363\n    relativeDirection: DEPART\n    streetName: Erlen Drive\n    absoluteDirection: SOUTH\n    exit: \n    stayOn: false\n    area: false\n    bogusName: false\n    lon: -76.67966600881111\n    lat: 39.96437079412677\n    alerts: \n    elevation: []\n  - distance: 98.53025812689052\n    relativeDirection: RIGHT\n    streetName: Raleigh Drive\n    absoluteDirection: WEST\n    exit: \n    stayOn: false\n    area: false\n    bogusName: false\n    lon: -76.6800351\n    lat: 39.9614712\n    alerts: \n    elevation: []\n  - distance: 201.8719325153749\n    relativeDirection: LEFT\n    streetName: Haines Road\n    absoluteDirection: SOUTH\n    exit: \n    stayOn: false\n    area: false\n    bogusName: false\n    lon: -76.68118\n    lat: 39.9615941\n    alerts: \n    elevation: []\n  - distance: 138.77360094966465\n    relativeDirection: RIGHT\n    streetName: service road\n    absoluteDirection: WEST\n    exit: \n    stayOn: false\n    area: false\n    bogusName: true\n    lon: -76.6816898\n    lat: 39.9598213\n    alerts: \n    elevation: []\n  notes: \n  alerts: \n  routeShortName: \n  routeLongName: \n  boardRule: \n  alightRule: \n  rentedBike: false\n  duration: 593.0\n- startTime: 1435611900000\n  endTime: 1435613400000\n  departureDelay: 0\n  arrivalDelay: 0\n  realTime: false\n  isNonExactFrequency: \n  headway: \n  distance: 4999.767934170017\n  from:\n    name: Haines Rd K-Mart\n    stopId:\n      agencyId: '210'\n      id: '765018'\n    stopCode: \n    platformCode: \n    lon: -76.683279\n    lat: 39.959727\n    arrival: 1435611899000\n    departure: 1435611900000\n    orig: \n    zoneId: '0'\n    stopIndex: 0\n  to:\n    name: Transfer Center\n    stopId:\n      agencyId: '210'\n      id: '765237'\n    stopCode: \n    platformCode: \n    lon: -76.731524\n    lat: 39.959945\n    arrival: 1435613400000\n    departure: 1435613400000\n    orig: \n    zoneId: '0'\n    stopIndex: 16\n  legGeometry:\n    points: is{rFne`sMBA]}DVyBpDt@`B`@LdGBhC@p@BlB?fA?pB?hDQbKOpBEjEOfGAp@i@zNAh@]nGY~Ha@lIEz@MpBQfEMtBC\\OfAm@dCoCjLCDyClMXhQb@bS??Bn@PvI@h@JrDFbD@jB@Zi@HYLq@^w@L_BSoAKeAEoCVS@uAb@aEjBmCrAaDbBRPTZDJFN`CnLFXf@hCR`ADNj@dD^bBZvAz@fEPt@Jf@^`B|@fE^fB^bBr@nDLf@A?hBhJzEqBtEmB\\xAfAG\n    levels: \n    length: 83\n  transitLeg: true\n  mode: BUS\n  route: 5E\n  agencyName: \n  agencyUrl: \n  agencyTimeZoneOffset: -14400000\n  routeColor: DB7093\n  routeType: 3\n  routeId: '1271'\n  routeTextColor: '000000'\n  interlineWithPreviousLeg: false\n  tripShortName: \n  tripBlockId: \n  headsign: 5e Downtown\n  agencyId: '210'\n  tripId: 54063A1024B1797\n  serviceDate: '20150629'\n  intermediateStops: \n  steps: []\n  notes: \n  alerts: \n  routeShortName: 5E\n  routeLongName: Haines Rd  Kmart  Greensprings\n  boardRule: \n  alightRule: \n  rentedBike: false\n  duration: 1500.0\n- startTime: 1435613400000\n  endTime: 1435614205000\n  departureDelay: 0\n  arrivalDelay: 0\n  realTime: false\n  isNonExactFrequency: \n  headway: \n  distance: 3454.556396043503\n  from:\n    name: Transfer Center\n    stopId:\n      agencyId: '210'\n      id: '765237'\n    stopCode: \n    platformCode: \n    lon: -76.731524\n    lat: 39.959945\n    arrival: 1435613400000\n    departure: 1435613400000\n    orig: \n    zoneId: '0'\n    stopIndex: 0\n  to:\n    name: Bannister At Seward Ob\n    stopId:\n      agencyId: '210'\n      id: '765385'\n    stopCode: \n    platformCode: \n    lon: -76.763942\n    lat: 39.960678\n    arrival: 1435614205000\n    departure: 1435614206000\n    orig: \n    zoneId: '0'\n    stopIndex: 13\n  legGeometry:\n    points: qt{rFxsisMz@?aDsOuHxC?A{Bx@cC`ALf@n@vCv@fEFVTfAb@tBx@pDBL`AlEFZrC~Lf@dCBNnCxMH`@hAtF`B~HP|@jB~IHZdC|KC@TrA_ApDwBvI@AEL]zAk@~Bi@pBs@nCo@lCm@|BIb@_@`Bk@dCEL}BrKRhHRfKTbK@V\n    levels: \n    length: 49\n  transitLeg: true\n  mode: BUS\n  route: 1W\n  agencyName: \n  agencyUrl: \n  agencyTimeZoneOffset: -14400000\n  routeColor: FF0000\n  routeType: 3\n  routeId: '1264'\n  routeTextColor: '000000'\n  interlineWithPreviousLeg: false\n  tripShortName: \n  tripBlockId: \n  headsign: W Manch Mall\n  agencyId: '210'\n  tripId: 53752A1024B1797\n  serviceDate: '20150629'\n  intermediateStops: \n  steps: []\n  notes: \n  alerts: \n  routeShortName: 1W\n  routeLongName: West Manchester Mall\n  boardRule: \n  alightRule: \n  rentedBike: false\n  duration: 805.0\n- startTime: 1435614206000\n  endTime: 1435614392000\n  departureDelay: 0\n  arrivalDelay: 0\n  realTime: false\n  isNonExactFrequency: \n  headway: \n  distance: 234.27681689841432\n  from:\n    name: Bannister At Seward Ob\n    stopId:\n      agencyId: '210'\n      id: '765385'\n    stopCode: \n    platformCode: \n    lon: -76.76394113800453\n    lat: 39.960662909175014\n    arrival: 1435614205000\n    departure: 1435614206000\n    orig: \n    zoneId: \n    stopIndex: \n  to:\n    name: service road\n    stopId: \n    stopCode: \n    platformCode: \n    lon: -76.7633366\n    lat: 39.9591893\n    arrival: 1435614392000\n    departure: \n    orig: ''\n    zoneId: \n    stopIndex: \n  legGeometry:\n    points: cy{rFt}osMAYt@A\\?TANAVCXGL?L?BLBJ@HDDHHH@H?H?FIHMJ]FSBQ?S?S\n    levels: \n    length: 25\n  transitLeg: false\n  mode: WALK\n  route: ''\n  agencyName: \n  agencyUrl: \n  agencyTimeZoneOffset: -14400000\n  routeColor: \n  routeType: \n  routeId: \n  routeTextColor: \n  interlineWithPreviousLeg: false\n  tripShortName: \n  tripBlockId: \n  headsign: \n  agencyId: \n  tripId: \n  serviceDate: \n  intermediateStops: \n  steps:\n  - distance: 10.609558098677711\n    relativeDirection: DEPART\n    streetName: Bannister Street\n    absoluteDirection: EAST\n    exit: \n    stayOn: false\n    area: false\n    bogusName: false\n    lon: -76.76394113800453\n    lat: 39.960662909175014\n    alerts: \n    elevation: []\n  - distance: 223.6672587997366\n    relativeDirection: RIGHT\n    streetName: service road\n    absoluteDirection: SOUTH\n    exit: \n    stayOn: false\n    area: false\n    bogusName: true\n    lon: -76.763817\n    lat: 39.96067\n    alerts: \n    elevation: []\n  notes: \n  alerts: \n  routeShortName: \n  routeLongName: \n  boardRule: \n  alightRule: \n  rentedBike: false\n  duration: 186.0\n","cost":"1.6","hidden":false,"created_at":"2015-06-26T20:57:17.365-04:00","updated_at":"2015-06-26T20:57:17.535-04:00","ride_count":null,"external_info":null,"match_score":-0.3,"missing_information":false,"accommodation_mismatch":false,"missing_information_text":null,"date_mismatch":false,"time_mismatch":false,"too_late":false,"missing_accommodations":"","cost_comments":null,"selected":null,"start_time":"2015-06-29T16:55:06.000-04:00","end_time":"2015-06-29T17:46:32.000-04:00","is_bookable":false,"booking_confirmation":null,"duration_estimated":false,"map_image":{"url":null},"too_early":false,"returned_mode_code":"mode_transit","order_xml":null,"discounts":null,"segment_index":1,"start_location":{"address_components":[{"long_name":"701 Erlen Drive","short_name":"701 Erlen Drive","types":["street_address"]},{"long_name":"York","short_name":"York","types":["locality","political"]},{"long_name":"Pennsylvania","short_name":"Pennsylvania","types":["administrative_area_level_1","political"]},{"long_name":"17402","short_name":"17402","types":["postal_code"]}],"formatted_address":"701 Erlen Drive, York, Pennsylvania 17402","geometry":{"location":{"lat":39.964296,"lng":-76.678936}},"id":4718,"name":"East York Elementary School","scope":"user"},"end_location":{"address_components":[{"long_name":"1800 Bannister Street","short_name":"1800 Bannister Street","types":["street_address"]},{"long_name":"York","short_name":"York","types":["locality","political"]},{"long_name":"Pennsylvania","short_name":"Pennsylvania","types":["administrative_area_level_1","political"]},{"long_name":"17404","short_name":"17404","types":["postal_code"]}],"formatted_address":"1800 Bannister Street, York, Pennsylvania 17404","geometry":{"location":{"lat":39.958989,"lng":-76.763218}},"id":4717,"name":"West York Area High School","scope":"user"},"prebooking_questions":[{"question":"Will you be traveling with an approved escort","choices":[true,false],"code":"assistant"},{"question":"How many children or family members will be traveling with you?","choices":[0,1,2],"code":"children"}],"bookable":false,"json_legs":[{"startTime":1435611306000,"endTime":1435611899000,"departureDelay":0,"arrivalDelay":0,"realTime":false,"isNonExactFrequency":null,"headway":null,"distance":763.3969315504737,"from":{"name":"Erlen Drive","stopId":null,"stopCode":null,"platformCode":null,"lon":-76.67966600881111,"lat":39.96437079412677,"arrival":null,"departure":1435611306000,"orig":"","zoneId":null,"stopIndex":null},"to":{"name":"Haines Rd K-Mart","stopId":{"agencyId":"210","id":"765018"},"stopCode":null,"platformCode":null,"lon":-76.6832710419985,"lat":39.9597295760251,"arrival":1435611899000,"departure":1435611900000,"orig":null,"zoneId":null,"stopIndex":null},"legGeometry":{"points":"ip|rF|n_sM~Fj@`DF`DTWbFlCd@dCh@lATKdBBV\\|DA@","levels":null,"length":12},"transitLeg":false,"mode":"WALK","route":"","agencyName":null,"agencyUrl":null,"agencyTimeZoneOffset":-14400000,"routeColor":null,"routeType":null,"routeId":null,"routeTextColor":null,"interlineWithPreviousLeg":false,"tripShortName":null,"tripBlockId":null,"headsign":null,"agencyId":null,"tripId":null,"serviceDate":null,"intermediateStops":null,"steps":[{"distance":324.22113995854363,"relativeDirection":"DEPART","streetName":"Erlen Drive","absoluteDirection":"SOUTH","exit":null,"stayOn":false,"area":false,"bogusName":false,"lon":-76.67966600881111,"lat":39.96437079412677,"alerts":null,"elevation":[]},{"distance":98.53025812689052,"relativeDirection":"RIGHT","streetName":"Raleigh Drive","absoluteDirection":"WEST","exit":null,"stayOn":false,"area":false,"bogusName":false,"lon":-76.6800351,"lat":39.9614712,"alerts":null,"elevation":[]},{"distance":201.8719325153749,"relativeDirection":"LEFT","streetName":"Haines Road","absoluteDirection":"SOUTH","exit":null,"stayOn":false,"area":false,"bogusName":false,"lon":-76.68118,"lat":39.9615941,"alerts":null,"elevation":[]},{"distance":138.77360094966465,"relativeDirection":"RIGHT","streetName":"service road","absoluteDirection":"WEST","exit":null,"stayOn":false,"area":false,"bogusName":true,"lon":-76.6816898,"lat":39.9598213,"alerts":null,"elevation":[]}],"notes":null,"alerts":null,"routeShortName":null,"routeLongName":null,"boardRule":null,"alightRule":null,"rentedBike":false,"duration":593.0},{"startTime":1435611900000,"endTime":1435613400000,"departureDelay":0,"arrivalDelay":0,"realTime":false,"isNonExactFrequency":null,"headway":null,"distance":4999.767934170017,"from":{"name":"Haines Rd K-Mart","stopId":{"agencyId":"210","id":"765018"},"stopCode":null,"platformCode":null,"lon":-76.683279,"lat":39.959727,"arrival":1435611899000,"departure":1435611900000,"orig":null,"zoneId":"0","stopIndex":0},"to":{"name":"Transfer Center","stopId":{"agencyId":"210","id":"765237"},"stopCode":null,"platformCode":null,"lon":-76.731524,"lat":39.959945,"arrival":1435613400000,"departure":1435613400000,"orig":null,"zoneId":"0","stopIndex":16},"legGeometry":{"points":"is{rFne`sMBA]}DVyBpDt@`B`@LdGBhC@p@BlB?fA?pB?hDQbKOpBEjEOfGAp@i@zNAh@]nGY~Ha@lIEz@MpBQfEMtBC\\OfAm@dCoCjLCDyClMXhQb@bS??Bn@PvI@h@JrDFbD@jB@Zi@HYLq@^w@L_BSoAKeAEoCVS@uAb@aEjBmCrAaDbBRPTZDJFN`CnLFXf@hCR`ADNj@dD^bBZvAz@fEPt@Jf@^`B|@fE^fB^bBr@nDLf@A?hBhJzEqBtEmB\\xAfAG","levels":null,"length":83},"transitLeg":true,"mode":"BUS","route":"5E","agencyName":null,"agencyUrl":null,"agencyTimeZoneOffset":-14400000,"routeColor":"DB7093","routeType":3,"routeId":"1271","routeTextColor":"000000","interlineWithPreviousLeg":false,"tripShortName":null,"tripBlockId":null,"headsign":"5e Downtown","agencyId":"210","tripId":"54063A1024B1797","serviceDate":"20150629","intermediateStops":null,"steps":[],"notes":null,"alerts":null,"routeShortName":"5E","routeLongName":"Haines Rd  Kmart  Greensprings","boardRule":null,"alightRule":null,"rentedBike":false,"duration":1500.0},{"startTime":1435613400000,"endTime":1435614205000,"departureDelay":0,"arrivalDelay":0,"realTime":false,"isNonExactFrequency":null,"headway":null,"distance":3454.556396043503,"from":{"name":"Transfer Center","stopId":{"agencyId":"210","id":"765237"},"stopCode":null,"platformCode":null,"lon":-76.731524,"lat":39.959945,"arrival":1435613400000,"departure":1435613400000,"orig":null,"zoneId":"0","stopIndex":0},"to":{"name":"Bannister At Seward Ob","stopId":{"agencyId":"210","id":"765385"},"stopCode":null,"platformCode":null,"lon":-76.763942,"lat":39.960678,"arrival":1435614205000,"departure":1435614206000,"orig":null,"zoneId":"0","stopIndex":13},"legGeometry":{"points":"qt{rFxsisMz@?aDsOuHxC?A{Bx@cC`ALf@n@vCv@fEFVTfAb@tBx@pDBL`AlEFZrC~Lf@dCBNnCxMH`@hAtF`B~HP|@jB~IHZdC|KC@TrA_ApDwBvI@AEL]zAk@~Bi@pBs@nCo@lCm@|BIb@_@`Bk@dCEL}BrKRhHRfKTbK@V","levels":null,"length":49},"transitLeg":true,"mode":"BUS","route":"1W","agencyName":null,"agencyUrl":null,"agencyTimeZoneOffset":-14400000,"routeColor":"FF0000","routeType":3,"routeId":"1264","routeTextColor":"000000","interlineWithPreviousLeg":false,"tripShortName":null,"tripBlockId":null,"headsign":"W Manch Mall","agencyId":"210","tripId":"53752A1024B1797","serviceDate":"20150629","intermediateStops":null,"steps":[],"notes":null,"alerts":null,"routeShortName":"1W","routeLongName":"West Manchester Mall","boardRule":null,"alightRule":null,"rentedBike":false,"duration":805.0},{"startTime":1435614206000,"endTime":1435614392000,"departureDelay":0,"arrivalDelay":0,"realTime":false,"isNonExactFrequency":null,"headway":null,"distance":234.27681689841432,"from":{"name":"Bannister At Seward Ob","stopId":{"agencyId":"210","id":"765385"},"stopCode":null,"platformCode":null,"lon":-76.76394113800453,"lat":39.960662909175014,"arrival":1435614205000,"departure":1435614206000,"orig":null,"zoneId":null,"stopIndex":null},"to":{"name":"service road","stopId":null,"stopCode":null,"platformCode":null,"lon":-76.7633366,"lat":39.9591893,"arrival":1435614392000,"departure":null,"orig":"","zoneId":null,"stopIndex":null},"legGeometry":{"points":"cy{rFt}osMAYt@A\\?TANAVCXGL?L?BLBJ@HDDHHH@H?H?FIHMJ]FSBQ?S?S","levels":null,"length":25},"transitLeg":false,"mode":"WALK","route":"","agencyName":null,"agencyUrl":null,"agencyTimeZoneOffset":-14400000,"routeColor":null,"routeType":null,"routeId":null,"routeTextColor":null,"interlineWithPreviousLeg":false,"tripShortName":null,"tripBlockId":null,"headsign":null,"agencyId":null,"tripId":null,"serviceDate":null,"intermediateStops":null,"steps":[{"distance":10.609558098677711,"relativeDirection":"DEPART","streetName":"Bannister Street","absoluteDirection":"EAST","exit":null,"stayOn":false,"area":false,"bogusName":false,"lon":-76.76394113800453,"lat":39.960662909175014,"alerts":null,"elevation":[]},{"distance":223.6672587997366,"relativeDirection":"RIGHT","streetName":"service road","absoluteDirection":"SOUTH","exit":null,"stayOn":false,"area":false,"bogusName":true,"lon":-76.763817,"lat":39.96067,"alerts":null,"elevation":[]}],"notes":null,"alerts":null,"routeShortName":null,"routeLongName":null,"boardRule":null,"alightRule":null,"rentedBike":false,"duration":186.0}]},{"id":14598,"trip_part_id":3698,"mode_id":1,"service_id":3,"server_status":200,"server_message":null,"duration":3026,"walk_time":779,"transit_time":1705,"wait_time":542,"walk_distance":997.8858845731818,"transfers":1,"count":null,"legs":"---\n- startTime: 1435609566000\n  endTime: 1435610159000\n  departureDelay: 0\n  arrivalDelay: 0\n  realTime: false\n  isNonExactFrequency: \n  headway: \n  distance: 763.3969315504737\n  from:\n    name: Erlen Drive\n    stopId: \n    stopCode: \n    platformCode: \n    lon: -76.67966600881111\n    lat: 39.96437079412677\n    arrival: \n    departure: 1435609566000\n    orig: ''\n    zoneId: \n    stopIndex: \n  to:\n    name: Haines Rd K-Mart\n    stopId:\n      agencyId: '210'\n      id: '765018'\n    stopCode: \n    platformCode: \n    lon: -76.6832710419985\n    lat: 39.9597295760251\n    arrival: 1435610159000\n    departure: 1435610160000\n    orig: \n    zoneId: \n    stopIndex: \n  legGeometry:\n    points: ip|rF|n_sM~Fj@`DF`DTWbFlCd@dCh@lATKdBBV\\|DA@\n    levels: \n    length: 12\n  transitLeg: false\n  mode: WALK\n  route: ''\n  agencyName: \n  agencyUrl: \n  agencyTimeZoneOffset: -14400000\n  routeColor: \n  routeType: \n  routeId: \n  routeTextColor: \n  interlineWithPreviousLeg: false\n  tripShortName: \n  tripBlockId: \n  headsign: \n  agencyId: \n  tripId: \n  serviceDate: \n  intermediateStops: \n  steps:\n  - distance: 324.22113995854363\n    relativeDirection: DEPART\n    streetName: Erlen Drive\n    absoluteDirection: SOUTH\n    exit: \n    stayOn: false\n    area: false\n    bogusName: false\n    lon: -76.67966600881111\n    lat: 39.96437079412677\n    alerts: \n    elevation: []\n  - distance: 98.53025812689052\n    relativeDirection: RIGHT\n    streetName: Raleigh Drive\n    absoluteDirection: WEST\n    exit: \n    stayOn: false\n    area: false\n    bogusName: false\n    lon: -76.6800351\n    lat: 39.9614712\n    alerts: \n    elevation: []\n  - distance: 201.8719325153749\n    relativeDirection: LEFT\n    streetName: Haines Road\n    absoluteDirection: SOUTH\n    exit: \n    stayOn: false\n    area: false\n    bogusName: false\n    lon: -76.68118\n    lat: 39.9615941\n    alerts: \n    elevation: []\n  - distance: 138.77360094966465\n    relativeDirection: RIGHT\n    streetName: service road\n    absoluteDirection: WEST\n    exit: \n    stayOn: false\n    area: false\n    bogusName: true\n    lon: -76.6816898\n    lat: 39.9598213\n    alerts: \n    elevation: []\n  notes: \n  alerts: \n  routeShortName: \n  routeLongName: \n  boardRule: \n  alightRule: \n  rentedBike: false\n  duration: 593.0\n- startTime: 1435610160000\n  endTime: 1435611060000\n  departureDelay: 0\n  arrivalDelay: 0\n  realTime: false\n  isNonExactFrequency: \n  headway: \n  distance: 4112.015514885079\n  from:\n    name: Haines Rd K-Mart\n    stopId:\n      agencyId: '210'\n      id: '765018'\n    stopCode: \n    platformCode: \n    lon: -76.683279\n    lat: 39.959727\n    arrival: 1435610159000\n    departure: 1435610160000\n    orig: \n    zoneId: '0'\n    stopIndex: 9\n  to:\n    name: Transfer Center\n    stopId:\n      agencyId: '210'\n      id: '765237'\n    stopCode: \n    platformCode: \n    lon: -76.731524\n    lat: 39.959945\n    arrival: 1435611060000\n    departure: 1435611600000\n    orig: \n    zoneId: '0'\n    stopIndex: 10\n  legGeometry:\n    points: ks{rFhe`sM@?FC`Ck@g@yCsBa@J_ArGlARtKHxMDJGnFe@dI?nFUvHoDdy@UtB{Ix^Ip@jBb}@\\tBbBfI~B~KtBjKkVxJqJ~DjJnc@rL}EV|ArAE\n    levels: \n    length: 30\n  transitLeg: true\n  mode: BUS\n  route: 83N\n  agencyName: \n  agencyUrl: \n  agencyTimeZoneOffset: -14400000\n  routeColor: 7685B8\n  routeType: 3\n  routeId: '1263'\n  routeTextColor: FFFFFF\n  interlineWithPreviousLeg: false\n  tripShortName: \n  tripBlockId: \n  headsign: Transfer Center\n  agencyId: '210'\n  tripId: 49164A1024B1797\n  serviceDate: '20150629'\n  intermediateStops: \n  steps: []\n  notes: \n  alerts: \n  routeShortName: 83N\n  routeLongName: Harrisburg Express\n  boardRule: \n  alightRule: \n  rentedBike: false\n  duration: 900.0\n- startTime: 1435611600000\n  endTime: 1435612405000\n  departureDelay: 0\n  arrivalDelay: 0\n  realTime: false\n  isNonExactFrequency: \n  headway: \n  distance: 3454.556396043503\n  from:\n    name: Transfer Center\n    stopId:\n      agencyId: '210'\n      id: '765237'\n    stopCode: \n    platformCode: \n    lon: -76.731524\n    lat: 39.959945\n    arrival: 1435611060000\n    departure: 1435611600000\n    orig: \n    zoneId: '0'\n    stopIndex: 0\n  to:\n    name: Bannister At Seward Ob\n    stopId:\n      agencyId: '210'\n      id: '765385'\n    stopCode: \n    platformCode: \n    lon: -76.763942\n    lat: 39.960678\n    arrival: 1435612405000\n    departure: 1435612406000\n    orig: \n    zoneId: '0'\n    stopIndex: 13\n  legGeometry:\n    points: qt{rFxsisMz@?aDsOuHxC?A{Bx@cC`ALf@n@vCv@fEFVTfAb@tBx@pDBL`AlEFZrC~Lf@dCBNnCxMH`@hAtF`B~HP|@jB~IHZdC|KC@TrA_ApDwBvI@AEL]zAk@~Bi@pBs@nCo@lCm@|BIb@_@`Bk@dCEL}BrKRhHRfKTbK@V\n    levels: \n    length: 49\n  transitLeg: true\n  mode: BUS\n  route: 1W\n  agencyName: \n  agencyUrl: \n  agencyTimeZoneOffset: -14400000\n  routeColor: FF0000\n  routeType: 3\n  routeId: '1264'\n  routeTextColor: '000000'\n  interlineWithPreviousLeg: false\n  tripShortName: \n  tripBlockId: \n  headsign: W Manch Mall\n  agencyId: '210'\n  tripId: 53751A1024B1797\n  serviceDate: '20150629'\n  intermediateStops: \n  steps: []\n  notes: \n  alerts: \n  routeShortName: 1W\n  routeLongName: West Manchester Mall\n  boardRule: \n  alightRule: \n  rentedBike: false\n  duration: 805.0\n- startTime: 1435612406000\n  endTime: 1435612592000\n  departureDelay: 0\n  arrivalDelay: 0\n  realTime: false\n  isNonExactFrequency: \n  headway: \n  distance: 234.27681689841432\n  from:\n    name: Bannister At Seward Ob\n    stopId:\n      agencyId: '210'\n      id: '765385'\n    stopCode: \n    platformCode: \n    lon: -76.76394113800453\n    lat: 39.960662909175014\n    arrival: 1435612405000\n    departure: 1435612406000\n    orig: \n    zoneId: \n    stopIndex: \n  to:\n    name: service road\n    stopId: \n    stopCode: \n    platformCode: \n    lon: -76.7633366\n    lat: 39.9591893\n    arrival: 1435612592000\n    departure: \n    orig: ''\n    zoneId: \n    stopIndex: \n  legGeometry:\n    points: cy{rFt}osMAYt@A\\?TANAVCXGL?L?BLBJ@HDDHHH@H?H?FIHMJ]FSBQ?S?S\n    levels: \n    length: 25\n  transitLeg: false\n  mode: WALK\n  route: ''\n  agencyName: \n  agencyUrl: \n  agencyTimeZoneOffset: -14400000\n  routeColor: \n  routeType: \n  routeId: \n  routeTextColor: \n  interlineWithPreviousLeg: false\n  tripShortName: \n  tripBlockId: \n  headsign: \n  agencyId: \n  tripId: \n  serviceDate: \n  intermediateStops: \n  steps:\n  - distance: 10.609558098677711\n    relativeDirection: DEPART\n    streetName: Bannister Street\n    absoluteDirection: EAST\n    exit: \n    stayOn: false\n    area: false\n    bogusName: false\n    lon: -76.76394113800453\n    lat: 39.960662909175014\n    alerts: \n    elevation: []\n  - distance: 223.6672587997366\n    relativeDirection: RIGHT\n    streetName: service road\n    absoluteDirection: SOUTH\n    exit: \n    stayOn: false\n    area: false\n    bogusName: true\n    lon: -76.763817\n    lat: 39.96067\n    alerts: \n    elevation: []\n  notes: \n  alerts: \n  routeShortName: \n  routeLongName: \n  boardRule: \n  alightRule: \n  rentedBike: false\n  duration: 186.0\n","cost":"5.1","hidden":false,"created_at":"2015-06-26T20:57:17.423-04:00","updated_at":"2015-06-26T20:57:17.542-04:00","ride_count":null,"external_info":null,"match_score":-0.19999999999999998,"missing_information":false,"accommodation_mismatch":false,"missing_information_text":null,"date_mismatch":false,"time_mismatch":false,"too_late":false,"missing_accommodations":"","cost_comments":null,"selected":null,"start_time":"2015-06-29T16:26:06.000-04:00","end_time":"2015-06-29T17:16:32.000-04:00","is_bookable":false,"booking_confirmation":null,"duration_estimated":false,"map_image":{"url":null},"too_early":false,"returned_mode_code":"mode_transit","order_xml":null,"discounts":null,"segment_index":1,"start_location":{"address_components":[{"long_name":"701 Erlen Drive","short_name":"701 Erlen Drive","types":["street_address"]},{"long_name":"York","short_name":"York","types":["locality","political"]},{"long_name":"Pennsylvania","short_name":"Pennsylvania","types":["administrative_area_level_1","political"]},{"long_name":"17402","short_name":"17402","types":["postal_code"]}],"formatted_address":"701 Erlen Drive, York, Pennsylvania 17402","geometry":{"location":{"lat":39.964296,"lng":-76.678936}},"id":4718,"name":"East York Elementary School","scope":"user"},"end_location":{"address_components":[{"long_name":"1800 Bannister Street","short_name":"1800 Bannister Street","types":["street_address"]},{"long_name":"York","short_name":"York","types":["locality","political"]},{"long_name":"Pennsylvania","short_name":"Pennsylvania","types":["administrative_area_level_1","political"]},{"long_name":"17404","short_name":"17404","types":["postal_code"]}],"formatted_address":"1800 Bannister Street, York, Pennsylvania 17404","geometry":{"location":{"lat":39.958989,"lng":-76.763218}},"id":4717,"name":"West York Area High School","scope":"user"},"prebooking_questions":[{"question":"Will you be traveling with an approved escort","choices":[true,false],"code":"assistant"},{"question":"How many children or family members will be traveling with you?","choices":[0,1,2],"code":"children"}],"bookable":false,"json_legs":[{"startTime":1435609566000,"endTime":1435610159000,"departureDelay":0,"arrivalDelay":0,"realTime":false,"isNonExactFrequency":null,"headway":null,"distance":763.3969315504737,"from":{"name":"Erlen Drive","stopId":null,"stopCode":null,"platformCode":null,"lon":-76.67966600881111,"lat":39.96437079412677,"arrival":null,"departure":1435609566000,"orig":"","zoneId":null,"stopIndex":null},"to":{"name":"Haines Rd K-Mart","stopId":{"agencyId":"210","id":"765018"},"stopCode":null,"platformCode":null,"lon":-76.6832710419985,"lat":39.9597295760251,"arrival":1435610159000,"departure":1435610160000,"orig":null,"zoneId":null,"stopIndex":null},"legGeometry":{"points":"ip|rF|n_sM~Fj@`DF`DTWbFlCd@dCh@lATKdBBV\\|DA@","levels":null,"length":12},"transitLeg":false,"mode":"WALK","route":"","agencyName":null,"agencyUrl":null,"agencyTimeZoneOffset":-14400000,"routeColor":null,"routeType":null,"routeId":null,"routeTextColor":null,"interlineWithPreviousLeg":false,"tripShortName":null,"tripBlockId":null,"headsign":null,"agencyId":null,"tripId":null,"serviceDate":null,"intermediateStops":null,"steps":[{"distance":324.22113995854363,"relativeDirection":"DEPART","streetName":"Erlen Drive","absoluteDirection":"SOUTH","exit":null,"stayOn":false,"area":false,"bogusName":false,"lon":-76.67966600881111,"lat":39.96437079412677,"alerts":null,"elevation":[]},{"distance":98.53025812689052,"relativeDirection":"RIGHT","streetName":"Raleigh Drive","absoluteDirection":"WEST","exit":null,"stayOn":false,"area":false,"bogusName":false,"lon":-76.6800351,"lat":39.9614712,"alerts":null,"elevation":[]},{"distance":201.8719325153749,"relativeDirection":"LEFT","streetName":"Haines Road","absoluteDirection":"SOUTH","exit":null,"stayOn":false,"area":false,"bogusName":false,"lon":-76.68118,"lat":39.9615941,"alerts":null,"elevation":[]},{"distance":138.77360094966465,"relativeDirection":"RIGHT","streetName":"service road","absoluteDirection":"WEST","exit":null,"stayOn":false,"area":false,"bogusName":true,"lon":-76.6816898,"lat":39.9598213,"alerts":null,"elevation":[]}],"notes":null,"alerts":null,"routeShortName":null,"routeLongName":null,"boardRule":null,"alightRule":null,"rentedBike":false,"duration":593.0},{"startTime":1435610160000,"endTime":1435611060000,"departureDelay":0,"arrivalDelay":0,"realTime":false,"isNonExactFrequency":null,"headway":null,"distance":4112.015514885079,"from":{"name":"Haines Rd K-Mart","stopId":{"agencyId":"210","id":"765018"},"stopCode":null,"platformCode":null,"lon":-76.683279,"lat":39.959727,"arrival":1435610159000,"departure":1435610160000,"orig":null,"zoneId":"0","stopIndex":9},"to":{"name":"Transfer Center","stopId":{"agencyId":"210","id":"765237"},"stopCode":null,"platformCode":null,"lon":-76.731524,"lat":39.959945,"arrival":1435611060000,"departure":1435611600000,"orig":null,"zoneId":"0","stopIndex":10},"legGeometry":{"points":"ks{rFhe`sM@?FC`Ck@g@yCsBa@J_ArGlARtKHxMDJGnFe@dI?nFUvHoDdy@UtB{Ix^Ip@jBb}@\\tBbBfI~B~KtBjKkVxJqJ~DjJnc@rL}EV|ArAE","levels":null,"length":30},"transitLeg":true,"mode":"BUS","route":"83N","agencyName":null,"agencyUrl":null,"agencyTimeZoneOffset":-14400000,"routeColor":"7685B8","routeType":3,"routeId":"1263","routeTextColor":"FFFFFF","interlineWithPreviousLeg":false,"tripShortName":null,"tripBlockId":null,"headsign":"Transfer Center","agencyId":"210","tripId":"49164A1024B1797","serviceDate":"20150629","intermediateStops":null,"steps":[],"notes":null,"alerts":null,"routeShortName":"83N","routeLongName":"Harrisburg Express","boardRule":null,"alightRule":null,"rentedBike":false,"duration":900.0},{"startTime":1435611600000,"endTime":1435612405000,"departureDelay":0,"arrivalDelay":0,"realTime":false,"isNonExactFrequency":null,"headway":null,"distance":3454.556396043503,"from":{"name":"Transfer Center","stopId":{"agencyId":"210","id":"765237"},"stopCode":null,"platformCode":null,"lon":-76.731524,"lat":39.959945,"arrival":1435611060000,"departure":1435611600000,"orig":null,"zoneId":"0","stopIndex":0},"to":{"name":"Bannister At Seward Ob","stopId":{"agencyId":"210","id":"765385"},"stopCode":null,"platformCode":null,"lon":-76.763942,"lat":39.960678,"arrival":1435612405000,"departure":1435612406000,"orig":null,"zoneId":"0","stopIndex":13},"legGeometry":{"points":"qt{rFxsisMz@?aDsOuHxC?A{Bx@cC`ALf@n@vCv@fEFVTfAb@tBx@pDBL`AlEFZrC~Lf@dCBNnCxMH`@hAtF`B~HP|@jB~IHZdC|KC@TrA_ApDwBvI@AEL]zAk@~Bi@pBs@nCo@lCm@|BIb@_@`Bk@dCEL}BrKRhHRfKTbK@V","levels":null,"length":49},"transitLeg":true,"mode":"BUS","route":"1W","agencyName":null,"agencyUrl":null,"agencyTimeZoneOffset":-14400000,"routeColor":"FF0000","routeType":3,"routeId":"1264","routeTextColor":"000000","interlineWithPreviousLeg":false,"tripShortName":null,"tripBlockId":null,"headsign":"W Manch Mall","agencyId":"210","tripId":"53751A1024B1797","serviceDate":"20150629","intermediateStops":null,"steps":[],"notes":null,"alerts":null,"routeShortName":"1W","routeLongName":"West Manchester Mall","boardRule":null,"alightRule":null,"rentedBike":false,"duration":805.0},{"startTime":1435612406000,"endTime":1435612592000,"departureDelay":0,"arrivalDelay":0,"realTime":false,"isNonExactFrequency":null,"headway":null,"distance":234.27681689841432,"from":{"name":"Bannister At Seward Ob","stopId":{"agencyId":"210","id":"765385"},"stopCode":null,"platformCode":null,"lon":-76.76394113800453,"lat":39.960662909175014,"arrival":1435612405000,"departure":1435612406000,"orig":null,"zoneId":null,"stopIndex":null},"to":{"name":"service road","stopId":null,"stopCode":null,"platformCode":null,"lon":-76.7633366,"lat":39.9591893,"arrival":1435612592000,"departure":null,"orig":"","zoneId":null,"stopIndex":null},"legGeometry":{"points":"cy{rFt}osMAYt@A\\?TANAVCXGL?L?BLBJ@HDDHHH@H?H?FIHMJ]FSBQ?S?S","levels":null,"length":25},"transitLeg":false,"mode":"WALK","route":"","agencyName":null,"agencyUrl":null,"agencyTimeZoneOffset":-14400000,"routeColor":null,"routeType":null,"routeId":null,"routeTextColor":null,"interlineWithPreviousLeg":false,"tripShortName":null,"tripBlockId":null,"headsign":null,"agencyId":null,"tripId":null,"serviceDate":null,"intermediateStops":null,"steps":[{"distance":10.609558098677711,"relativeDirection":"DEPART","streetName":"Bannister Street","absoluteDirection":"EAST","exit":null,"stayOn":false,"area":false,"bogusName":false,"lon":-76.76394113800453,"lat":39.960662909175014,"alerts":null,"elevation":[]},{"distance":223.6672587997366,"relativeDirection":"RIGHT","streetName":"service road","absoluteDirection":"SOUTH","exit":null,"stayOn":false,"area":false,"bogusName":true,"lon":-76.763817,"lat":39.96067,"alerts":null,"elevation":[]}],"notes":null,"alerts":null,"routeShortName":null,"routeLongName":null,"boardRule":null,"alightRule":null,"rentedBike":false,"duration":186.0}]},{"id":14599,"trip_part_id":3698,"mode_id":1,"service_id":3,"server_status":200,"server_message":null,"duration":3014,"walk_time":1332,"transit_time":1680,"wait_time":2,"walk_distance":1718.7537311824622,"transfers":1,"count":null,"legs":"---\n- startTime: 1435609506000\n  endTime: 1435610099000\n  departureDelay: 0\n  arrivalDelay: 0\n  realTime: false\n  isNonExactFrequency: \n  headway: \n  distance: 763.3969315504737\n  from:\n    name: Erlen Drive\n    stopId: \n    stopCode: \n    platformCode: \n    lon: -76.67966600881111\n    lat: 39.96437079412677\n    arrival: \n    departure: 1435609506000\n    orig: ''\n    zoneId: \n    stopIndex: \n  to:\n    name: Haines Rd K-Mart\n    stopId:\n      agencyId: '210'\n      id: '765018'\n    stopCode: \n    platformCode: \n    lon: -76.6832710419985\n    lat: 39.9597295760251\n    arrival: 1435610099000\n    departure: 1435610100000\n    orig: \n    zoneId: \n    stopIndex: \n  legGeometry:\n    points: ip|rF|n_sM~Fj@`DF`DTWbFlCd@dCh@lATKdBBV\\|DA@\n    levels: \n    length: 12\n  transitLeg: false\n  mode: WALK\n  route: ''\n  agencyName: \n  agencyUrl: \n  agencyTimeZoneOffset: -14400000\n  routeColor: \n  routeType: \n  routeId: \n  routeTextColor: \n  interlineWithPreviousLeg: false\n  tripShortName: \n  tripBlockId: \n  headsign: \n  agencyId: \n  tripId: \n  serviceDate: \n  intermediateStops: \n  steps:\n  - distance: 324.22113995854363\n    relativeDirection: DEPART\n    streetName: Erlen Drive\n    absoluteDirection: SOUTH\n    exit: \n    stayOn: false\n    area: false\n    bogusName: false\n    lon: -76.67966600881111\n    lat: 39.96437079412677\n    alerts: \n    elevation: []\n  - distance: 98.53025812689052\n    relativeDirection: RIGHT\n    streetName: Raleigh Drive\n    absoluteDirection: WEST\n    exit: \n    stayOn: false\n    area: false\n    bogusName: false\n    lon: -76.6800351\n    lat: 39.9614712\n    alerts: \n    elevation: []\n  - distance: 201.8719325153749\n    relativeDirection: LEFT\n    streetName: Haines Road\n    absoluteDirection: SOUTH\n    exit: \n    stayOn: false\n    area: false\n    bogusName: false\n    lon: -76.68118\n    lat: 39.9615941\n    alerts: \n    elevation: []\n  - distance: 138.77360094966465\n    relativeDirection: RIGHT\n    streetName: service road\n    absoluteDirection: WEST\n    exit: \n    stayOn: false\n    area: false\n    bogusName: true\n    lon: -76.6816898\n    lat: 39.9598213\n    alerts: \n    elevation: []\n  notes: \n  alerts: \n  routeShortName: \n  routeLongName: \n  boardRule: \n  alightRule: \n  rentedBike: false\n  duration: 593.0\n- startTime: 1435610100000\n  endTime: 1435611600000\n  departureDelay: 0\n  arrivalDelay: 0\n  realTime: false\n  isNonExactFrequency: \n  headway: \n  distance: 4999.767934170017\n  from:\n    name: Haines Rd K-Mart\n    stopId:\n      agencyId: '210'\n      id: '765018'\n    stopCode: \n    platformCode: \n    lon: -76.683279\n    lat: 39.959727\n    arrival: 1435610099000\n    departure: 1435610100000\n    orig: \n    zoneId: '0'\n    stopIndex: 0\n  to:\n    name: Transfer Center\n    stopId:\n      agencyId: '210'\n      id: '765237'\n    stopCode: \n    platformCode: \n    lon: -76.731524\n    lat: 39.959945\n    arrival: 1435611600000\n    departure: 1435611600000\n    orig: \n    zoneId: '0'\n    stopIndex: 16\n  legGeometry:\n    points: is{rFne`sMBA]}DVyBpDt@`B`@LdGBhC@p@BlB?fA?pB?hDQbKOpBEjEOfGAp@i@zNAh@]nGY~Ha@lIEz@MpBQfEMtBC\\OfAm@dCoCjLCDyClMXhQb@bS??Bn@PvI@h@JrDFbD@jB@Zi@HYLq@^w@L_BSoAKeAEoCVS@uAb@aEjBmCrAaDbBRPTZDJFN`CnLFXf@hCR`ADNj@dD^bBZvAz@fEPt@Jf@^`B|@fE^fB^bBr@nDLf@A?hBhJzEqBtEmB\\xAfAG\n    levels: \n    length: 83\n  transitLeg: true\n  mode: BUS\n  route: 5E\n  agencyName: \n  agencyUrl: \n  agencyTimeZoneOffset: -14400000\n  routeColor: DB7093\n  routeType: 3\n  routeId: '1271'\n  routeTextColor: '000000'\n  interlineWithPreviousLeg: false\n  tripShortName: \n  tripBlockId: \n  headsign: 5e Downtown\n  agencyId: '210'\n  tripId: 54062A1024B1797\n  serviceDate: '20150629'\n  intermediateStops: \n  steps: []\n  notes: \n  alerts: \n  routeShortName: 5E\n  routeLongName: Haines Rd  Kmart  Greensprings\n  boardRule: \n  alightRule: \n  rentedBike: false\n  duration: 1500.0\n- startTime: 1435611600000\n  endTime: 1435611780000\n  departureDelay: 0\n  arrivalDelay: 0\n  realTime: false\n  isNonExactFrequency: \n  headway: \n  distance: 2659.2172677762774\n  from:\n    name: Transfer Center\n    stopId:\n      agencyId: '210'\n      id: '765237'\n    stopCode: \n    platformCode: \n    lon: -76.731524\n    lat: 39.959945\n    arrival: 1435611600000\n    departure: 1435611600000\n    orig: \n    zoneId: '0'\n    stopIndex: 0\n  to:\n    name: W Market At Adams St Ob\n    stopId:\n      agencyId: '210'\n      id: '765382'\n    stopCode: \n    platformCode: \n    lon: -76.761542\n    lat: 39.953545\n    arrival: 1435611780000\n    departure: 1435611781000\n    orig: \n    zoneId: '0'\n    stopIndex: 2\n  legGeometry:\n    points: as{rFprisMc@qBiCbAwAj@u@\\h@fCBN\\bBb@rBpApFlCxM`EdSxD~PbCfLn@~C\\zAH\\fEbS`BtHhA`F\\vBfAzFfAtFTlHVbKDzARtHDvA\n    levels: \n    length: 28\n  transitLeg: true\n  mode: BUS\n  route: '16'\n  agencyName: \n  agencyUrl: \n  agencyTimeZoneOffset: -14400000\n  routeColor: D3D3D3\n  routeType: 3\n  routeId: '1273'\n  routeTextColor: '000000'\n  interlineWithPreviousLeg: false\n  tripShortName: \n  tripBlockId: \n  headsign: Hanover Spring Grove\n  agencyId: '210'\n  tripId: 54128A1024B1797\n  serviceDate: '20150629'\n  intermediateStops: \n  steps: []\n  notes: \n  alerts: \n  routeShortName: '16'\n  routeLongName: York To Hanover\n  boardRule: \n  alightRule: \n  rentedBike: false\n  duration: 180.0\n- startTime: 1435611781000\n  endTime: 1435612520000\n  departureDelay: 0\n  arrivalDelay: 0\n  realTime: false\n  isNonExactFrequency: \n  headway: \n  distance: 955.1465276212646\n  from:\n    name: W Market At Adams St Ob\n    stopId:\n      agencyId: '210'\n      id: '765382'\n    stopCode: \n    platformCode: \n    lon: -76.76153755741935\n    lat: 39.953474753972856\n    arrival: 1435611780000\n    departure: 1435611781000\n    orig: \n    zoneId: \n    stopIndex: \n  to:\n    name: service road\n    stopId: \n    stopCode: \n    platformCode: \n    lon: -76.7633366\n    lat: 39.9591893\n    arrival: 1435612520000\n    departure: \n    orig: ''\n    zoneId: \n    stopIndex: \n  legGeometry:\n    points: elzrFrnosMEuAsCJkCNeBL{AJoADwAJsABsAFs@HwBNsCN@z@CFE@oCBJfEd@Al@AL@JDJJHLHN\n    levels: \n    length: 25\n  transitLeg: false\n  mode: WALK\n  route: ''\n  agencyName: \n  agencyUrl: \n  agencyTimeZoneOffset: -14400000\n  routeColor: \n  routeType: \n  routeId: \n  routeTextColor: \n  interlineWithPreviousLeg: false\n  tripShortName: \n  tripBlockId: \n  headsign: \n  agencyId: \n  tripId: \n  serviceDate: \n  intermediateStops: \n  steps:\n  - distance: 37.25237233764868\n    relativeDirection: DEPART\n    streetName: West Market Street\n    absoluteDirection: EAST\n    exit: \n    stayOn: false\n    area: false\n    bogusName: false\n    lon: -76.76153755741935\n    lat: 39.953474753972856\n    alerts: \n    elevation: []\n  - distance: 635.4486831604652\n    relativeDirection: LEFT\n    streetName: North Adams Street\n    absoluteDirection: NORTH\n    exit: \n    stayOn: false\n    area: false\n    bogusName: false\n    lon: -76.761102\n    lat: 39.9535023\n    alerts: \n    elevation: []\n  - distance: 282.44547212315075\n    relativeDirection: LEFT\n    streetName: service road\n    absoluteDirection: WEST\n    exit: \n    stayOn: false\n    area: false\n    bogusName: true\n    lon: -76.7617334\n    lat: 39.9591955\n    alerts: \n    elevation: []\n  notes: \n  alerts: \n  routeShortName: \n  routeLongName: \n  boardRule: \n  alightRule: \n  rentedBike: false\n  duration: 739.0\n","cost":"1.6","hidden":false,"created_at":"2015-06-26T20:57:17.451-04:00","updated_at":"2015-06-26T20:57:17.546-04:00","ride_count":null,"external_info":null,"match_score":-0.09999999999999998,"missing_information":false,"accommodation_mismatch":false,"missing_information_text":null,"date_mismatch":false,"time_mismatch":false,"too_late":false,"missing_accommodations":"","cost_comments":null,"selected":null,"start_time":"2015-06-29T16:25:06.000-04:00","end_time":"2015-06-29T17:15:20.000-04:00","is_bookable":false,"booking_confirmation":null,"duration_estimated":false,"map_image":{"url":null},"too_early":false,"returned_mode_code":"mode_transit","order_xml":null,"discounts":null,"segment_index":1,"start_location":{"address_components":[{"long_name":"701 Erlen Drive","short_name":"701 Erlen Drive","types":["street_address"]},{"long_name":"York","short_name":"York","types":["locality","political"]},{"long_name":"Pennsylvania","short_name":"Pennsylvania","types":["administrative_area_level_1","political"]},{"long_name":"17402","short_name":"17402","types":["postal_code"]}],"formatted_address":"701 Erlen Drive, York, Pennsylvania 17402","geometry":{"location":{"lat":39.964296,"lng":-76.678936}},"id":4718,"name":"East York Elementary School","scope":"user"},"end_location":{"address_components":[{"long_name":"1800 Bannister Street","short_name":"1800 Bannister Street","types":["street_address"]},{"long_name":"York","short_name":"York","types":["locality","political"]},{"long_name":"Pennsylvania","short_name":"Pennsylvania","types":["administrative_area_level_1","political"]},{"long_name":"17404","short_name":"17404","types":["postal_code"]}],"formatted_address":"1800 Bannister Street, York, Pennsylvania 17404","geometry":{"location":{"lat":39.958989,"lng":-76.763218}},"id":4717,"name":"West York Area High School","scope":"user"},"prebooking_questions":[{"question":"Will you be traveling with an approved escort","choices":[true,false],"code":"assistant"},{"question":"How many children or family members will be traveling with you?","choices":[0,1,2],"code":"children"}],"bookable":false,"json_legs":[{"startTime":1435609506000,"endTime":1435610099000,"departureDelay":0,"arrivalDelay":0,"realTime":false,"isNonExactFrequency":null,"headway":null,"distance":763.3969315504737,"from":{"name":"Erlen Drive","stopId":null,"stopCode":null,"platformCode":null,"lon":-76.67966600881111,"lat":39.96437079412677,"arrival":null,"departure":1435609506000,"orig":"","zoneId":null,"stopIndex":null},"to":{"name":"Haines Rd K-Mart","stopId":{"agencyId":"210","id":"765018"},"stopCode":null,"platformCode":null,"lon":-76.6832710419985,"lat":39.9597295760251,"arrival":1435610099000,"departure":1435610100000,"orig":null,"zoneId":null,"stopIndex":null},"legGeometry":{"points":"ip|rF|n_sM~Fj@`DF`DTWbFlCd@dCh@lATKdBBV\\|DA@","levels":null,"length":12},"transitLeg":false,"mode":"WALK","route":"","agencyName":null,"agencyUrl":null,"agencyTimeZoneOffset":-14400000,"routeColor":null,"routeType":null,"routeId":null,"routeTextColor":null,"interlineWithPreviousLeg":false,"tripShortName":null,"tripBlockId":null,"headsign":null,"agencyId":null,"tripId":null,"serviceDate":null,"intermediateStops":null,"steps":[{"distance":324.22113995854363,"relativeDirection":"DEPART","streetName":"Erlen Drive","absoluteDirection":"SOUTH","exit":null,"stayOn":false,"area":false,"bogusName":false,"lon":-76.67966600881111,"lat":39.96437079412677,"alerts":null,"elevation":[]},{"distance":98.53025812689052,"relativeDirection":"RIGHT","streetName":"Raleigh Drive","absoluteDirection":"WEST","exit":null,"stayOn":false,"area":false,"bogusName":false,"lon":-76.6800351,"lat":39.9614712,"alerts":null,"elevation":[]},{"distance":201.8719325153749,"relativeDirection":"LEFT","streetName":"Haines Road","absoluteDirection":"SOUTH","exit":null,"stayOn":false,"area":false,"bogusName":false,"lon":-76.68118,"lat":39.9615941,"alerts":null,"elevation":[]},{"distance":138.77360094966465,"relativeDirection":"RIGHT","streetName":"service road","absoluteDirection":"WEST","exit":null,"stayOn":false,"area":false,"bogusName":true,"lon":-76.6816898,"lat":39.9598213,"alerts":null,"elevation":[]}],"notes":null,"alerts":null,"routeShortName":null,"routeLongName":null,"boardRule":null,"alightRule":null,"rentedBike":false,"duration":593.0},{"startTime":1435610100000,"endTime":1435611600000,"departureDelay":0,"arrivalDelay":0,"realTime":false,"isNonExactFrequency":null,"headway":null,"distance":4999.767934170017,"from":{"name":"Haines Rd K-Mart","stopId":{"agencyId":"210","id":"765018"},"stopCode":null,"platformCode":null,"lon":-76.683279,"lat":39.959727,"arrival":1435610099000,"departure":1435610100000,"orig":null,"zoneId":"0","stopIndex":0},"to":{"name":"Transfer Center","stopId":{"agencyId":"210","id":"765237"},"stopCode":null,"platformCode":null,"lon":-76.731524,"lat":39.959945,"arrival":1435611600000,"departure":1435611600000,"orig":null,"zoneId":"0","stopIndex":16},"legGeometry":{"points":"is{rFne`sMBA]}DVyBpDt@`B`@LdGBhC@p@BlB?fA?pB?hDQbKOpBEjEOfGAp@i@zNAh@]nGY~Ha@lIEz@MpBQfEMtBC\\OfAm@dCoCjLCDyClMXhQb@bS??Bn@PvI@h@JrDFbD@jB@Zi@HYLq@^w@L_BSoAKeAEoCVS@uAb@aEjBmCrAaDbBRPTZDJFN`CnLFXf@hCR`ADNj@dD^bBZvAz@fEPt@Jf@^`B|@fE^fB^bBr@nDLf@A?hBhJzEqBtEmB\\xAfAG","levels":null,"length":83},"transitLeg":true,"mode":"BUS","route":"5E","agencyName":null,"agencyUrl":null,"agencyTimeZoneOffset":-14400000,"routeColor":"DB7093","routeType":3,"routeId":"1271","routeTextColor":"000000","interlineWithPreviousLeg":false,"tripShortName":null,"tripBlockId":null,"headsign":"5e Downtown","agencyId":"210","tripId":"54062A1024B1797","serviceDate":"20150629","intermediateStops":null,"steps":[],"notes":null,"alerts":null,"routeShortName":"5E","routeLongName":"Haines Rd  Kmart  Greensprings","boardRule":null,"alightRule":null,"rentedBike":false,"duration":1500.0},{"startTime":1435611600000,"endTime":1435611780000,"departureDelay":0,"arrivalDelay":0,"realTime":false,"isNonExactFrequency":null,"headway":null,"distance":2659.2172677762774,"from":{"name":"Transfer Center","stopId":{"agencyId":"210","id":"765237"},"stopCode":null,"platformCode":null,"lon":-76.731524,"lat":39.959945,"arrival":1435611600000,"departure":1435611600000,"orig":null,"zoneId":"0","stopIndex":0},"to":{"name":"W Market At Adams St Ob","stopId":{"agencyId":"210","id":"765382"},"stopCode":null,"platformCode":null,"lon":-76.761542,"lat":39.953545,"arrival":1435611780000,"departure":1435611781000,"orig":null,"zoneId":"0","stopIndex":2},"legGeometry":{"points":"as{rFprisMc@qBiCbAwAj@u@\\h@fCBN\\bBb@rBpApFlCxM`EdSxD~PbCfLn@~C\\zAH\\fEbS`BtHhA`F\\vBfAzFfAtFTlHVbKDzARtHDvA","levels":null,"length":28},"transitLeg":true,"mode":"BUS","route":"16","agencyName":null,"agencyUrl":null,"agencyTimeZoneOffset":-14400000,"routeColor":"D3D3D3","routeType":3,"routeId":"1273","routeTextColor":"000000","interlineWithPreviousLeg":false,"tripShortName":null,"tripBlockId":null,"headsign":"Hanover Spring Grove","agencyId":"210","tripId":"54128A1024B1797","serviceDate":"20150629","intermediateStops":null,"steps":[],"notes":null,"alerts":null,"routeShortName":"16","routeLongName":"York To Hanover","boardRule":null,"alightRule":null,"rentedBike":false,"duration":180.0},{"startTime":1435611781000,"endTime":1435612520000,"departureDelay":0,"arrivalDelay":0,"realTime":false,"isNonExactFrequency":null,"headway":null,"distance":955.1465276212646,"from":{"name":"W Market At Adams St Ob","stopId":{"agencyId":"210","id":"765382"},"stopCode":null,"platformCode":null,"lon":-76.76153755741935,"lat":39.953474753972856,"arrival":1435611780000,"departure":1435611781000,"orig":null,"zoneId":null,"stopIndex":null},"to":{"name":"service road","stopId":null,"stopCode":null,"platformCode":null,"lon":-76.7633366,"lat":39.9591893,"arrival":1435612520000,"departure":null,"orig":"","zoneId":null,"stopIndex":null},"legGeometry":{"points":"elzrFrnosMEuAsCJkCNeBL{AJoADwAJsABsAFs@HwBNsCN@z@CFE@oCBJfEd@Al@AL@JDJJHLHN","levels":null,"length":25},"transitLeg":false,"mode":"WALK","route":"","agencyName":null,"agencyUrl":null,"agencyTimeZoneOffset":-14400000,"routeColor":null,"routeType":null,"routeId":null,"routeTextColor":null,"interlineWithPreviousLeg":false,"tripShortName":null,"tripBlockId":null,"headsign":null,"agencyId":null,"tripId":null,"serviceDate":null,"intermediateStops":null,"steps":[{"distance":37.25237233764868,"relativeDirection":"DEPART","streetName":"West Market Street","absoluteDirection":"EAST","exit":null,"stayOn":false,"area":false,"bogusName":false,"lon":-76.76153755741935,"lat":39.953474753972856,"alerts":null,"elevation":[]},{"distance":635.4486831604652,"relativeDirection":"LEFT","streetName":"North Adams Street","absoluteDirection":"NORTH","exit":null,"stayOn":false,"area":false,"bogusName":false,"lon":-76.761102,"lat":39.9535023,"alerts":null,"elevation":[]},{"distance":282.44547212315075,"relativeDirection":"LEFT","streetName":"service road","absoluteDirection":"WEST","exit":null,"stayOn":false,"area":false,"bogusName":true,"lon":-76.7617334,"lat":39.9591955,"alerts":null,"elevation":[]}],"notes":null,"alerts":null,"routeShortName":null,"routeLongName":null,"boardRule":null,"alightRule":null,"rentedBike":false,"duration":739.0}]},{"id":14600,"trip_part_id":3698,"mode_id":1,"service_id":3,"server_status":200,"server_message":null,"duration":3086,"walk_time":779,"transit_time":2305,"wait_time":2,"walk_distance":997.8858845731818,"transfers":1,"count":null,"legs":"---\n- startTime: 1435607706000\n  endTime: 1435608299000\n  departureDelay: 0\n  arrivalDelay: 0\n  realTime: false\n  isNonExactFrequency: \n  headway: \n  distance: 763.3969315504737\n  from:\n    name: Erlen Drive\n    stopId: \n    stopCode: \n    platformCode: \n    lon: -76.67966600881111\n    lat: 39.96437079412677\n    arrival: \n    departure: 1435607706000\n    orig: ''\n    zoneId: \n    stopIndex: \n  to:\n    name: Haines Rd K-Mart\n    stopId:\n      agencyId: '210'\n      id: '765018'\n    stopCode: \n    platformCode: \n    lon: -76.6832710419985\n    lat: 39.9597295760251\n    arrival: 1435608299000\n    departure: 1435608300000\n    orig: \n    zoneId: \n    stopIndex: \n  legGeometry:\n    points: ip|rF|n_sM~Fj@`DF`DTWbFlCd@dCh@lATKdBBV\\|DA@\n    levels: \n    length: 12\n  transitLeg: false\n  mode: WALK\n  route: ''\n  agencyName: \n  agencyUrl: \n  agencyTimeZoneOffset: -14400000\n  routeColor: \n  routeType: \n  routeId: \n  routeTextColor: \n  interlineWithPreviousLeg: false\n  tripShortName: \n  tripBlockId: \n  headsign: \n  agencyId: \n  tripId: \n  serviceDate: \n  intermediateStops: \n  steps:\n  - distance: 324.22113995854363\n    relativeDirection: DEPART\n    streetName: Erlen Drive\n    absoluteDirection: SOUTH\n    exit: \n    stayOn: false\n    area: false\n    bogusName: false\n    lon: -76.67966600881111\n    lat: 39.96437079412677\n    alerts: \n    elevation: []\n  - distance: 98.53025812689052\n    relativeDirection: RIGHT\n    streetName: Raleigh Drive\n    absoluteDirection: WEST\n    exit: \n    stayOn: false\n    area: false\n    bogusName: false\n    lon: -76.6800351\n    lat: 39.9614712\n    alerts: \n    elevation: []\n  - distance: 201.8719325153749\n    relativeDirection: LEFT\n    streetName: Haines Road\n    absoluteDirection: SOUTH\n    exit: \n    stayOn: false\n    area: false\n    bogusName: false\n    lon: -76.68118\n    lat: 39.9615941\n    alerts: \n    elevation: []\n  - distance: 138.77360094966465\n    relativeDirection: RIGHT\n    streetName: service road\n    absoluteDirection: WEST\n    exit: \n    stayOn: false\n    area: false\n    bogusName: true\n    lon: -76.6816898\n    lat: 39.9598213\n    alerts: \n    elevation: []\n  notes: \n  alerts: \n  routeShortName: \n  routeLongName: \n  boardRule: \n  alightRule: \n  rentedBike: false\n  duration: 593.0\n- startTime: 1435608300000\n  endTime: 1435609800000\n  departureDelay: 0\n  arrivalDelay: 0\n  realTime: false\n  isNonExactFrequency: \n  headway: \n  distance: 4999.767934170017\n  from:\n    name: Haines Rd K-Mart\n    stopId:\n      agencyId: '210'\n      id: '765018'\n    stopCode: \n    platformCode: \n    lon: -76.683279\n    lat: 39.959727\n    arrival: 1435608299000\n    departure: 1435608300000\n    orig: \n    zoneId: '0'\n    stopIndex: 0\n  to:\n    name: Transfer Center\n    stopId:\n      agencyId: '210'\n      id: '765237'\n    stopCode: \n    platformCode: \n    lon: -76.731524\n    lat: 39.959945\n    arrival: 1435609800000\n    departure: 1435609800000\n    orig: \n    zoneId: '0'\n    stopIndex: 16\n  legGeometry:\n    points: is{rFne`sMBA]}DVyBpDt@`B`@LdGBhC@p@BlB?fA?pB?hDQbKOpBEjEOfGAp@i@zNAh@]nGY~Ha@lIEz@MpBQfEMtBC\\OfAm@dCoCjLCDyClMXhQb@bS??Bn@PvI@h@JrDFbD@jB@Zi@HYLq@^w@L_BSoAKeAEoCVS@uAb@aEjBmCrAaDbBRPTZDJFN`CnLFXf@hCR`ADNj@dD^bBZvAz@fEPt@Jf@^`B|@fE^fB^bBr@nDLf@A?hBhJzEqBtEmB\\xAfAG\n    levels: \n    length: 83\n  transitLeg: true\n  mode: BUS\n  route: 5E\n  agencyName: \n  agencyUrl: \n  agencyTimeZoneOffset: -14400000\n  routeColor: DB7093\n  routeType: 3\n  routeId: '1271'\n  routeTextColor: '000000'\n  interlineWithPreviousLeg: false\n  tripShortName: \n  tripBlockId: \n  headsign: 5e Downtown\n  agencyId: '210'\n  tripId: 54061A1024B1797\n  serviceDate: '20150629'\n  intermediateStops: \n  steps: []\n  notes: \n  alerts: \n  routeShortName: 5E\n  routeLongName: Haines Rd  Kmart  Greensprings\n  boardRule: \n  alightRule: \n  rentedBike: false\n  duration: 1500.0\n- startTime: 1435609800000\n  endTime: 1435610605000\n  departureDelay: 0\n  arrivalDelay: 0\n  realTime: false\n  isNonExactFrequency: \n  headway: \n  distance: 3454.556396043503\n  from:\n    name: Transfer Center\n    stopId:\n      agencyId: '210'\n      id: '765237'\n    stopCode: \n    platformCode: \n    lon: -76.731524\n    lat: 39.959945\n    arrival: 1435609800000\n    departure: 1435609800000\n    orig: \n    zoneId: '0'\n    stopIndex: 0\n  to:\n    name: Bannister At Seward Ob\n    stopId:\n      agencyId: '210'\n      id: '765385'\n    stopCode: \n    platformCode: \n    lon: -76.763942\n    lat: 39.960678\n    arrival: 1435610605000\n    departure: 1435610606000\n    orig: \n    zoneId: '0'\n    stopIndex: 13\n  legGeometry:\n    points: qt{rFxsisMz@?aDsOuHxC?A{Bx@cC`ALf@n@vCv@fEFVTfAb@tBx@pDBL`AlEFZrC~Lf@dCBNnCxMH`@hAtF`B~HP|@jB~IHZdC|KC@TrA_ApDwBvI@AEL]zAk@~Bi@pBs@nCo@lCm@|BIb@_@`Bk@dCEL}BrKRhHRfKTbK@V\n    levels: \n    length: 49\n  transitLeg: true\n  mode: BUS\n  route: 1W\n  agencyName: \n  agencyUrl: \n  agencyTimeZoneOffset: -14400000\n  routeColor: FF0000\n  routeType: 3\n  routeId: '1264'\n  routeTextColor: '000000'\n  interlineWithPreviousLeg: false\n  tripShortName: \n  tripBlockId: \n  headsign: W Manch Mall\n  agencyId: '210'\n  tripId: 53750A1024B1797\n  serviceDate: '20150629'\n  intermediateStops: \n  steps: []\n  notes: \n  alerts: \n  routeShortName: 1W\n  routeLongName: West Manchester Mall\n  boardRule: \n  alightRule: \n  rentedBike: false\n  duration: 805.0\n- startTime: 1435610606000\n  endTime: 1435610792000\n  departureDelay: 0\n  arrivalDelay: 0\n  realTime: false\n  isNonExactFrequency: \n  headway: \n  distance: 234.27681689841432\n  from:\n    name: Bannister At Seward Ob\n    stopId:\n      agencyId: '210'\n      id: '765385'\n    stopCode: \n    platformCode: \n    lon: -76.76394113800453\n    lat: 39.960662909175014\n    arrival: 1435610605000\n    departure: 1435610606000\n    orig: \n    zoneId: \n    stopIndex: \n  to:\n    name: service road\n    stopId: \n    stopCode: \n    platformCode: \n    lon: -76.7633366\n    lat: 39.9591893\n    arrival: 1435610792000\n    departure: \n    orig: ''\n    zoneId: \n    stopIndex: \n  legGeometry:\n    points: cy{rFt}osMAYt@A\\?TANAVCXGL?L?BLBJ@HDDHHH@H?H?FIHMJ]FSBQ?S?S\n    levels: \n    length: 25\n  transitLeg: false\n  mode: WALK\n  route: ''\n  agencyName: \n  agencyUrl: \n  agencyTimeZoneOffset: -14400000\n  routeColor: \n  routeType: \n  routeId: \n  routeTextColor: \n  interlineWithPreviousLeg: false\n  tripShortName: \n  tripBlockId: \n  headsign: \n  agencyId: \n  tripId: \n  serviceDate: \n  intermediateStops: \n  steps:\n  - distance: 10.609558098677711\n    relativeDirection: DEPART\n    streetName: Bannister Street\n    absoluteDirection: EAST\n    exit: \n    stayOn: false\n    area: false\n    bogusName: false\n    lon: -76.76394113800453\n    lat: 39.960662909175014\n    alerts: \n    elevation: []\n  - distance: 223.6672587997366\n    relativeDirection: RIGHT\n    streetName: service road\n    absoluteDirection: SOUTH\n    exit: \n    stayOn: false\n    area: false\n    bogusName: true\n    lon: -76.763817\n    lat: 39.96067\n    alerts: \n    elevation: []\n  notes: \n  alerts: \n  routeShortName: \n  routeLongName: \n  boardRule: \n  alightRule: \n  rentedBike: false\n  duration: 186.0\n","cost":"1.6","hidden":false,"created_at":"2015-06-26T20:57:17.479-04:00","updated_at":"2015-06-26T20:57:17.552-04:00","ride_count":null,"external_info":null,"match_score":2.7755575615628914e-17,"missing_information":false,"accommodation_mismatch":false,"missing_information_text":null,"date_mismatch":false,"time_mismatch":false,"too_late":false,"missing_accommodations":"","cost_comments":null,"selected":null,"start_time":"2015-06-29T15:55:06.000-04:00","end_time":"2015-06-29T16:46:32.000-04:00","is_bookable":false,"booking_confirmation":null,"duration_estimated":false,"map_image":{"url":null},"too_early":false,"returned_mode_code":"mode_transit","order_xml":null,"discounts":null,"segment_index":1,"start_location":{"address_components":[{"long_name":"701 Erlen Drive","short_name":"701 Erlen Drive","types":["street_address"]},{"long_name":"York","short_name":"York","types":["locality","political"]},{"long_name":"Pennsylvania","short_name":"Pennsylvania","types":["administrative_area_level_1","political"]},{"long_name":"17402","short_name":"17402","types":["postal_code"]}],"formatted_address":"701 Erlen Drive, York, Pennsylvania 17402","geometry":{"location":{"lat":39.964296,"lng":-76.678936}},"id":4718,"name":"East York Elementary School","scope":"user"},"end_location":{"address_components":[{"long_name":"1800 Bannister Street","short_name":"1800 Bannister Street","types":["street_address"]},{"long_name":"York","short_name":"York","types":["locality","political"]},{"long_name":"Pennsylvania","short_name":"Pennsylvania","types":["administrative_area_level_1","political"]},{"long_name":"17404","short_name":"17404","types":["postal_code"]}],"formatted_address":"1800 Bannister Street, York, Pennsylvania 17404","geometry":{"location":{"lat":39.958989,"lng":-76.763218}},"id":4717,"name":"West York Area High School","scope":"user"},"prebooking_questions":[{"question":"Will you be traveling with an approved escort","choices":[true,false],"code":"assistant"},{"question":"How many children or family members will be traveling with you?","choices":[0,1,2],"code":"children"}],"bookable":false,"json_legs":[{"startTime":1435607706000,"endTime":1435608299000,"departureDelay":0,"arrivalDelay":0,"realTime":false,"isNonExactFrequency":null,"headway":null,"distance":763.3969315504737,"from":{"name":"Erlen Drive","stopId":null,"stopCode":null,"platformCode":null,"lon":-76.67966600881111,"lat":39.96437079412677,"arrival":null,"departure":1435607706000,"orig":"","zoneId":null,"stopIndex":null},"to":{"name":"Haines Rd K-Mart","stopId":{"agencyId":"210","id":"765018"},"stopCode":null,"platformCode":null,"lon":-76.6832710419985,"lat":39.9597295760251,"arrival":1435608299000,"departure":1435608300000,"orig":null,"zoneId":null,"stopIndex":null},"legGeometry":{"points":"ip|rF|n_sM~Fj@`DF`DTWbFlCd@dCh@lATKdBBV\\|DA@","levels":null,"length":12},"transitLeg":false,"mode":"WALK","route":"","agencyName":null,"agencyUrl":null,"agencyTimeZoneOffset":-14400000,"routeColor":null,"routeType":null,"routeId":null,"routeTextColor":null,"interlineWithPreviousLeg":false,"tripShortName":null,"tripBlockId":null,"headsign":null,"agencyId":null,"tripId":null,"serviceDate":null,"intermediateStops":null,"steps":[{"distance":324.22113995854363,"relativeDirection":"DEPART","streetName":"Erlen Drive","absoluteDirection":"SOUTH","exit":null,"stayOn":false,"area":false,"bogusName":false,"lon":-76.67966600881111,"lat":39.96437079412677,"alerts":null,"elevation":[]},{"distance":98.53025812689052,"relativeDirection":"RIGHT","streetName":"Raleigh Drive","absoluteDirection":"WEST","exit":null,"stayOn":false,"area":false,"bogusName":false,"lon":-76.6800351,"lat":39.9614712,"alerts":null,"elevation":[]},{"distance":201.8719325153749,"relativeDirection":"LEFT","streetName":"Haines Road","absoluteDirection":"SOUTH","exit":null,"stayOn":false,"area":false,"bogusName":false,"lon":-76.68118,"lat":39.9615941,"alerts":null,"elevation":[]},{"distance":138.77360094966465,"relativeDirection":"RIGHT","streetName":"service road","absoluteDirection":"WEST","exit":null,"stayOn":false,"area":false,"bogusName":true,"lon":-76.6816898,"lat":39.9598213,"alerts":null,"elevation":[]}],"notes":null,"alerts":null,"routeShortName":null,"routeLongName":null,"boardRule":null,"alightRule":null,"rentedBike":false,"duration":593.0},{"startTime":1435608300000,"endTime":1435609800000,"departureDelay":0,"arrivalDelay":0,"realTime":false,"isNonExactFrequency":null,"headway":null,"distance":4999.767934170017,"from":{"name":"Haines Rd K-Mart","stopId":{"agencyId":"210","id":"765018"},"stopCode":null,"platformCode":null,"lon":-76.683279,"lat":39.959727,"arrival":1435608299000,"departure":1435608300000,"orig":null,"zoneId":"0","stopIndex":0},"to":{"name":"Transfer Center","stopId":{"agencyId":"210","id":"765237"},"stopCode":null,"platformCode":null,"lon":-76.731524,"lat":39.959945,"arrival":1435609800000,"departure":1435609800000,"orig":null,"zoneId":"0","stopIndex":16},"legGeometry":{"points":"is{rFne`sMBA]}DVyBpDt@`B`@LdGBhC@p@BlB?fA?pB?hDQbKOpBEjEOfGAp@i@zNAh@]nGY~Ha@lIEz@MpBQfEMtBC\\OfAm@dCoCjLCDyClMXhQb@bS??Bn@PvI@h@JrDFbD@jB@Zi@HYLq@^w@L_BSoAKeAEoCVS@uAb@aEjBmCrAaDbBRPTZDJFN`CnLFXf@hCR`ADNj@dD^bBZvAz@fEPt@Jf@^`B|@fE^fB^bBr@nDLf@A?hBhJzEqBtEmB\\xAfAG","levels":null,"length":83},"transitLeg":true,"mode":"BUS","route":"5E","agencyName":null,"agencyUrl":null,"agencyTimeZoneOffset":-14400000,"routeColor":"DB7093","routeType":3,"routeId":"1271","routeTextColor":"000000","interlineWithPreviousLeg":false,"tripShortName":null,"tripBlockId":null,"headsign":"5e Downtown","agencyId":"210","tripId":"54061A1024B1797","serviceDate":"20150629","intermediateStops":null,"steps":[],"notes":null,"alerts":null,"routeShortName":"5E","routeLongName":"Haines Rd  Kmart  Greensprings","boardRule":null,"alightRule":null,"rentedBike":false,"duration":1500.0},{"startTime":1435609800000,"endTime":1435610605000,"departureDelay":0,"arrivalDelay":0,"realTime":false,"isNonExactFrequency":null,"headway":null,"distance":3454.556396043503,"from":{"name":"Transfer Center","stopId":{"agencyId":"210","id":"765237"},"stopCode":null,"platformCode":null,"lon":-76.731524,"lat":39.959945,"arrival":1435609800000,"departure":1435609800000,"orig":null,"zoneId":"0","stopIndex":0},"to":{"name":"Bannister At Seward Ob","stopId":{"agencyId":"210","id":"765385"},"stopCode":null,"platformCode":null,"lon":-76.763942,"lat":39.960678,"arrival":1435610605000,"departure":1435610606000,"orig":null,"zoneId":"0","stopIndex":13},"legGeometry":{"points":"qt{rFxsisMz@?aDsOuHxC?A{Bx@cC`ALf@n@vCv@fEFVTfAb@tBx@pDBL`AlEFZrC~Lf@dCBNnCxMH`@hAtF`B~HP|@jB~IHZdC|KC@TrA_ApDwBvI@AEL]zAk@~Bi@pBs@nCo@lCm@|BIb@_@`Bk@dCEL}BrKRhHRfKTbK@V","levels":null,"length":49},"transitLeg":true,"mode":"BUS","route":"1W","agencyName":null,"agencyUrl":null,"agencyTimeZoneOffset":-14400000,"routeColor":"FF0000","routeType":3,"routeId":"1264","routeTextColor":"000000","interlineWithPreviousLeg":false,"tripShortName":null,"tripBlockId":null,"headsign":"W Manch Mall","agencyId":"210","tripId":"53750A1024B1797","serviceDate":"20150629","intermediateStops":null,"steps":[],"notes":null,"alerts":null,"routeShortName":"1W","routeLongName":"West Manchester Mall","boardRule":null,"alightRule":null,"rentedBike":false,"duration":805.0},{"startTime":1435610606000,"endTime":1435610792000,"departureDelay":0,"arrivalDelay":0,"realTime":false,"isNonExactFrequency":null,"headway":null,"distance":234.27681689841432,"from":{"name":"Bannister At Seward Ob","stopId":{"agencyId":"210","id":"765385"},"stopCode":null,"platformCode":null,"lon":-76.76394113800453,"lat":39.960662909175014,"arrival":1435610605000,"departure":1435610606000,"orig":null,"zoneId":null,"stopIndex":null},"to":{"name":"service road","stopId":null,"stopCode":null,"platformCode":null,"lon":-76.7633366,"lat":39.9591893,"arrival":1435610792000,"departure":null,"orig":"","zoneId":null,"stopIndex":null},"legGeometry":{"points":"cy{rFt}osMAYt@A\\?TANAVCXGL?L?BLBJ@HDDHHH@H?H?FIHMJ]FSBQ?S?S","levels":null,"length":25},"transitLeg":false,"mode":"WALK","route":"","agencyName":null,"agencyUrl":null,"agencyTimeZoneOffset":-14400000,"routeColor":null,"routeType":null,"routeId":null,"routeTextColor":null,"interlineWithPreviousLeg":false,"tripShortName":null,"tripBlockId":null,"headsign":null,"agencyId":null,"tripId":null,"serviceDate":null,"intermediateStops":null,"steps":[{"distance":10.609558098677711,"relativeDirection":"DEPART","streetName":"Bannister Street","absoluteDirection":"EAST","exit":null,"stayOn":false,"area":false,"bogusName":false,"lon":-76.76394113800453,"lat":39.960662909175014,"alerts":null,"elevation":[]},{"distance":223.6672587997366,"relativeDirection":"RIGHT","streetName":"service road","absoluteDirection":"SOUTH","exit":null,"stayOn":false,"area":false,"bogusName":true,"lon":-76.763817,"lat":39.96067,"alerts":null,"elevation":[]}],"notes":null,"alerts":null,"routeShortName":null,"routeLongName":null,"boardRule":null,"alightRule":null,"rentedBike":false,"duration":186.0}]}]}
